Workbook

Sheet README
B1: Client Environment Review - Assessment Workbook
B2: v1.1 - 5 Sep 2026 - blueAPACHE Portfolio Engineering (Bikash Shrestha). Companion to 'Client-Environment-Review-Method-and-Report-Template.docx'.
B4: What this is
B5: Purpose | C5: A repeatable, scored review of one client environment across 11 domains (124 controls) to find gaps, risks and improvement/billable opportunities. One workbook per client per review. Internal working tool - the client-ready output is the .docx report.
B6: Discharges (PE Handbook) | C6: Priority 5 (risks -> SDM & CAM), 13 (quarterly BAMS inclusions review), 14 (documentation currency), 15 (billable items -> eFO leads), quarterly technology/M365 health reporting (top-3 per customer per quarter).
B7: Baseline | C7: Security domains score against ACSC/ASD Essential Eight ML1 (target 2) with ML2 as 'optimised' (3). Other domains use vendor / bA best-practice checklists. E8 model version: last updated 27 Nov 2023 (cyber.gov.au), confirmed current 5 Sep 2026.
B9: How to run a review (about half a day for a baseline; 1-2 h for a quarterly refresh)
B10: 1. Client tab | C10: Fill the yellow cells. Mark domains out of scope. Note the E8 target agreed (or 'none yet').
B11: 2. Prep (30 min) | C11: Load PROFILE / STACK / COMMITMENTS / PROBLEMS / OPPORTUNITIES for the client, the last quarterly report, the BAMS inclusions PowerBI extract, and open the consoles you have access to (Lighthouse, Orion, N-Central, Veeam/vminfo, FortiManager, EDR, Huntress/Rapid7, SNOW).
B12: 3. Score (2-3 h) | C12: Checklist tab: for each control set Score (0-3 or N/A) using the rubric; record what you saw in 'Current state / evidence'. Unknown = 0 and a note. Skip nothing - N/A is a decision, blank is not.
B13: 4. Rate gaps | C13: For every row showing 'Gap': set Risk (H/M/L), Effort (S/M/L), confirm the Tag (BAU / Billable / Value-add / Client-owned), write a one-line Recommendation and an Owner. Priority and Quick-win compute automatically.
B14: 5. Read the roll-ups | C14: Summary = domain scorecard + Essential Eight indicative maturity + gap counts by tag. Findings = top 20 gaps ranked, plus the Top-3 for the quarter you choose. Roadmap = 30/90/180-day plan by ID.
B15: 6. Validate with the SDM (30 min) | C15: Scope, politics, what the client already knows, what is in flight. Adjust risk ratings; agree the Top-3.
B16: 7. File it | C16: Set 'Filed to' + Ref per gap: OPPORTUNITIES.md (business consequence), STACK debt register / verification backlog, PROBLEMS.md, SNOW ticket, eFO lead via SDM, or Risk notified (SDM+CAM). High risks must be notified in writing.
B17: 8. Write up | C17: Use the .docx template (Part B). Real client names only when the SDM confirms it is going out. This workbook holds identifiers - keep it local; sanitise per the client's sanitiser map before pasting anywhere.
B18: 9. Portfolio | C18: Copy the Summary 'Export strip' and the Checklist 'GapFlag' column into the master Portfolio tab for pattern hunting. A gap at 3+ clients is a service offering, not a client problem - raise with Head of PE / Presales.
B19: Quarterly refresh | C19: Re-score only: rows that were gaps, all COV rows, anything that changed (LOG.md), plus any control whose 'Last reviewed' is older than 6 months. Full pass annually or on handover / contract renewal / major incident.
B21: Scoring rubric
B22: 0 | C22: Absent or unknown - not implemented, or no evidence could be found. Unknown scores 0 until evidenced.
B23: 1 | C23: Partial or ad hoc - implemented for part of the scope, undocumented, unverified, or relies on one person.
B24: 2 | C24: Implemented and consistent - meets the target state across the in-scope estate; evidence sighted; documented. (Baseline / ~E8 ML1 where mapped)
B25: 3 | C25: Optimised - exceeds baseline, monitored and alerted, reviewed on a cadence, documented and owned. (~E8 ML2 where mapped - verify formally)
B26: N/A | C26: Not applicable to this client (e.g. no Azure, no on-prem AD). Excluded from percentages. Say why in the notes column.
B27: Target score | C27: Default 2 for every control (baseline). Raise to 3 for tier-1 systems or regulated clients; lower only with a documented reason. Gap = Score < Target.
B29: Priority (Risk x Effort) and tags
B30: Priority | C30: H+S=P1, H+M=P1, H+L=P2, M+S=P2, M+M=P2, M+L=P3, L+S=P3, L+M=P3, L+L=P4. Quick win = Gap with Effort S and Risk H or M. Risk is business consequence x likelihood in this client's context, not generic severity.
B31: BAU | C31: bA should already be delivering this under BAMS. A BAU gap is a service-delivery issue - fix it, do not sell it. Raise a SNOW ticket / Catalogue Task.
B32: Billable | C32: Out of BAMS scope; remediation is project or T&M work -> eFO lead via SDM (handbook: agreed remediation from technology reports is billable).
B33: Value-add | C33: Advice or a small fix done within the relationship. Builds trust; note the time in the Proactive subtask.
B34: Client-owned | C34: The client's responsibility (policy, budget, their vendor). bA advises and records the risk decision.
B36: Colour legend
B37: Yellow fill / blue text | C37: Input cells - you fill these.
B38: White, black text | C38: Formulas - leave alone. Hidden helper columns (RankKey, Attained, E8 *) feed Summary/Findings; do not delete.
B39: Green fill | C39: Tool status / Tool evidence - filled automatically from the AutoEvidence tab (CER-Discovery output). Read it, then write your own Current state line and score.
B40: Score cell colours | C40: 0 red, 1 orange, 2 light green, 3 green, N/A grey. Priority P1 red, P2 orange. RAG: Green >= 80% of target, Amber >= 50%, Red below (thresholds on Lists tab).
B42: Example of a completed row (format only - not real data)
B43: ID | C43: BDR-04
B44: Score | C44: 1 (partial - second copy exists but is not protected)
B45: Risk / Effort | C45: H / M -> Priority P1 (computed)
B46: Tag | C46: Billable
B47: Current state / evidence | C47: Veeam 12.1; second copy to emPOWER SYD but repository is domain-joined, no immutability; console login is a domain admin account without MFA. [VERIFIED] 05/09/2026 via Veeam console + RDM.
B48: Recommendation | C48: Hardened Linux repository with 14-day immutability, dedicated local backup-admin account, MFA on the console. ~2 days effort.
B49: Owner / Filed to / Ref | C49: bA / eFO lead (via SDM) / OPP-07, LEAD-12345
B51: Version log
B52: v1.1 - 05/09/2026 | C52: Added AutoEvidence tab and 'Tool status' / 'Tool evidence' columns on the Checklist, fed by CER-Discovery (New-CEREvidencePack -> AutoEvidence.csv). Summary gains a tool-coverage block. No changes to controls or scoring.
B53: v1.0 - 05/09/2026 | C53: Initial release. 11 domains, 124 controls. E8 mapping to ML1/ML2 (Nov 2023 model). Lifecycle anchors verified 05/09/2026: Microsoft Learn (Server 2016 EoS 12 Jan 2027; Server 2022 mainstream 13 Oct 2026; SQL 2016 EoS 14 Jul 2026; Win10/Office 2016-19/Exchange 2016-19 EoS 14 Oct 2025), Broadcom KB (vSphere 7 EoGS 2 Oct 2025), Fortinet docs (SSL-VPN tunnel mode removed 7.6.3), CA/B Forum SC-081 (TLS 200/100/47 days).

Sheet Client
B1: Client and review details
B2: Yellow cells are inputs. This sheet may hold real client identifiers - keep local; sanitise before sharing (sanitiser-maps/<alias>.json).
B4: Field | C4: Value | E4: Domain | F4: In scope? | G4: Scope note
B5: Client code | C5: C-0XX | E5: IAM - Identity & Access | F5: Yes
B6: Client alias | E6: M365 - Microsoft 365 & Email Security | F6: Yes
B7: Client name (real - local only) | E7: END - Endpoint | F7: Yes
B8: Sector / obligations | E8: SRV - Servers & Virtualisation | F8: Yes
B9: SDM | E9: NET - Network & Firewall | F9: Yes
B10: CAM / AM | E10: BDR - Backup & DR | F10: Yes
B11: Reviewer | C11: Bikash Shrestha | E11: COV - Monitoring, Patching & BAMS Coverage | F11: Yes
B12: Review date | C12: 46270 | E12: SEC - Security Programme & Essential Eight | F12: Yes
B13: Review type | C13: Baseline | E13: AZ - Azure & Cloud | F13: Yes
B14: Next review due | C14: =IF(ISNUMBER(C11),C11+91,"") | E14: DOC - Documentation & Operational Hygiene | F14: Yes
B15: Contract (BAMS tier / SoW ref) | E15: LIC - Lifecycle, Licensing & Commercial | F15: Yes
B16: Users (approx.)
B17: Sites | E17: If 'No': set every control in that domain to N/A on the Checklist so percentages exclude it.
B18: Servers (on-prem / emPOWER / Azure)
B19: M365 tenant(s) | E19: Evidence pulled (tick) | F19: Done | G19: Where / date
B20: Identity posture | C20: Hybrid - Entra Connect | E20: Client flow files (PROFILE/STACK/LOG/COMMITMENTS/PROBLEMS/OPPORTUNITIES)
B21: Security stack (EDR / MDR / gateway / app control) | E21: BAMS inclusions PowerBI extract
B22: Backup platform(s) | E22: Last quarterly / M365 health report
B23: Firewall / network platform | E23: Secure Score + Defender report
B24: Essential Eight target agreed | C24: None agreed | E24: Orion node list / N-Central patch + OS reports
B25: Last quarterly report date | E25: Veeam / vminfo backup status
B26: Notes / context from SDM | E26: FortiManager firmware + policy export
E27: EDR + Huntress/Rapid7 coverage
E28: SNOW: CIs, 90-day incidents, open problems
E29: Lifecycle lookups (MS Lifecycle, vendor EoS, warranty)

Sheet Checklist
A1: Client Environment Review - Checklist (v1.2)
A2: Score every row (0-3 or N/A). For each 'Gap' set Risk, Effort, Tag, Recommendation, Owner, Filed to. Yellow = input; green = pulled from the AutoEvidence tab (CER-Discovery). Hidden helper columns feed the roll-ups - do not delete. Filter by Dom to work one domain at a time.
A4: ID | B4: Dom | C4: Domain | D4: Control / check | E4: Why it matters | F4: Evidence source (bA tools) | G4: How to check | H4: Target state (baseline = score 2) | I4: E8 map | J4: Typical tag | K4: Target score | L4: Score (0-3 / N/A) | M4: Gap? | N4: Risk (H/M/L) | O4: Effort (S/M/L) | P4: Priority | Q4: Quick win | R4: Tag | S4: Tool status (auto) | T4: Tool evidence (auto, from CER-Discovery via AutoEvidence tab) | U4: Current state / evidence (what you saw, where, when) | V4: Recommendation | W4: Owner | X4: Filed to | Y4: Ref (ticket / lead / row) | Z4: Source tag | AA4: Last reviewed | AB4: GapFlag (copy to Portfolio) | AC4: RankKey | AD4: Attained | AE4: E8 PA | AF4: E8 PO | AG4: E8 MFA | AH4: E8 RAP | AI4: E8 AC | AJ4: E8 MAC | AK4: E8 UAH | AL4: E8 RB
A5: IAM-01 | B5: IAM | C5: Identity & Access | D5: Identity architecture documented and healthy (cloud-only / hybrid; Entra Connect or Cloud Sync; sync status) | E5: Everything else in identity depends on knowing where the source of truth is and that sync is not silently broken. | F5: Entra admin centre (via M365 Lighthouse) > Entra Connect / Cloud Sync health; STACK.md | G5: Confirm sync type and server, last sync < 1 h, zero export errors, staging server present or absence noted. Record in STACK.md. | H5: Documented in STACK.md; sync healthy; owner of the sync server known. | J5: BAU | K5: 2 | M5: =IF(ISNUMBER(L5),IF(L5<K5,"Gap","OK"),IF(L5="N/A","N/A","")) | P5: =IF(AND(M5="Gap",N5<>"",O5<>""),VLOOKUP(N5&O5,Lists!$H$4:$I$12,2,FALSE()),"") | Q5: =IF(AND(M5="Gap",O5="S",OR(N5="H",N5="M")),"Yes","") | R5: BAU | S5: =IF(A5="","",IFERROR(IF(OR(VLOOKUP(A5,AutoEvidence!$A$2:$G$400,2,FALSE())="Collected",VLOOKUP(A5,AutoEvidence!$A$2:$G$400,2,FALSE())="Partial"),VLOOKUP(A5,AutoEvidence!$A$2:$G$400,3,FALSE())&" ("&VLOOKUP(A5,AutoEvidence!$A$2:$G$400,2,FALSE())&")",VLOOKUP(A5,AutoEvidence!$A$2:$G$400,2,FALSE())),"")) | T5: =IF(A5="","",IFERROR(VLOOKUP(A5,AutoEvidence!$A$2:$G$400,4,FALSE())&"","")) | AB5: =IF(M5="Gap",1,IF(M5="OK",0,"")) | AC5: =IF(P5<>"",VALUE(RIGHT(P5,1))*1000+ROW(),"") | AD5: =IF(ISNUMBER(L5),MIN(L5,K5),"") | AE5: =IF(AND(ISNUMBER(SEARCH(" PA "," "&SUBSTITUTE($I5,","," ")&" ")),ISNUMBER($L5)),$L5,"") | AF5: =IF(AND(ISNUMBER(SEARCH(" PO "," "&SUBSTITUTE($I5,","," ")&" ")),ISNUMBER($L5)),$L5,"") | AG5: =IF(AND(ISNUMBER(SEARCH(" MFA "," "&SUBSTITUTE($I5,","," ")&" ")),ISNUMBER($L5)),$L5,"") | AH5: =IF(AND(ISNUMBER(SEARCH(" RAP "," "&SUBSTITUTE($I5,","," ")&" ")),ISNUMBER($L5)),$L5,"") | AI5: =IF(AND(ISNUMBER(SEARCH(" AC "," "&SUBSTITUTE($I5,","," ")&" ")),ISNUMBER($L5)),$L5,"") | AJ5: =IF(AND(ISNUMBER(SEARCH(" MAC "," "&SUBSTITUTE($I5,","," ")&" ")),ISNUMBER($L5)),$L5,"") | AK5: =IF(AND(ISNUMBER(SEARCH(" UAH "," "&SUBSTITUTE($I5,","," ")&" ")),ISNUMBER($L5)),$L5,"") | AL5: =IF(AND(ISNUMBER(SEARCH(" RB "," "&SUBSTITUTE($I5,","," ")&" ")),ISNUMBER($L5)),$L5,"")
A6: IAM-02 | B6: IAM | C6: Identity & Access | D6: MFA enforced for all users via Conditional Access (not legacy per-user MFA); registration coverage | E6: Commodity credential attacks are the #1 initial access path (E8 ML1 MFA). | F6: Entra > Conditional Access; Entra > Authentication methods > Registration report; Lighthouse 'Users without MFA' | G6: Policy requiring MFA for all users is On (not report-only); exclusions limited to break-glass and reviewed; % registered = 100%; no Security Defaults/per-user mix. | H6: 100% of enabled users registered and enforced through CA; exclusions documented. | I6: MFA | J6: BAU | K6: 2 | M6: =IF(ISNUMBER(L6),IF(L6<K6,"Gap","OK"),IF(L6="N/A","N/A","")) | P6: =IF(AND(M6="Gap",N6<>"",O6<>""),VLOOKUP(N6&O6,Lists!$H$4:$I$12,2,FALSE()),"") | Q6: =IF(AND(M6="Gap",O6="S",OR(N6="H",N6="M")),"Yes","") | R6: BAU | S6: =IF(A6="","",IFERROR(IF(OR(VLOOKUP(A6,AutoEvidence!$A$2:$G$400,2,FALSE())="Collected",VLOOKUP(A6,AutoEvidence!$A$2:$G$400,2,FALSE())="Partial"),VLOOKUP(A6,AutoEvidence!$A$2:$G$400,3,FALSE())&" ("&VLOOKUP(A6,AutoEvidence!$A$2:$G$400,2,FALSE())&")",VLOOKUP(A6,AutoEvidence!$A$2:$G$400,2,FALSE())),"")) | T6: =IF(A6="","",IFERROR(VLOOKUP(A6,AutoEvidence!$A$2:$G$400,4,FALSE())&"","")) | AB6: =IF(M6="Gap",1,IF(M6="OK",0,"")) | AC6: =IF(P6<>"",VALUE(RIGHT(P6,1))*1000+ROW(),"") | AD6: =IF(ISNUMBER(L6),MIN(L6,K6),"") | AE6: =IF(AND(ISNUMBER(SEARCH(" PA "," "&SUBSTITUTE($I6,","," ")&" ")),ISNUMBER($L6)),$L6,"") | AF6: =IF(AND(ISNUMBER(SEARCH(" PO "," "&SUBSTITUTE($I6,","," ")&" ")),ISNUMBER($L6)),$L6,"") | AG6: =IF(AND(ISNUMBER(SEARCH(" MFA "," "&SUBSTITUTE($I6,","," ")&" ")),ISNUMBER($L6)),$L6,"") | AH6: =IF(AND(ISNUMBER(SEARCH(" RAP "," "&SUBSTITUTE($I6,","," ")&" ")),ISNUMBER($L6)),$L6,"") | AI6: =IF(AND(ISNUMBER(SEARCH(" AC "," "&SUBSTITUTE($I6,","," ")&" ")),ISNUMBER($L6)),$L6,"") | AJ6: =IF(AND(ISNUMBER(SEARCH(" MAC "," "&SUBSTITUTE($I6,","," ")&" ")),ISNUMBER($L6)),$L6,"") | AK6: =IF(AND(ISNUMBER(SEARCH(" UAH "," "&SUBSTITUTE($I6,","," ")&" ")),ISNUMBER($L6)),$L6,"") | AL6: =IF(AND(ISNUMBER(SEARCH(" RB "," "&SUBSTITUTE($I6,","," ")&" ")),ISNUMBER($L6)),$L6,"")
A7: IAM-03 | B7: IAM | C7: Identity & Access | D7: Strong / phishing-resistant MFA for privileged users; weak methods (SMS/voice) disabled; number matching on | E7: E8 ML2 requires phishing-resistant MFA for privileged access; SMS/voice are trivially phished or SIM-swapped. | F7: Entra > Authentication methods policy; CA authentication strengths; admin sign-in logs | G7: Admins use FIDO2/passkeys/Windows Hello or certificate; auth-strength CA policy scoped to admin roles; SMS and voice disabled tenant-wide or scoped out. | H7: All admin roles behind phishing-resistant auth strength; SMS/voice off. | I7: MFA | J7: Value-add | K7: 2 | M7: =IF(ISNUMBER(L7),IF(L7<K7,"Gap","OK"),IF(L7="N/A","N/A","")) | P7: =IF(AND(M7="Gap",N7<>"",O7<>""),VLOOKUP(N7&O7,Lists!$H$4:$I$12,2,FALSE()),"") | Q7: =IF(AND(M7="Gap",O7="S",OR(N7="H",N7="M")),"Yes","") | R7: Value-add | S7: =IF(A7="","",IFERROR(IF(OR(VLOOKUP(A7,AutoEvidence!$A$2:$G$400,2,FALSE())="Collected",VLOOKUP(A7,AutoEvidence!$A$2:$G$400,2,FALSE())="Partial"),VLOOKUP(A7,AutoEvidence!$A$2:$G$400,3,FALSE())&" ("&VLOOKUP(A7,AutoEvidence!$A$2:$G$400,2,FALSE())&")",VLOOKUP(A7,AutoEvidence!$A$2:$G$400,2,FALSE())),"")) | T7: =IF(A7="","",IFERROR(VLOOKUP(A7,AutoEvidence!$A$2:$G$400,4,FALSE())&"","")) | AB7: =IF(M7="Gap",1,IF(M7="OK",0,"")) | AC7: =IF(P7<>"",VALUE(RIGHT(P7,1))*1000+ROW(),"") | AD7: =IF(ISNUMBER(L7),MIN(L7,K7),"") | AE7: =IF(AND(ISNUMBER(SEARCH(" PA "," "&SUBSTITUTE($I7,","," ")&" ")),ISNUMBER($L7)),$L7,"") | AF7: =IF(AND(ISNUMBER(SEARCH(" PO "," "&SUBSTITUTE($I7,","," ")&" ")),ISNUMBER($L7)),$L7,"") | AG7: =IF(AND(ISNUMBER(SEARCH(" MFA "," "&SUBSTITUTE($I7,","," ")&" ")),ISNUMBER($L7)),$L7,"") | AH7: =IF(AND(ISNUMBER(SEARCH(" RAP "," "&SUBSTITUTE($I7,","," ")&" ")),ISNUMBER($L7)),$L7,"") | AI7: =IF(AND(ISNUMBER(SEARCH(" AC "," "&SUBSTITUTE($I7,","," ")&" ")),ISNUMBER($L7)),$L7,"") | AJ7: =IF(AND(ISNUMBER(SEARCH(" MAC "," "&SUBSTITUTE($I7,","," ")&" ")),ISNUMBER($L7)),$L7,"") | AK7: =IF(AND(ISNUMBER(SEARCH(" UAH "," "&SUBSTITUTE($I7,","," ")&" ")),ISNUMBER($L7)),$L7,"") | AL7: =IF(AND(ISNUMBER(SEARCH(" RB "," "&SUBSTITUTE($I7,","," ")&" ")),ISNUMBER($L7)),$L7,"")
A8: IAM-04 | B8: IAM | C8: Identity & Access | D8: Legacy authentication blocked (CA block policy; basic auth off in Exchange Online) | E8: Legacy protocols bypass MFA entirely. | F8: CA policy 'Block legacy authentication'; Entra sign-in logs filtered by legacy client apps (30 days) | G8: Block policy On for all users/apps; sign-in log shows zero successful legacy sign-ins in 30 days; SMTP AUTH disabled except documented relays. | H8: Blocked; zero legacy successes in 30 days. | I8: MFA | J8: BAU | K8: 2 | M8: =IF(ISNUMBER(L8),IF(L8<K8,"Gap","OK"),IF(L8="N/A","N/A","")) | P8: =IF(AND(M8="Gap",N8<>"",O8<>""),VLOOKUP(N8&O8,Lists!$H$4:$I$12,2,FALSE()),"") | Q8: =IF(AND(M8="Gap",O8="S",OR(N8="H",N8="M")),"Yes","") | R8: BAU | S8: =IF(A8="","",IFERROR(IF(OR(VLOOKUP(A8,AutoEvidence!$A$2:$G$400,2,FALSE())="Collected",VLOOKUP(A8,AutoEvidence!$A$2:$G$400,2,FALSE())="Partial"),VLOOKUP(A8,AutoEvidence!$A$2:$G$400,3,FALSE())&" ("&VLOOKUP(A8,AutoEvidence!$A$2:$G$400,2,FALSE())&")",VLOOKUP(A8,AutoEvidence!$A$2:$G$400,2,FALSE())),"")) | T8: =IF(A8="","",IFERROR(VLOOKUP(A8,AutoEvidence!$A$2:$G$400,4,FALSE())&"","")) | AB8: =IF(M8="Gap",1,IF(M8="OK",0,"")) | AC8: =IF(P8<>"",VALUE(RIGHT(P8,1))*1000+ROW(),"") | AD8: =IF(ISNUMBER(L8),MIN(L8,K8),"") | AE8: =IF(AND(ISNUMBER(SEARCH(" PA "," "&SUBSTITUTE($I8,","," ")&" ")),ISNUMBER($L8)),$L8,"") | AF8: =IF(AND(ISNUMBER(SEARCH(" PO "," "&SUBSTITUTE($I8,","," ")&" ")),ISNUMBER($L8)),$L8,"") | AG8: =IF(AND(ISNUMBER(SEARCH(" MFA "," "&SUBSTITUTE($I8,","," ")&" ")),ISNUMBER($L8)),$L8,"") | AH8: =IF(AND(ISNUMBER(SEARCH(" RAP "," "&SUBSTITUTE($I8,","," ")&" ")),ISNUMBER($L8)),$L8,"") | AI8: =IF(AND(ISNUMBER(SEARCH(" AC "," "&SUBSTITUTE($I8,","," ")&" ")),ISNUMBER($L8)),$L8,"") | AJ8: =IF(AND(ISNUMBER(SEARCH(" MAC "," "&SUBSTITUTE($I8,","," ")&" ")),ISNUMBER($L8)),$L8,"") | AK8: =IF(AND(ISNUMBER(SEARCH(" UAH "," "&SUBSTITUTE($I8,","," ")&" ")),ISNUMBER($L8)),$L8,"") | AL8: =IF(AND(ISNUMBER(SEARCH(" RB "," "&SUBSTITUTE($I8,","," ")&" ")),ISNUMBER($L8)),$L8,"")
A9: IAM-05 | B9: IAM | C9: Identity & Access | D9: Privileged role hygiene: Global Admin count 2-4, dedicated cloud-only admin accounts, least-privilege roles, PIM/JIT where licensed | E9: Standing global admin on daily-driver accounts is the most common tenant-loss pattern (E8 RAP). | F9: Entra > Roles and administrators; Secure Score 'Designate fewer than 5 global admins'; PIM (P2) | G9: List all privileged role holders; check each is a dedicated account with no mailbox/licence, cloud-only, MFA strong; roles are least privilege; PIM eligible not permanent where P2 exists. | H9: 2-4 GAs; all admins dedicated accounts; least privilege roles; PIM if licensed. | I9: RAP | J9: BAU | K9: 2 | M9: =IF(ISNUMBER(L9),IF(L9<K9,"Gap","OK"),IF(L9="N/A","N/A","")) | P9: =IF(AND(M9="Gap",N9<>"",O9<>""),VLOOKUP(N9&O9,Lists!$H$4:$I$12,2,FALSE()),"") | Q9: =IF(AND(M9="Gap",O9="S",OR(N9="H",N9="M")),"Yes","") | R9: BAU | S9: =IF(A9="","",IFERROR(IF(OR(VLOOKUP(A9,AutoEvidence!$A$2:$G$400,2,FALSE())="Collected",VLOOKUP(A9,AutoEvidence!$A$2:$G$400,2,FALSE())="Partial"),VLOOKUP(A9,AutoEvidence!$A$2:$G$400,3,FALSE())&" ("&VLOOKUP(A9,AutoEvidence!$A$2:$G$400,2,FALSE())&")",VLOOKUP(A9,AutoEvidence!$A$2:$G$400,2,FALSE())),"")) | T9: =IF(A9="","",IFERROR(VLOOKUP(A9,AutoEvidence!$A$2:$G$400,4,FALSE())&"","")) | AB9: =IF(M9="Gap",1,IF(M9="OK",0,"")) | AC9: =IF(P9<>"",VALUE(RIGHT(P9,1))*1000+ROW(),"") | AD9: =IF(ISNUMBER(L9),MIN(L9,K9),"") | AE9: =IF(AND(ISNUMBER(SEARCH(" PA "," "&SUBSTITUTE($I9,","," ")&" ")),ISNUMBER($L9)),$L9,"") | AF9: =IF(AND(ISNUMBER(SEARCH(" PO "," "&SUBSTITUTE($I9,","," ")&" ")),ISNUMBER($L9)),$L9,"") | AG9: =IF(AND(ISNUMBER(SEARCH(" MFA "," "&SUBSTITUTE($I9,","," ")&" ")),ISNUMBER($L9)),$L9,"") | AH9: =IF(AND(ISNUMBER(SEARCH(" RAP "," "&SUBSTITUTE($I9,","," ")&" ")),ISNUMBER($L9)),$L9,"") | AI9: =IF(AND(ISNUMBER(SEARCH(" AC "," "&SUBSTITUTE($I9,","," ")&" ")),ISNUMBER($L9)),$L9,"") | AJ9: =IF(AND(ISNUMBER(SEARCH(" MAC "," "&SUBSTITUTE($I9,","," ")&" ")),ISNUMBER($L9)),$L9,"") | AK9: =IF(AND(ISNUMBER(SEARCH(" UAH "," "&SUBSTITUTE($I9,","," ")&" ")),ISNUMBER($L9)),$L9,"") | AL9: =IF(AND(ISNUMBER(SEARCH(" RB "," "&SUBSTITUTE($I9,","," ")&" ")),ISNUMBER($L9)),$L9,"")
A10: IAM-06 | B10: IAM | C10: Identity & Access | D10: Break-glass accounts: two exist, cloud-only, excluded from CA, credentials vaulted, sign-in alert configured | E10: Lock-out from a CA or MFA outage becomes a P1 without them; unmonitored ones are a backdoor. | F10: Entra users; CA exclusions; alert rule (Entra/Log Analytics/Sentinel or Huntress); CyberArk (if bA-held) | G10: Confirm both accounts, long random passwords stored securely (client vault or CyberArk safe), tested in last 6 months, alert on any sign-in. | H10: Two accounts, vaulted, alerting, tested. | I10: RAP | J10: Value-add | K10: 2 | M10: =IF(ISNUMBER(L10),IF(L10<K10,"Gap","OK"),IF(L10="N/A","N/A","")) | P10: =IF(AND(M10="Gap",N10<>"",O10<>""),VLOOKUP(N10&O10,Lists!$H$4:$I$12,2,FALSE()),"") | Q10: =IF(AND(M10="Gap",O10="S",OR(N10="H",N10="M")),"Yes","") | R10: Value-add | S10: =IF(A10="","",IFERROR(IF(OR(VLOOKUP(A10,AutoEvidence!$A$2:$G$400,2,FALSE())="Collected",VLOOKUP(A10,AutoEvidence!$A$2:$G$400,2,FALSE())="Partial"),VLOOKUP(A10,AutoEvidence!$A$2:$G$400,3,FALSE())&" ("&VLOOKUP(A10,AutoEvidence!$A$2:$G$400,2,FALSE())&")",VLOOKUP(A10,AutoEvidence!$A$2:$G$400,2,FALSE())),"")) | T10: =IF(A10="","",IFERROR(VLOOKUP(A10,AutoEvidence!$A$2:$G$400,4,FALSE())&"","")) | AB10: =IF(M10="Gap",1,IF(M10="OK",0,"")) | AC10: =IF(P10<>"",VALUE(RIGHT(P10,1))*1000+ROW(),"") | AD10: =IF(ISNUMBER(L10),MIN(L10,K10),"") | AE10: =IF(AND(ISNUMBER(SEARCH(" PA "," "&SUBSTITUTE($I10,","," ")&" ")),ISNUMBER($L10)),$L10,"") | AF10: =IF(AND(ISNUMBER(SEARCH(" PO "," "&SUBSTITUTE($I10,","," ")&" ")),ISNUMBER($L10)),$L10,"") | AG10: =IF(AND(ISNUMBER(SEARCH(" MFA "," "&SUBSTITUTE($I10,","," ")&" ")),ISNUMBER($L10)),$L10,"") | AH10: =IF(AND(ISNUMBER(SEARCH(" RAP "," "&SUBSTITUTE($I10,","," ")&" ")),ISNUMBER($L10)),$L10,"") | AI10: =IF(AND(ISNUMBER(SEARCH(" AC "," "&SUBSTITUTE($I10,","," ")&" ")),ISNUMBER($L10)),$L10,"") | AJ10: =IF(AND(ISNUMBER(SEARCH(" MAC "," "&SUBSTITUTE($I10,","," ")&" ")),ISNUMBER($L10)),$L10,"") | AK10: =IF(AND(ISNUMBER(SEARCH(" UAH "," "&SUBSTITUTE($I10,","," ")&" ")),ISNUMBER($L10)),$L10,"") | AL10: =IF(AND(ISNUMBER(SEARCH(" RB "," "&SUBSTITUTE($I10,","," ")&" ")),ISNUMBER($L10)),$L10,"")
A11: IAM-07 | B11: IAM | C11: Identity & Access | D11: Partner access is GDAP (not DAP) with least-privilege roles; bA access via Lighthouse named admin accounts; no shared customer admin accounts in CyberArk | E11: bA policy (KB0012228/KB0012557): named-account audit trail; shared accounts are an audit and insurance finding. | F11: M365 Lighthouse > Tenants > GDAP; Partner Center; CyberArk customer safe | G11: GDAP relationship active with expiry > 90 days, roles scoped; DAP removed; any stored customer-managed admin account has rotation + JIT safe or a plan to remove. | H11: GDAP least privilege; no DAP; no shared standing admin accounts. | I11: RAP | J11: BAU | K11: 2 | M11: =IF(ISNUMBER(L11),IF(L11<K11,"Gap","OK"),IF(L11="N/A","N/A","")) | P11: =IF(AND(M11="Gap",N11<>"",O11<>""),VLOOKUP(N11&O11,Lists!$H$4:$I$12,2,FALSE()),"") | Q11: =IF(AND(M11="Gap",O11="S",OR(N11="H",N11="M")),"Yes","") | R11: BAU | S11: =IF(A11="","",IFERROR(IF(OR(VLOOKUP(A11,AutoEvidence!$A$2:$G$400,2,FALSE())="Collected",VLOOKUP(A11,AutoEvidence!$A$2:$G$400,2,FALSE())="Partial"),VLOOKUP(A11,AutoEvidence!$A$2:$G$400,3,FALSE())&" ("&VLOOKUP(A11,AutoEvidence!$A$2:$G$400,2,FALSE())&")",VLOOKUP(A11,AutoEvidence!$A$2:$G$400,2,FALSE())),"")) | T11: =IF(A11="","",IFERROR(VLOOKUP(A11,AutoEvidence!$A$2:$G$400,4,FALSE())&"","")) | AB11: =IF(M11="Gap",1,IF(M11="OK",0,"")) | AC11: =IF(P11<>"",VALUE(RIGHT(P11,1))*1000+ROW(),"") | AD11: =IF(ISNUMBER(L11),MIN(L11,K11),"") | AE11: =IF(AND(ISNUMBER(SEARCH(" PA "," "&SUBSTITUTE($I11,","," ")&" ")),ISNUMBER($L11)),$L11,"") | AF11: =IF(AND(ISNUMBER(SEARCH(" PO "," "&SUBSTITUTE($I11,","," ")&" ")),ISNUMBER($L11)),$L11,"") | AG11: =IF(AND(ISNUMBER(SEARCH(" MFA "," "&SUBSTITUTE($I11,","," ")&" ")),ISNUMBER($L11)),$L11,"") | AH11: =IF(AND(ISNUMBER(SEARCH(" RAP "," "&SUBSTITUTE($I11,","," ")&" ")),ISNUMBER($L11)),$L11,"") | AI11: =IF(AND(ISNUMBER(SEARCH(" AC "," "&SUBSTITUTE($I11,","," ")&" ")),ISNUMBER($L11)),$L11,"") | AJ11: =IF(AND(ISNUMBER(SEARCH(" MAC "," "&SUBSTITUTE($I11,","," ")&" ")),ISNUMBER($L11)),$L11,"") | AK11: =IF(AND(ISNUMBER(SEARCH(" UAH "," "&SUBSTITUTE($I11,","," ")&" ")),ISNUMBER($L11)),$L11,"") | AL11: =IF(AND(ISNUMBER(SEARCH(" RB "," "&SUBSTITUTE($I11,","," ")&" ")),ISNUMBER($L11)),$L11,"")
A12: IAM-08 | B12: IAM | C12: Identity & Access | D12: Guest and external identity governance: stale guests removed, collaboration settings restricted, access reviews where licensed | E12: Guests accumulate silently and retain access to Teams/SharePoint data indefinitely. | F12: Entra > Users (guest filter, last sign-in); External collaboration settings; Access reviews (P2) | G12: Count guests with no sign-in > 90 days; guest invite setting restricted to admins/members; access reviews or a documented quarterly manual review. | H12: No guest inactive > 90 days; invite restricted; review cadence exists. | J12: Value-add | K12: 2 | M12: =IF(ISNUMBER(L12),IF(L12<K12,"Gap","OK"),IF(L12="N/A","N/A","")) | P12: =IF(AND(M12="Gap",N12<>"",O12<>""),VLOOKUP(N12&O12,Lists!$H$4:$I$12,2,FALSE()),"") | Q12: =IF(AND(M12="Gap",O12="S",OR(N12="H",N12="M")),"Yes","") | R12: Value-add | S12: =IF(A12="","",IFERROR(IF(OR(VLOOKUP(A12,AutoEvidence!$A$2:$G$400,2,FALSE())="Collected",VLOOKUP(A12,AutoEvidence!$A$2:$G$400,2,FALSE())="Partial"),VLOOKUP(A12,AutoEvidence!$A$2:$G$400,3,FALSE())&" ("&VLOOKUP(A12,AutoEvidence!$A$2:$G$400,2,FALSE())&")",VLOOKUP(A12,AutoEvidence!$A$2:$G$400,2,FALSE())),"")) | T12: =IF(A12="","",IFERROR(VLOOKUP(A12,AutoEvidence!$A$2:$G$400,4,FALSE())&"","")) | AB12: =IF(M12="Gap",1,IF(M12="OK",0,"")) | AC12: =IF(P12<>"",VALUE(RIGHT(P12,1))*1000+ROW(),"") | AD12: =IF(ISNUMBER(L12),MIN(L12,K12),"") | AE12: =IF(AND(ISNUMBER(SEARCH(" PA "," "&SUBSTITUTE($I12,","," ")&" ")),ISNUMBER($L12)),$L12,"") | AF12: =IF(AND(ISNUMBER(SEARCH(" PO "," "&SUBSTITUTE($I12,","," ")&" ")),ISNUMBER($L12)),$L12,"") | AG12: =IF(AND(ISNUMBER(SEARCH(" MFA "," "&SUBSTITUTE($I12,","," ")&" ")),ISNUMBER($L12)),$L12,"") | AH12: =IF(AND(ISNUMBER(SEARCH(" RAP "," "&SUBSTITUTE($I12,","," ")&" ")),ISNUMBER($L12)),$L12,"") | AI12: =IF(AND(ISNUMBER(SEARCH(" AC "," "&SUBSTITUTE($I12,","," ")&" ")),ISNUMBER($L12)),$L12,"") | AJ12: =IF(AND(ISNUMBER(SEARCH(" MAC "," "&SUBSTITUTE($I12,","," ")&" ")),ISNUMBER($L12)),$L12,"") | AK12: =IF(AND(ISNUMBER(SEARCH(" UAH "," "&SUBSTITUTE($I12,","," ")&" ")),ISNUMBER($L12)),$L12,"") | AL12: =IF(AND(ISNUMBER(SEARCH(" RB "," "&SUBSTITUTE($I12,","," ")&" ")),ISNUMBER($L12)),$L12,"")
A13: IAM-09 | B13: IAM | C13: Identity & Access | D13: Account lifecycle: stale users/computers disabled, JML (joiner-mover-leaver) process defined, service accounts inventoried with owners | E13: Leavers with live accounts and orphaned service accounts are the quiet way in. | F13: Entra sign-in activity; AD (Get-ADUser/Get-ADComputer LastLogonDate via RDM/N-Central script); SNOW KB for JML | G13: Users no sign-in > 90 days disabled/removed; computers > 90 days disabled; service account register exists (owner, purpose, password age, interactive logon denied). | H13: Stale objects < 2%; JML documented; service account register current. | I13: RAP | J13: BAU | K13: 2 | M13: =IF(ISNUMBER(L13),IF(L13<K13,"Gap","OK"),IF(L13="N/A","N/A","")) | P13: =IF(AND(M13="Gap",N13<>"",O13<>""),VLOOKUP(N13&O13,Lists!$H$4:$I$12,2,FALSE()),"") | Q13: =IF(AND(M13="Gap",O13="S",OR(N13="H",N13="M")),"Yes","") | R13: BAU | S13: =IF(A13="","",IFERROR(IF(OR(VLOOKUP(A13,AutoEvidence!$A$2:$G$400,2,FALSE())="Collected",VLOOKUP(A13,AutoEvidence!$A$2:$G$400,2,FALSE())="Partial"),VLOOKUP(A13,AutoEvidence!$A$2:$G$400,3,FALSE())&" ("&VLOOKUP(A13,AutoEvidence!$A$2:$G$400,2,FALSE())&")",VLOOKUP(A13,AutoEvidence!$A$2:$G$400,2,FALSE())),"")) | T13: =IF(A13="","",IFERROR(VLOOKUP(A13,AutoEvidence!$A$2:$G$400,4,FALSE())&"","")) | AB13: =IF(M13="Gap",1,IF(M13="OK",0,"")) | AC13: =IF(P13<>"",VALUE(RIGHT(P13,1))*1000+ROW(),"") | AD13: =IF(ISNUMBER(L13),MIN(L13,K13),"") | AE13: =IF(AND(ISNUMBER(SEARCH(" PA "," "&SUBSTITUTE($I13,","," ")&" ")),ISNUMBER($L13)),$L13,"") | AF13: =IF(AND(ISNUMBER(SEARCH(" PO "," "&SUBSTITUTE($I13,","," ")&" ")),ISNUMBER($L13)),$L13,"") | AG13: =IF(AND(ISNUMBER(SEARCH(" MFA "," "&SUBSTITUTE($I13,","," ")&" ")),ISNUMBER($L13)),$L13,"") | AH13: =IF(AND(ISNUMBER(SEARCH(" RAP "," "&SUBSTITUTE($I13,","," ")&" ")),ISNUMBER($L13)),$L13,"") | AI13: =IF(AND(ISNUMBER(SEARCH(" AC "," "&SUBSTITUTE($I13,","," ")&" ")),ISNUMBER($L13)),$L13,"") | AJ13: =IF(AND(ISNUMBER(SEARCH(" MAC "," "&SUBSTITUTE($I13,","," ")&" ")),ISNUMBER($L13)),$L13,"") | AK13: =IF(AND(ISNUMBER(SEARCH(" UAH "," "&SUBSTITUTE($I13,","," ")&" ")),ISNUMBER($L13)),$L13,"") | AL13: =IF(AND(ISNUMBER(SEARCH(" RB "," "&SUBSTITUTE($I13,","," ")&" ")),ISNUMBER($L13)),$L13,"")
A14: IAM-10 | B14: IAM | C14: Identity & Access | D14: On-prem AD DS health (if hybrid): supported DC OS, replication clean, FSMO/DNS sane, KRBTGT rotated, recycle bin on, legacy protocols disabled | E14: An unhealthy or unhardened AD undermines every cloud control and is the ransomware pivot point. | F14: RDM session to DC: dcdiag /q, repadmin /replsummary; AD Recycle Bin; KRBTGT pwdLastSet; GPO for SMBv1/NTLMv1/LDAP signing | G14: Zero replication errors; DC OS in support; KRBTGT reset < 180 days (twice, spaced); SMBv1 off; LDAP signing/channel binding required; Protected Users for tier-0 admins. | H14: Healthy replication, supported DCs, KRBTGT < 180 d, legacy protocols off. | I14: RAP, PO | J14: BAU | K14: 2 | M14: =IF(ISNUMBER(L14),IF(L14<K14,"Gap","OK"),IF(L14="N/A","N/A","")) | P14: =IF(AND(M14="Gap",N14<>"",O14<>""),VLOOKUP(N14&O14,Lists!$H$4:$I$12,2,FALSE()),"") | Q14: =IF(AND(M14="Gap",O14="S",OR(N14="H",N14="M")),"Yes","") | R14: BAU | S14: =IF(A14="","",IFERROR(IF(OR(VLOOKUP(A14,AutoEvidence!$A$2:$G$400,2,FALSE())="Collected",VLOOKUP(A14,AutoEvidence!$A$2:$G$400,2,FALSE())="Partial"),VLOOKUP(A14,AutoEvidence!$A$2:$G$400,3,FALSE())&" ("&VLOOKUP(A14,AutoEvidence!$A$2:$G$400,2,FALSE())&")",VLOOKUP(A14,AutoEvidence!$A$2:$G$400,2,FALSE())),"")) | T14: =IF(A14="","",IFERROR(VLOOKUP(A14,AutoEvidence!$A$2:$G$400,4,FALSE())&"","")) | AB14: =IF(M14="Gap",1,IF(M14="OK",0,"")) | AC14: =IF(P14<>"",VALUE(RIGHT(P14,1))*1000+ROW(),"") | AD14: =IF(ISNUMBER(L14),MIN(L14,K14),"") | AE14: =IF(AND(ISNUMBER(SEARCH(" PA "," "&SUBSTITUTE($I14,","," ")&" ")),ISNUMBER($L14)),$L14,"") | AF14: =IF(AND(ISNUMBER(SEARCH(" PO "," "&SUBSTITUTE($I14,","," ")&" ")),ISNUMBER($L14)),$L14,"") | AG14: =IF(AND(ISNUMBER(SEARCH(" MFA "," "&SUBSTITUTE($I14,","," ")&" ")),ISNUMBER($L14)),$L14,"") | AH14: =IF(AND(ISNUMBER(SEARCH(" RAP "," "&SUBSTITUTE($I14,","," ")&" ")),ISNUMBER($L14)),$L14,"") | AI14: =IF(AND(ISNUMBER(SEARCH(" AC "," "&SUBSTITUTE($I14,","," ")&" ")),ISNUMBER($L14)),$L14,"") | AJ14: =IF(AND(ISNUMBER(SEARCH(" MAC "," "&SUBSTITUTE($I14,","," ")&" ")),ISNUMBER($L14)),$L14,"") | AK14: =IF(AND(ISNUMBER(SEARCH(" UAH "," "&SUBSTITUTE($I14,","," ")&" ")),ISNUMBER($L14)),$L14,"") | AL14: =IF(AND(ISNUMBER(SEARCH(" RB "," "&SUBSTITUTE($I14,","," ")&" ")),ISNUMBER($L14)),$L14,"")
A15: IAM-11 | B15: IAM | C15: Identity & Access | D15: Credential policy: Entra Password Protection (incl. on-prem agent), sensible expiry policy, Windows LAPS for local admin passwords | E15: Reused/guessable passwords and shared local admin passwords enable lateral movement (E8 ML2: local admin creds unique and managed). | F15: Entra > Password protection; GPO/Intune LAPS policy; Intune > Devices > Local admin password | G15: Banned password list enforced (hybrid agent on DCs if AD); LAPS deployed to 100% of Windows devices and servers; policy on expiry documented and consistent with MFA posture. | H15: Password Protection on; LAPS on all Windows endpoints and member servers. | I15: RAP | J15: BAU | K15: 2 | M15: =IF(ISNUMBER(L15),IF(L15<K15,"Gap","OK"),IF(L15="N/A","N/A","")) | P15: =IF(AND(M15="Gap",N15<>"",O15<>""),VLOOKUP(N15&O15,Lists!$H$4:$I$12,2,FALSE()),"") | Q15: =IF(AND(M15="Gap",O15="S",OR(N15="H",N15="M")),"Yes","") | R15: BAU | S15: =IF(A15="","",IFERROR(IF(OR(VLOOKUP(A15,AutoEvidence!$A$2:$G$400,2,FALSE())="Collected",VLOOKUP(A15,AutoEvidence!$A$2:$G$400,2,FALSE())="Partial"),VLOOKUP(A15,AutoEvidence!$A$2:$G$400,3,FALSE())&" ("&VLOOKUP(A15,AutoEvidence!$A$2:$G$400,2,FALSE())&")",VLOOKUP(A15,AutoEvidence!$A$2:$G$400,2,FALSE())),"")) | T15: =IF(A15="","",IFERROR(VLOOKUP(A15,AutoEvidence!$A$2:$G$400,4,FALSE())&"","")) | AB15: =IF(M15="Gap",1,IF(M15="OK",0,"")) | AC15: =IF(P15<>"",VALUE(RIGHT(P15,1))*1000+ROW(),"") | AD15: =IF(ISNUMBER(L15),MIN(L15,K15),"") | AE15: =IF(AND(ISNUMBER(SEARCH(" PA "," "&SUBSTITUTE($I15,","," ")&" ")),ISNUMBER($L15)),$L15,"") | AF15: =IF(AND(ISNUMBER(SEARCH(" PO "," "&SUBSTITUTE($I15,","," ")&" ")),ISNUMBER($L15)),$L15,"") | AG15: =IF(AND(ISNUMBER(SEARCH(" MFA "," "&SUBSTITUTE($I15,","," ")&" ")),ISNUMBER($L15)),$L15,"") | AH15: =IF(AND(ISNUMBER(SEARCH(" RAP "," "&SUBSTITUTE($I15,","," ")&" ")),ISNUMBER($L15)),$L15,"") | AI15: =IF(AND(ISNUMBER(SEARCH(" AC "," "&SUBSTITUTE($I15,","," ")&" ")),ISNUMBER($L15)),$L15,"") | AJ15: =IF(AND(ISNUMBER(SEARCH(" MAC "," "&SUBSTITUTE($I15,","," ")&" ")),ISNUMBER($L15)),$L15,"") | AK15: =IF(AND(ISNUMBER(SEARCH(" UAH "," "&SUBSTITUTE($I15,","," ")&" ")),ISNUMBER($L15)),$L15,"") | AL15: =IF(AND(ISNUMBER(SEARCH(" RB "," "&SUBSTITUTE($I15,","," ")&" ")),ISNUMBER($L15)),$L15,"")
A16: IAM-12 | B16: IAM | C16: Identity & Access | D16: Conditional Access baseline: compliant/hybrid-joined device for corporate apps, unsupported platforms blocked, session controls for unmanaged devices, named locations | E16: MFA alone does not stop token theft or access from unmanaged devices. | F16: Entra > Conditional Access (policy list + CA insights workbook); Intune compliance | G16: Policies exist for: require compliant device (or app protection) for M365, block unsupported device platforms, sign-in frequency/no persistent browser for unmanaged; report-only policies not left indefinitely. | H16: Documented CA baseline with the four core policies enabled. | I16: MFA | J16: Value-add | K16: 2 | M16: =IF(ISNUMBER(L16),IF(L16<K16,"Gap","OK"),IF(L16="N/A","N/A","")) | P16: =IF(AND(M16="Gap",N16<>"",O16<>""),VLOOKUP(N16&O16,Lists!$H$4:$I$12,2,FALSE()),"") | Q16: =IF(AND(M16="Gap",O16="S",OR(N16="H",N16="M")),"Yes","") | R16: Value-add | S16: =IF(A16="","",IFERROR(IF(OR(VLOOKUP(A16,AutoEvidence!$A$2:$G$400,2,FALSE())="Collected",VLOOKUP(A16,AutoEvidence!$A$2:$G$400,2,FALSE())="Partial"),VLOOKUP(A16,AutoEvidence!$A$2:$G$400,3,FALSE())&" ("&VLOOKUP(A16,AutoEvidence!$A$2:$G$400,2,FALSE())&")",VLOOKUP(A16,AutoEvidence!$A$2:$G$400,2,FALSE())),"")) | T16: =IF(A16="","",IFERROR(VLOOKUP(A16,AutoEvidence!$A$2:$G$400,4,FALSE())&"","")) | AB16: =IF(M16="Gap",1,IF(M16="OK",0,"")) | AC16: =IF(P16<>"",VALUE(RIGHT(P16,1))*1000+ROW(),"") | AD16: =IF(ISNUMBER(L16),MIN(L16,K16),"") | AE16: =IF(AND(ISNUMBER(SEARCH(" PA "," "&SUBSTITUTE($I16,","," ")&" ")),ISNUMBER($L16)),$L16,"") | AF16: =IF(AND(ISNUMBER(SEARCH(" PO "," "&SUBSTITUTE($I16,","," ")&" ")),ISNUMBER($L16)),$L16,"") | AG16: =IF(AND(ISNUMBER(SEARCH(" MFA "," "&SUBSTITUTE($I16,","," ")&" ")),ISNUMBER($L16)),$L16,"") | AH16: =IF(AND(ISNUMBER(SEARCH(" RAP "," "&SUBSTITUTE($I16,","," ")&" ")),ISNUMBER($L16)),$L16,"") | AI16: =IF(AND(ISNUMBER(SEARCH(" AC "," "&SUBSTITUTE($I16,","," ")&" ")),ISNUMBER($L16)),$L16,"") | AJ16: =IF(AND(ISNUMBER(SEARCH(" MAC "," "&SUBSTITUTE($I16,","," ")&" ")),ISNUMBER($L16)),$L16,"") | AK16: =IF(AND(ISNUMBER(SEARCH(" UAH "," "&SUBSTITUTE($I16,","," ")&" ")),ISNUMBER($L16)),$L16,"") | AL16: =IF(AND(ISNUMBER(SEARCH(" RB "," "&SUBSTITUTE($I16,","," ")&" ")),ISNUMBER($L16)),$L16,"")
A17: IAM-13 | B17: IAM | C17: Identity & Access | D17: Identity Protection / risky sign-in handling (P2): risk policies enabled, risky users remediated, alerts routed to MDR/SOC | E17: Licensed detection that nobody watches is a paid-for gap. | F17: Entra > Protection > Identity Protection (risky users, risk policies); Huntress/Rapid7 alert routing | G17: If P2 licensed: user-risk and sign-in-risk CA policies enabled; risky users list at zero unremediated > 7 days; alerts reach a monitored queue. If not licensed: mark N/A and note in M365-10. | H17: Policies on; no unremediated risky users > 7 days; alerts monitored. | I17: MFA | J17: Value-add | K17: 2 | M17: =IF(ISNUMBER(L17),IF(L17<K17,"Gap","OK"),IF(L17="N/A","N/A","")) | P17: =IF(AND(M17="Gap",N17<>"",O17<>""),VLOOKUP(N17&O17,Lists!$H$4:$I$12,2,FALSE()),"") | Q17: =IF(AND(M17="Gap",O17="S",OR(N17="H",N17="M")),"Yes","") | R17: Value-add | S17: =IF(A17="","",IFERROR(IF(OR(VLOOKUP(A17,AutoEvidence!$A$2:$G$400,2,FALSE())="Collected",VLOOKUP(A17,AutoEvidence!$A$2:$G$400,2,FALSE())="Partial"),VLOOKUP(A17,AutoEvidence!$A$2:$G$400,3,FALSE())&" ("&VLOOKUP(A17,AutoEvidence!$A$2:$G$400,2,FALSE())&")",VLOOKUP(A17,AutoEvidence!$A$2:$G$400,2,FALSE())),"")) | T17: =IF(A17="","",IFERROR(VLOOKUP(A17,AutoEvidence!$A$2:$G$400,4,FALSE())&"","")) | AB17: =IF(M17="Gap",1,IF(M17="OK",0,"")) | AC17: =IF(P17<>"",VALUE(RIGHT(P17,1))*1000+ROW(),"") | AD17: =IF(ISNUMBER(L17),MIN(L17,K17),"") | AE17: =IF(AND(ISNUMBER(SEARCH(" PA "," "&SUBSTITUTE($I17,","," ")&" ")),ISNUMBER($L17)),$L17,"") | AF17: =IF(AND(ISNUMBER(SEARCH(" PO "," "&SUBSTITUTE($I17,","," ")&" ")),ISNUMBER($L17)),$L17,"") | AG17: =IF(AND(ISNUMBER(SEARCH(" MFA "," "&SUBSTITUTE($I17,","," ")&" ")),ISNUMBER($L17)),$L17,"") | AH17: =IF(AND(ISNUMBER(SEARCH(" RAP "," "&SUBSTITUTE($I17,","," ")&" ")),ISNUMBER($L17)),$L17,"") | AI17: =IF(AND(ISNUMBER(SEARCH(" AC "," "&SUBSTITUTE($I17,","," ")&" ")),ISNUMBER($L17)),$L17,"") | AJ17: =IF(AND(ISNUMBER(SEARCH(" MAC "," "&SUBSTITUTE($I17,","," ")&" ")),ISNUMBER($L17)),$L17,"") | AK17: =IF(AND(ISNUMBER(SEARCH(" UAH "," "&SUBSTITUTE($I17,","," ")&" ")),ISNUMBER($L17)),$L17,"") | AL17: =IF(AND(ISNUMBER(SEARCH(" RB "," "&SUBSTITUTE($I17,","," ")&" ")),ISNUMBER($L17)),$L17,"")
A18: IAM-14 | B18: IAM | C18: Identity & Access | D18: SaaS SSO coverage and app consent governance: key apps behind Entra SSO; user consent to unverified apps blocked; admin consent workflow | E18: OAuth consent phishing and orphaned SaaS logins bypass every device and MFA control. | F18: Entra > Enterprise applications; Consent and permissions settings; Secure Score item | G18: User consent set to 'verified publishers, low-impact' or disabled; admin consent workflow enabled with named approvers; top 10 business SaaS apps use SSO. | H18: Consent restricted; workflow on; critical SaaS on SSO. | J18: Value-add | K18: 2 | M18: =IF(ISNUMBER(L18),IF(L18<K18,"Gap","OK"),IF(L18="N/A","N/A","")) | P18: =IF(AND(M18="Gap",N18<>"",O18<>""),VLOOKUP(N18&O18,Lists!$H$4:$I$12,2,FALSE()),"") | Q18: =IF(AND(M18="Gap",O18="S",OR(N18="H",N18="M")),"Yes","") | R18: Value-add | S18: =IF(A18="","",IFERROR(IF(OR(VLOOKUP(A18,AutoEvidence!$A$2:$G$400,2,FALSE())="Collected",VLOOKUP(A18,AutoEvidence!$A$2:$G$400,2,FALSE())="Partial"),VLOOKUP(A18,AutoEvidence!$A$2:$G$400,3,FALSE())&" ("&VLOOKUP(A18,AutoEvidence!$A$2:$G$400,2,FALSE())&")",VLOOKUP(A18,AutoEvidence!$A$2:$G$400,2,FALSE())),"")) | T18: =IF(A18="","",IFERROR(VLOOKUP(A18,AutoEvidence!$A$2:$G$400,4,FALSE())&"","")) | AB18: =IF(M18="Gap",1,IF(M18="OK",0,"")) | AC18: =IF(P18<>"",VALUE(RIGHT(P18,1))*1000+ROW(),"") | AD18: =IF(ISNUMBER(L18),MIN(L18,K18),"") | AE18: =IF(AND(ISNUMBER(SEARCH(" PA "," "&SUBSTITUTE($I18,","," ")&" ")),ISNUMBER($L18)),$L18,"") | AF18: =IF(AND(ISNUMBER(SEARCH(" PO "," "&SUBSTITUTE($I18,","," ")&" ")),ISNUMBER($L18)),$L18,"") | AG18: =IF(AND(ISNUMBER(SEARCH(" MFA "," "&SUBSTITUTE($I18,","," ")&" ")),ISNUMBER($L18)),$L18,"") | AH18: =IF(AND(ISNUMBER(SEARCH(" RAP "," "&SUBSTITUTE($I18,","," ")&" ")),ISNUMBER($L18)),$L18,"") | AI18: =IF(AND(ISNUMBER(SEARCH(" AC "," "&SUBSTITUTE($I18,","," ")&" ")),ISNUMBER($L18)),$L18,"") | AJ18: =IF(AND(ISNUMBER(SEARCH(" MAC "," "&SUBSTITUTE($I18,","," ")&" ")),ISNUMBER($L18)),$L18,"") | AK18: =IF(AND(ISNUMBER(SEARCH(" UAH "," "&SUBSTITUTE($I18,","," ")&" ")),ISNUMBER($L18)),$L18,"") | AL18: =IF(AND(ISNUMBER(SEARCH(" RB "," "&SUBSTITUTE($I18,","," ")&" ")),ISNUMBER($L18)),$L18,"")
A19: M365-01 | B19: M365 | C19: Microsoft 365 & Email Security | D19: Tenant baseline: Microsoft Secure Score tracked, top actions actioned or formally risk-accepted, quarterly M365 Health Report top-3 closed | E19: Handbook expects top-3 priorities per customer per quarter; Secure Score is the shared yardstick with the client. | F19: Defender portal > Secure Score (via Lighthouse); last quarterly M365 Health Report; LOG.md | G19: Record score % and 90-day trend; check last quarter's top-3 status; alternatively-mitigated items marked in portal so they drop off future reports. | H19: Score trending up; last quarter's top-3 closed or re-planned with dates. | J19: BAU | K19: 2 | M19: =IF(ISNUMBER(L19),IF(L19<K19,"Gap","OK"),IF(L19="N/A","N/A","")) | P19: =IF(AND(M19="Gap",N19<>"",O19<>""),VLOOKUP(N19&O19,Lists!$H$4:$I$12,2,FALSE()),"") | Q19: =IF(AND(M19="Gap",O19="S",OR(N19="H",N19="M")),"Yes","") | R19: BAU | S19: =IF(A19="","",IFERROR(IF(OR(VLOOKUP(A19,AutoEvidence!$A$2:$G$400,2,FALSE())="Collected",VLOOKUP(A19,AutoEvidence!$A$2:$G$400,2,FALSE())="Partial"),VLOOKUP(A19,AutoEvidence!$A$2:$G$400,3,FALSE())&" ("&VLOOKUP(A19,AutoEvidence!$A$2:$G$400,2,FALSE())&")",VLOOKUP(A19,AutoEvidence!$A$2:$G$400,2,FALSE())),"")) | T19: =IF(A19="","",IFERROR(VLOOKUP(A19,AutoEvidence!$A$2:$G$400,4,FALSE())&"","")) | AB19: =IF(M19="Gap",1,IF(M19="OK",0,"")) | AC19: =IF(P19<>"",VALUE(RIGHT(P19,1))*1000+ROW(),"") | AD19: =IF(ISNUMBER(L19),MIN(L19,K19),"") | AE19: =IF(AND(ISNUMBER(SEARCH(" PA "," "&SUBSTITUTE($I19,","," ")&" ")),ISNUMBER($L19)),$L19,"") | AF19: =IF(AND(ISNUMBER(SEARCH(" PO "," "&SUBSTITUTE($I19,","," ")&" ")),ISNUMBER($L19)),$L19,"") | AG19: =IF(AND(ISNUMBER(SEARCH(" MFA "," "&SUBSTITUTE($I19,","," ")&" ")),ISNUMBER($L19)),$L19,"") | AH19: =IF(AND(ISNUMBER(SEARCH(" RAP "," "&SUBSTITUTE($I19,","," ")&" ")),ISNUMBER($L19)),$L19,"") | AI19: =IF(AND(ISNUMBER(SEARCH(" AC "," "&SUBSTITUTE($I19,","," ")&" ")),ISNUMBER($L19)),$L19,"") | AJ19: =IF(AND(ISNUMBER(SEARCH(" MAC "," "&SUBSTITUTE($I19,","," ")&" ")),ISNUMBER($L19)),$L19,"") | AK19: =IF(AND(ISNUMBER(SEARCH(" UAH "," "&SUBSTITUTE($I19,","," ")&" ")),ISNUMBER($L19)),$L19,"") | AL19: =IF(AND(ISNUMBER(SEARCH(" RB "," "&SUBSTITUTE($I19,","," ")&" ")),ISNUMBER($L19)),$L19,"")
A20: M365-02 | B20: M365 | C20: Microsoft 365 & Email Security | D20: Email authentication: SPF (single record, < 10 lookups, -all), DKIM on all sending domains and third-party senders, DMARC at quarantine/reject with reporting | E20: Spoofing of the client's own domain drives BEC losses; DMARC p=none is not protection. | F20: mxtoolbox / dmarcian; EXO > DKIM; Mimecast DKIM signing; DNS (EasyDNS) | G20: Check every owned/sending domain: SPF valid and hard-fail, DKIM selectors live (M365 + Mimecast + marketing/ERP senders), DMARC policy and rua address monitored. Note parked domains lacking null SPF/DMARC. | H20: All domains SPF -all, DKIM aligned, DMARC p=quarantine or reject with reports reviewed. | J20: Value-add | K20: 2 | M20: =IF(ISNUMBER(L20),IF(L20<K20,"Gap","OK"),IF(L20="N/A","N/A","")) | P20: =IF(AND(M20="Gap",N20<>"",O20<>""),VLOOKUP(N20&O20,Lists!$H$4:$I$12,2,FALSE()),"") | Q20: =IF(AND(M20="Gap",O20="S",OR(N20="H",N20="M")),"Yes","") | R20: Value-add | S20: =IF(A20="","",IFERROR(IF(OR(VLOOKUP(A20,AutoEvidence!$A$2:$G$400,2,FALSE())="Collected",VLOOKUP(A20,AutoEvidence!$A$2:$G$400,2,FALSE())="Partial"),VLOOKUP(A20,AutoEvidence!$A$2:$G$400,3,FALSE())&" ("&VLOOKUP(A20,AutoEvidence!$A$2:$G$400,2,FALSE())&")",VLOOKUP(A20,AutoEvidence!$A$2:$G$400,2,FALSE())),"")) | T20: =IF(A20="","",IFERROR(VLOOKUP(A20,AutoEvidence!$A$2:$G$400,4,FALSE())&"","")) | AB20: =IF(M20="Gap",1,IF(M20="OK",0,"")) | AC20: =IF(P20<>"",VALUE(RIGHT(P20,1))*1000+ROW(),"") | AD20: =IF(ISNUMBER(L20),MIN(L20,K20),"") | AE20: =IF(AND(ISNUMBER(SEARCH(" PA "," "&SUBSTITUTE($I20,","," ")&" ")),ISNUMBER($L20)),$L20,"") | AF20: =IF(AND(ISNUMBER(SEARCH(" PO "," "&SUBSTITUTE($I20,","," ")&" ")),ISNUMBER($L20)),$L20,"") | AG20: =IF(AND(ISNUMBER(SEARCH(" MFA "," "&SUBSTITUTE($I20,","," ")&" ")),ISNUMBER($L20)),$L20,"") | AH20: =IF(AND(ISNUMBER(SEARCH(" RAP "," "&SUBSTITUTE($I20,","," ")&" ")),ISNUMBER($L20)),$L20,"") | AI20: =IF(AND(ISNUMBER(SEARCH(" AC "," "&SUBSTITUTE($I20,","," ")&" ")),ISNUMBER($L20)),$L20,"") | AJ20: =IF(AND(ISNUMBER(SEARCH(" MAC "," "&SUBSTITUTE($I20,","," ")&" ")),ISNUMBER($L20)),$L20,"") | AK20: =IF(AND(ISNUMBER(SEARCH(" UAH "," "&SUBSTITUTE($I20,","," ")&" ")),ISNUMBER($L20)),$L20,"") | AL20: =IF(AND(ISNUMBER(SEARCH(" RB "," "&SUBSTITUTE($I20,","," ")&" ")),ISNUMBER($L20)),$L20,"")
A21: M365-03 | B21: M365 | C21: Microsoft 365 & Email Security | D21: Inbound mail protection: Mimecast or Defender for Office 365 with impersonation/anti-phish, Safe Links/Attachments (or URL Protect/Attachment Protect), connectors locked to the gateway | E21: Email remains the top delivery channel; an open EXO connector lets attackers bypass the gateway. | F21: Mimecast console; Defender > Email & collaboration > Policies (Preset security policies); EXO inbound connectors | G21: Preset Standard/Strict or equivalent Mimecast policies applied to all users; impersonation protection lists executives and domains; if Mimecast, EXO only accepts mail from Mimecast IPs; enhanced filtering configured. | H21: Gateway policies on for all users; MX bypass closed. | J21: BAU | K21: 2 | M21: =IF(ISNUMBER(L21),IF(L21<K21,"Gap","OK"),IF(L21="N/A","N/A","")) | P21: =IF(AND(M21="Gap",N21<>"",O21<>""),VLOOKUP(N21&O21,Lists!$H$4:$I$12,2,FALSE()),"") | Q21: =IF(AND(M21="Gap",O21="S",OR(N21="H",N21="M")),"Yes","") | R21: BAU | S21: =IF(A21="","",IFERROR(IF(OR(VLOOKUP(A21,AutoEvidence!$A$2:$G$400,2,FALSE())="Collected",VLOOKUP(A21,AutoEvidence!$A$2:$G$400,2,FALSE())="Partial"),VLOOKUP(A21,AutoEvidence!$A$2:$G$400,3,FALSE())&" ("&VLOOKUP(A21,AutoEvidence!$A$2:$G$400,2,FALSE())&")",VLOOKUP(A21,AutoEvidence!$A$2:$G$400,2,FALSE())),"")) | T21: =IF(A21="","",IFERROR(VLOOKUP(A21,AutoEvidence!$A$2:$G$400,4,FALSE())&"","")) | AB21: =IF(M21="Gap",1,IF(M21="OK",0,"")) | AC21: =IF(P21<>"",VALUE(RIGHT(P21,1))*1000+ROW(),"") | AD21: =IF(ISNUMBER(L21),MIN(L21,K21),"") | AE21: =IF(AND(ISNUMBER(SEARCH(" PA "," "&SUBSTITUTE($I21,","," ")&" ")),ISNUMBER($L21)),$L21,"") | AF21: =IF(AND(ISNUMBER(SEARCH(" PO "," "&SUBSTITUTE($I21,","," ")&" ")),ISNUMBER($L21)),$L21,"") | AG21: =IF(AND(ISNUMBER(SEARCH(" MFA "," "&SUBSTITUTE($I21,","," ")&" ")),ISNUMBER($L21)),$L21,"") | AH21: =IF(AND(ISNUMBER(SEARCH(" RAP "," "&SUBSTITUTE($I21,","," ")&" ")),ISNUMBER($L21)),$L21,"") | AI21: =IF(AND(ISNUMBER(SEARCH(" AC "," "&SUBSTITUTE($I21,","," ")&" ")),ISNUMBER($L21)),$L21,"") | AJ21: =IF(AND(ISNUMBER(SEARCH(" MAC "," "&SUBSTITUTE($I21,","," ")&" ")),ISNUMBER($L21)),$L21,"") | AK21: =IF(AND(ISNUMBER(SEARCH(" UAH "," "&SUBSTITUTE($I21,","," ")&" ")),ISNUMBER($L21)),$L21,"") | AL21: =IF(AND(ISNUMBER(SEARCH(" RB "," "&SUBSTITUTE($I21,","," ")&" ")),ISNUMBER($L21)),$L21,"")
A22: M365-04 | B22: M365 | C22: Microsoft 365 & Email Security | D22: Mailbox hygiene: external auto-forwarding blocked, forwarding report clean, mailbox auditing on, shared mailboxes sign-in blocked, inactive licensed mailboxes reviewed | E22: Auto-forward rules are the classic post-compromise persistence; inactive licensed mailboxes are pure waste. | F22: EXO > Outbound spam policy (auto-forward); Mail flow > Auto-forwarded messages report; Get-Mailbox audit; M365 usage reports | G22: Automatic forwarding = Off in outbound spam policy; review forwarding report for rules to external domains; shared mailboxes have sign-in blocked; list mailboxes inactive > 90 days still licensed. | H22: Forwarding blocked; no unexplained external forwards; shared mailbox sign-in blocked. | J22: BAU | K22: 2 | M22: =IF(ISNUMBER(L22),IF(L22<K22,"Gap","OK"),IF(L22="N/A","N/A","")) | P22: =IF(AND(M22="Gap",N22<>"",O22<>""),VLOOKUP(N22&O22,Lists!$H$4:$I$12,2,FALSE()),"") | Q22: =IF(AND(M22="Gap",O22="S",OR(N22="H",N22="M")),"Yes","") | R22: BAU | S22: =IF(A22="","",IFERROR(IF(OR(VLOOKUP(A22,AutoEvidence!$A$2:$G$400,2,FALSE())="Collected",VLOOKUP(A22,AutoEvidence!$A$2:$G$400,2,FALSE())="Partial"),VLOOKUP(A22,AutoEvidence!$A$2:$G$400,3,FALSE())&" ("&VLOOKUP(A22,AutoEvidence!$A$2:$G$400,2,FALSE())&")",VLOOKUP(A22,AutoEvidence!$A$2:$G$400,2,FALSE())),"")) | T22: =IF(A22="","",IFERROR(VLOOKUP(A22,AutoEvidence!$A$2:$G$400,4,FALSE())&"","")) | AB22: =IF(M22="Gap",1,IF(M22="OK",0,"")) | AC22: =IF(P22<>"",VALUE(RIGHT(P22,1))*1000+ROW(),"") | AD22: =IF(ISNUMBER(L22),MIN(L22,K22),"") | AE22: =IF(AND(ISNUMBER(SEARCH(" PA "," "&SUBSTITUTE($I22,","," ")&" ")),ISNUMBER($L22)),$L22,"") | AF22: =IF(AND(ISNUMBER(SEARCH(" PO "," "&SUBSTITUTE($I22,","," ")&" ")),ISNUMBER($L22)),$L22,"") | AG22: =IF(AND(ISNUMBER(SEARCH(" MFA "," "&SUBSTITUTE($I22,","," ")&" ")),ISNUMBER($L22)),$L22,"") | AH22: =IF(AND(ISNUMBER(SEARCH(" RAP "," "&SUBSTITUTE($I22,","," ")&" ")),ISNUMBER($L22)),$L22,"") | AI22: =IF(AND(ISNUMBER(SEARCH(" AC "," "&SUBSTITUTE($I22,","," ")&" ")),ISNUMBER($L22)),$L22,"") | AJ22: =IF(AND(ISNUMBER(SEARCH(" MAC "," "&SUBSTITUTE($I22,","," ")&" ")),ISNUMBER($L22)),$L22,"") | AK22: =IF(AND(ISNUMBER(SEARCH(" UAH "," "&SUBSTITUTE($I22,","," ")&" ")),ISNUMBER($L22)),$L22,"") | AL22: =IF(AND(ISNUMBER(SEARCH(" RB "," "&SUBSTITUTE($I22,","," ")&" ")),ISNUMBER($L22)),$L22,"")
A23: M365-05 | B23: M365 | C23: Microsoft 365 & Email Security | D23: Exchange on-prem residual: no Exchange 2016/2019 (EoS 14 Oct 2025) - migrated to Exchange SE or removed; last-Exchange-server for recipient management handled | E23: Unsupported Exchange is internet-facing, unpatched and directly exploitable. | F23: STACK.md; Orion node list; SNOW CIs; Exchange admin (Get-ExchangeServer) | G23: Identify any on-prem Exchange server, version and CU; internet exposure; plan to Exchange SE (if hybrid management needed) or full decom using the management-tools-only path. | H23: No unsupported Exchange; hybrid management path documented. | I23: PA, PO | J23: Billable | K23: 2 | M23: =IF(ISNUMBER(L23),IF(L23<K23,"Gap","OK"),IF(L23="N/A","N/A","")) | P23: =IF(AND(M23="Gap",N23<>"",O23<>""),VLOOKUP(N23&O23,Lists!$H$4:$I$12,2,FALSE()),"") | Q23: =IF(AND(M23="Gap",O23="S",OR(N23="H",N23="M")),"Yes","") | R23: Billable | S23: =IF(A23="","",IFERROR(IF(OR(VLOOKUP(A23,AutoEvidence!$A$2:$G$400,2,FALSE())="Collected",VLOOKUP(A23,AutoEvidence!$A$2:$G$400,2,FALSE())="Partial"),VLOOKUP(A23,AutoEvidence!$A$2:$G$400,3,FALSE())&" ("&VLOOKUP(A23,AutoEvidence!$A$2:$G$400,2,FALSE())&")",VLOOKUP(A23,AutoEvidence!$A$2:$G$400,2,FALSE())),"")) | T23: =IF(A23="","",IFERROR(VLOOKUP(A23,AutoEvidence!$A$2:$G$400,4,FALSE())&"","")) | AB23: =IF(M23="Gap",1,IF(M23="OK",0,"")) | AC23: =IF(P23<>"",VALUE(RIGHT(P23,1))*1000+ROW(),"") | AD23: =IF(ISNUMBER(L23),MIN(L23,K23),"") | AE23: =IF(AND(ISNUMBER(SEARCH(" PA "," "&SUBSTITUTE($I23,","," ")&" ")),ISNUMBER($L23)),$L23,"") | AF23: =IF(AND(ISNUMBER(SEARCH(" PO "," "&SUBSTITUTE($I23,","," ")&" ")),ISNUMBER($L23)),$L23,"") | AG23: =IF(AND(ISNUMBER(SEARCH(" MFA "," "&SUBSTITUTE($I23,","," ")&" ")),ISNUMBER($L23)),$L23,"") | AH23: =IF(AND(ISNUMBER(SEARCH(" RAP "," "&SUBSTITUTE($I23,","," ")&" ")),ISNUMBER($L23)),$L23,"") | AI23: =IF(AND(ISNUMBER(SEARCH(" AC "," "&SUBSTITUTE($I23,","," ")&" ")),ISNUMBER($L23)),$L23,"") | AJ23: =IF(AND(ISNUMBER(SEARCH(" MAC "," "&SUBSTITUTE($I23,","," ")&" ")),ISNUMBER($L23)),$L23,"") | AK23: =IF(AND(ISNUMBER(SEARCH(" UAH "," "&SUBSTITUTE($I23,","," ")&" ")),ISNUMBER($L23)),$L23,"") | AL23: =IF(AND(ISNUMBER(SEARCH(" RB "," "&SUBSTITUTE($I23,","," ")&" ")),ISNUMBER($L23)),$L23,"")
A24: M365-06 | B24: M365 | C24: Microsoft 365 & Email Security | D24: SharePoint/OneDrive sharing: external sharing scoped, Anyone links off or expiring, default link type internal, unmanaged-device session controls, guest expiry | E24: Over-permissive links are the most common M365 data leakage path and an easy insurer/auditor finding. | F24: SharePoint admin centre > Policies > Sharing; Access control; Secure Score items | G24: Tenant sharing level 'New and existing guests' or tighter; Anyone links disabled or <= 30-day expiry; default link 'People in your organisation'; idle session sign-out and limited access for unmanaged devices. | H24: Sharing restricted per policy; Anyone links off/expiring; defaults internal. | J24: Value-add | K24: 2 | M24: =IF(ISNUMBER(L24),IF(L24<K24,"Gap","OK"),IF(L24="N/A","N/A","")) | P24: =IF(AND(M24="Gap",N24<>"",O24<>""),VLOOKUP(N24&O24,Lists!$H$4:$I$12,2,FALSE()),"") | Q24: =IF(AND(M24="Gap",O24="S",OR(N24="H",N24="M")),"Yes","") | R24: Value-add | S24: =IF(A24="","",IFERROR(IF(OR(VLOOKUP(A24,AutoEvidence!$A$2:$G$400,2,FALSE())="Collected",VLOOKUP(A24,AutoEvidence!$A$2:$G$400,2,FALSE())="Partial"),VLOOKUP(A24,AutoEvidence!$A$2:$G$400,3,FALSE())&" ("&VLOOKUP(A24,AutoEvidence!$A$2:$G$400,2,FALSE())&")",VLOOKUP(A24,AutoEvidence!$A$2:$G$400,2,FALSE())),"")) | T24: =IF(A24="","",IFERROR(VLOOKUP(A24,AutoEvidence!$A$2:$G$400,4,FALSE())&"","")) | AB24: =IF(M24="Gap",1,IF(M24="OK",0,"")) | AC24: =IF(P24<>"",VALUE(RIGHT(P24,1))*1000+ROW(),"") | AD24: =IF(ISNUMBER(L24),MIN(L24,K24),"") | AE24: =IF(AND(ISNUMBER(SEARCH(" PA "," "&SUBSTITUTE($I24,","," ")&" ")),ISNUMBER($L24)),$L24,"") | AF24: =IF(AND(ISNUMBER(SEARCH(" PO "," "&SUBSTITUTE($I24,","," ")&" ")),ISNUMBER($L24)),$L24,"") | AG24: =IF(AND(ISNUMBER(SEARCH(" MFA "," "&SUBSTITUTE($I24,","," ")&" ")),ISNUMBER($L24)),$L24,"") | AH24: =IF(AND(ISNUMBER(SEARCH(" RAP "," "&SUBSTITUTE($I24,","," ")&" ")),ISNUMBER($L24)),$L24,"") | AI24: =IF(AND(ISNUMBER(SEARCH(" AC "," "&SUBSTITUTE($I24,","," ")&" ")),ISNUMBER($L24)),$L24,"") | AJ24: =IF(AND(ISNUMBER(SEARCH(" MAC "," "&SUBSTITUTE($I24,","," ")&" ")),ISNUMBER($L24)),$L24,"") | AK24: =IF(AND(ISNUMBER(SEARCH(" UAH "," "&SUBSTITUTE($I24,","," ")&" ")),ISNUMBER($L24)),$L24,"") | AL24: =IF(AND(ISNUMBER(SEARCH(" RB "," "&SUBSTITUTE($I24,","," ")&" ")),ISNUMBER($L24)),$L24,"")
A25: M365-07 | B25: M365 | C25: Microsoft 365 & Email Security | D25: Teams governance: external access/federation and guest access deliberate, meeting policies (anonymous join, lobby), third-party app policies, team sprawl managed | E25: Open federation enables Teams-based phishing; uncontrolled apps and guests expand the attack surface. | F25: Teams admin centre > Users > External access; Guest access; Meetings > Meeting policies; Teams apps > Permission policies | G25: Federation allow-listed or blocked for known-bad; anonymous users held in lobby; app permission policy blocks unknown third-party apps; team creation governance or expiry policy exists. | H25: Deliberate, documented settings; no 'allow all' defaults left unreviewed. | J25: Value-add | K25: 2 | M25: =IF(ISNUMBER(L25),IF(L25<K25,"Gap","OK"),IF(L25="N/A","N/A","")) | P25: =IF(AND(M25="Gap",N25<>"",O25<>""),VLOOKUP(N25&O25,Lists!$H$4:$I$12,2,FALSE()),"") | Q25: =IF(AND(M25="Gap",O25="S",OR(N25="H",N25="M")),"Yes","") | R25: Value-add | S25: =IF(A25="","",IFERROR(IF(OR(VLOOKUP(A25,AutoEvidence!$A$2:$G$400,2,FALSE())="Collected",VLOOKUP(A25,AutoEvidence!$A$2:$G$400,2,FALSE())="Partial"),VLOOKUP(A25,AutoEvidence!$A$2:$G$400,3,FALSE())&" ("&VLOOKUP(A25,AutoEvidence!$A$2:$G$400,2,FALSE())&")",VLOOKUP(A25,AutoEvidence!$A$2:$G$400,2,FALSE())),"")) | T25: =IF(A25="","",IFERROR(VLOOKUP(A25,AutoEvidence!$A$2:$G$400,4,FALSE())&"","")) | AB25: =IF(M25="Gap",1,IF(M25="OK",0,"")) | AC25: =IF(P25<>"",VALUE(RIGHT(P25,1))*1000+ROW(),"") | AD25: =IF(ISNUMBER(L25),MIN(L25,K25),"") | AE25: =IF(AND(ISNUMBER(SEARCH(" PA "," "&SUBSTITUTE($I25,","," ")&" ")),ISNUMBER($L25)),$L25,"") | AF25: =IF(AND(ISNUMBER(SEARCH(" PO "," "&SUBSTITUTE($I25,","," ")&" ")),ISNUMBER($L25)),$L25,"") | AG25: =IF(AND(ISNUMBER(SEARCH(" MFA "," "&SUBSTITUTE($I25,","," ")&" ")),ISNUMBER($L25)),$L25,"") | AH25: =IF(AND(ISNUMBER(SEARCH(" RAP "," "&SUBSTITUTE($I25,","," ")&" ")),ISNUMBER($L25)),$L25,"") | AI25: =IF(AND(ISNUMBER(SEARCH(" AC "," "&SUBSTITUTE($I25,","," ")&" ")),ISNUMBER($L25)),$L25,"") | AJ25: =IF(AND(ISNUMBER(SEARCH(" MAC "," "&SUBSTITUTE($I25,","," ")&" ")),ISNUMBER($L25)),$L25,"") | AK25: =IF(AND(ISNUMBER(SEARCH(" UAH "," "&SUBSTITUTE($I25,","," ")&" ")),ISNUMBER($L25)),$L25,"") | AL25: =IF(AND(ISNUMBER(SEARCH(" RB "," "&SUBSTITUTE($I25,","," ")&" ")),ISNUMBER($L25)),$L25,"")
A26: M365-08 | B26: M365 | C26: Microsoft 365 & Email Security | D26: Data protection: retention policies for Exchange/SharePoint/Teams, DLP baseline (AU PII/TFN/credit card), sensitivity labels where licensed, audit log retention | E26: Retention is not backup, but its absence is a legal/regulatory exposure; DLP catches the accidental send. | F26: Purview > Data lifecycle management; DLP policies; Information protection; Audit retention policies | G26: At least one retention policy per workload aligned to the client's obligations; DLP policy in test-with-notifications or enforce for AU financial/PII templates; labels published if E3/E5/BP. | H26: Retention + baseline DLP in place and documented. | J26: Value-add | K26: 2 | M26: =IF(ISNUMBER(L26),IF(L26<K26,"Gap","OK"),IF(L26="N/A","N/A","")) | P26: =IF(AND(M26="Gap",N26<>"",O26<>""),VLOOKUP(N26&O26,Lists!$H$4:$I$12,2,FALSE()),"") | Q26: =IF(AND(M26="Gap",O26="S",OR(N26="H",N26="M")),"Yes","") | R26: Value-add | S26: =IF(A26="","",IFERROR(IF(OR(VLOOKUP(A26,AutoEvidence!$A$2:$G$400,2,FALSE())="Collected",VLOOKUP(A26,AutoEvidence!$A$2:$G$400,2,FALSE())="Partial"),VLOOKUP(A26,AutoEvidence!$A$2:$G$400,3,FALSE())&" ("&VLOOKUP(A26,AutoEvidence!$A$2:$G$400,2,FALSE())&")",VLOOKUP(A26,AutoEvidence!$A$2:$G$400,2,FALSE())),"")) | T26: =IF(A26="","",IFERROR(VLOOKUP(A26,AutoEvidence!$A$2:$G$400,4,FALSE())&"","")) | AB26: =IF(M26="Gap",1,IF(M26="OK",0,"")) | AC26: =IF(P26<>"",VALUE(RIGHT(P26,1))*1000+ROW(),"") | AD26: =IF(ISNUMBER(L26),MIN(L26,K26),"") | AE26: =IF(AND(ISNUMBER(SEARCH(" PA "," "&SUBSTITUTE($I26,","," ")&" ")),ISNUMBER($L26)),$L26,"") | AF26: =IF(AND(ISNUMBER(SEARCH(" PO "," "&SUBSTITUTE($I26,","," ")&" ")),ISNUMBER($L26)),$L26,"") | AG26: =IF(AND(ISNUMBER(SEARCH(" MFA "," "&SUBSTITUTE($I26,","," ")&" ")),ISNUMBER($L26)),$L26,"") | AH26: =IF(AND(ISNUMBER(SEARCH(" RAP "," "&SUBSTITUTE($I26,","," ")&" ")),ISNUMBER($L26)),$L26,"") | AI26: =IF(AND(ISNUMBER(SEARCH(" AC "," "&SUBSTITUTE($I26,","," ")&" ")),ISNUMBER($L26)),$L26,"") | AJ26: =IF(AND(ISNUMBER(SEARCH(" MAC "," "&SUBSTITUTE($I26,","," ")&" ")),ISNUMBER($L26)),$L26,"") | AK26: =IF(AND(ISNUMBER(SEARCH(" UAH "," "&SUBSTITUTE($I26,","," ")&" ")),ISNUMBER($L26)),$L26,"") | AL26: =IF(AND(ISNUMBER(SEARCH(" RB "," "&SUBSTITUTE($I26,","," ")&" ")),ISNUMBER($L26)),$L26,"")
A27: M365-09 | B27: M365 | C27: Microsoft 365 & Email Security | D27: Microsoft 365 backup (third-party) covering Exchange, SharePoint, OneDrive and Teams; coverage %, last job success, restore tested | E27: Microsoft's shared-responsibility model leaves data recovery to the customer (E8 RB). | F27: Backup console (Veeam for M365/Datto SaaS/AvePoint/other); BAMS inclusions (backup line items) | G27: Confirm product, all users/sites auto-protected (new users auto-added), last 7 days success, retention matches policy, a mailbox/file restore tested in last 6 months. | H27: 100% coverage, jobs green, restore tested. | I27: RB | J27: Billable | K27: 2 | M27: =IF(ISNUMBER(L27),IF(L27<K27,"Gap","OK"),IF(L27="N/A","N/A","")) | P27: =IF(AND(M27="Gap",N27<>"",O27<>""),VLOOKUP(N27&O27,Lists!$H$4:$I$12,2,FALSE()),"") | Q27: =IF(AND(M27="Gap",O27="S",OR(N27="H",N27="M")),"Yes","") | R27: Billable | S27: =IF(A27="","",IFERROR(IF(OR(VLOOKUP(A27,AutoEvidence!$A$2:$G$400,2,FALSE())="Collected",VLOOKUP(A27,AutoEvidence!$A$2:$G$400,2,FALSE())="Partial"),VLOOKUP(A27,AutoEvidence!$A$2:$G$400,3,FALSE())&" ("&VLOOKUP(A27,AutoEvidence!$A$2:$G$400,2,FALSE())&")",VLOOKUP(A27,AutoEvidence!$A$2:$G$400,2,FALSE())),"")) | T27: =IF(A27="","",IFERROR(VLOOKUP(A27,AutoEvidence!$A$2:$G$400,4,FALSE())&"","")) | AB27: =IF(M27="Gap",1,IF(M27="OK",0,"")) | AC27: =IF(P27<>"",VALUE(RIGHT(P27,1))*1000+ROW(),"") | AD27: =IF(ISNUMBER(L27),MIN(L27,K27),"") | AE27: =IF(AND(ISNUMBER(SEARCH(" PA "," "&SUBSTITUTE($I27,","," ")&" ")),ISNUMBER($L27)),$L27,"") | AF27: =IF(AND(ISNUMBER(SEARCH(" PO "," "&SUBSTITUTE($I27,","," ")&" ")),ISNUMBER($L27)),$L27,"") | AG27: =IF(AND(ISNUMBER(SEARCH(" MFA "," "&SUBSTITUTE($I27,","," ")&" ")),ISNUMBER($L27)),$L27,"") | AH27: =IF(AND(ISNUMBER(SEARCH(" RAP "," "&SUBSTITUTE($I27,","," ")&" ")),ISNUMBER($L27)),$L27,"") | AI27: =IF(AND(ISNUMBER(SEARCH(" AC "," "&SUBSTITUTE($I27,","," ")&" ")),ISNUMBER($L27)),$L27,"") | AJ27: =IF(AND(ISNUMBER(SEARCH(" MAC "," "&SUBSTITUTE($I27,","," ")&" ")),ISNUMBER($L27)),$L27,"") | AK27: =IF(AND(ISNUMBER(SEARCH(" UAH "," "&SUBSTITUTE($I27,","," ")&" ")),ISNUMBER($L27)),$L27,"") | AL27: =IF(AND(ISNUMBER(SEARCH(" RB "," "&SUBSTITUTE($I27,","," ")&" ")),ISNUMBER($L27)),$L27,"")
A28: M365-10 | B28: M365 | C28: Microsoft 365 & Email Security | D28: Licensing fit: SKU inventory vs assigned vs active; unused licences; security features licensed but not deployed (P1/P2, Defender for Endpoint, Intune, Purview) | E28: Clients pay for controls they do not use, or run controls they are not licensed for. | F28: M365 admin centre > Billing > Licenses (via Lighthouse); Usage reports; eFO annuity | G28: Table: SKU, purchased, assigned, active 30 days; list features in the SKU not in use; flag over/under-licensing and NCE renewal date. | H28: < 5% unassigned; licensed security features deployed or consciously deferred. | J28: Value-add | K28: 2 | M28: =IF(ISNUMBER(L28),IF(L28<K28,"Gap","OK"),IF(L28="N/A","N/A","")) | P28: =IF(AND(M28="Gap",N28<>"",O28<>""),VLOOKUP(N28&O28,Lists!$H$4:$I$12,2,FALSE()),"") | Q28: =IF(AND(M28="Gap",O28="S",OR(N28="H",N28="M")),"Yes","") | R28: Value-add | S28: =IF(A28="","",IFERROR(IF(OR(VLOOKUP(A28,AutoEvidence!$A$2:$G$400,2,FALSE())="Collected",VLOOKUP(A28,AutoEvidence!$A$2:$G$400,2,FALSE())="Partial"),VLOOKUP(A28,AutoEvidence!$A$2:$G$400,3,FALSE())&" ("&VLOOKUP(A28,AutoEvidence!$A$2:$G$400,2,FALSE())&")",VLOOKUP(A28,AutoEvidence!$A$2:$G$400,2,FALSE())),"")) | T28: =IF(A28="","",IFERROR(VLOOKUP(A28,AutoEvidence!$A$2:$G$400,4,FALSE())&"","")) | AB28: =IF(M28="Gap",1,IF(M28="OK",0,"")) | AC28: =IF(P28<>"",VALUE(RIGHT(P28,1))*1000+ROW(),"") | AD28: =IF(ISNUMBER(L28),MIN(L28,K28),"") | AE28: =IF(AND(ISNUMBER(SEARCH(" PA "," "&SUBSTITUTE($I28,","," ")&" ")),ISNUMBER($L28)),$L28,"") | AF28: =IF(AND(ISNUMBER(SEARCH(" PO "," "&SUBSTITUTE($I28,","," ")&" ")),ISNUMBER($L28)),$L28,"") | AG28: =IF(AND(ISNUMBER(SEARCH(" MFA "," "&SUBSTITUTE($I28,","," ")&" ")),ISNUMBER($L28)),$L28,"") | AH28: =IF(AND(ISNUMBER(SEARCH(" RAP "," "&SUBSTITUTE($I28,","," ")&" ")),ISNUMBER($L28)),$L28,"") | AI28: =IF(AND(ISNUMBER(SEARCH(" AC "," "&SUBSTITUTE($I28,","," ")&" ")),ISNUMBER($L28)),$L28,"") | AJ28: =IF(AND(ISNUMBER(SEARCH(" MAC "," "&SUBSTITUTE($I28,","," ")&" ")),ISNUMBER($L28)),$L28,"") | AK28: =IF(AND(ISNUMBER(SEARCH(" UAH "," "&SUBSTITUTE($I28,","," ")&" ")),ISNUMBER($L28)),$L28,"") | AL28: =IF(AND(ISNUMBER(SEARCH(" RB "," "&SUBSTITUTE($I28,","," ")&" ")),ISNUMBER($L28)),$L28,"")
A29: M365-11 | B29: M365 | C29: Microsoft 365 & Email Security | D29: Service health and Message Centre monitored; upcoming retirements/breaking changes tracked in LOG.md | E29: Microsoft retires features on a schedule; surprises become incidents. | F29: M365 admin centre > Health > Message centre (Lighthouse aggregate view); LOG.md | G29: Confirm who reads Message Centre for this tenant; last 90 days of 'Plan for change' items reviewed; anything affecting the client noted with a date. | H29: Named owner; changes tracked. | J29: BAU | K29: 2 | M29: =IF(ISNUMBER(L29),IF(L29<K29,"Gap","OK"),IF(L29="N/A","N/A","")) | P29: =IF(AND(M29="Gap",N29<>"",O29<>""),VLOOKUP(N29&O29,Lists!$H$4:$I$12,2,FALSE()),"") | Q29: =IF(AND(M29="Gap",O29="S",OR(N29="H",N29="M")),"Yes","") | R29: BAU | S29: =IF(A29="","",IFERROR(IF(OR(VLOOKUP(A29,AutoEvidence!$A$2:$G$400,2,FALSE())="Collected",VLOOKUP(A29,AutoEvidence!$A$2:$G$400,2,FALSE())="Partial"),VLOOKUP(A29,AutoEvidence!$A$2:$G$400,3,FALSE())&" ("&VLOOKUP(A29,AutoEvidence!$A$2:$G$400,2,FALSE())&")",VLOOKUP(A29,AutoEvidence!$A$2:$G$400,2,FALSE())),"")) | T29: =IF(A29="","",IFERROR(VLOOKUP(A29,AutoEvidence!$A$2:$G$400,4,FALSE())&"","")) | AB29: =IF(M29="Gap",1,IF(M29="OK",0,"")) | AC29: =IF(P29<>"",VALUE(RIGHT(P29,1))*1000+ROW(),"") | AD29: =IF(ISNUMBER(L29),MIN(L29,K29),"") | AE29: =IF(AND(ISNUMBER(SEARCH(" PA "," "&SUBSTITUTE($I29,","," ")&" ")),ISNUMBER($L29)),$L29,"") | AF29: =IF(AND(ISNUMBER(SEARCH(" PO "," "&SUBSTITUTE($I29,","," ")&" ")),ISNUMBER($L29)),$L29,"") | AG29: =IF(AND(ISNUMBER(SEARCH(" MFA "," "&SUBSTITUTE($I29,","," ")&" ")),ISNUMBER($L29)),$L29,"") | AH29: =IF(AND(ISNUMBER(SEARCH(" RAP "," "&SUBSTITUTE($I29,","," ")&" ")),ISNUMBER($L29)),$L29,"") | AI29: =IF(AND(ISNUMBER(SEARCH(" AC "," "&SUBSTITUTE($I29,","," ")&" ")),ISNUMBER($L29)),$L29,"") | AJ29: =IF(AND(ISNUMBER(SEARCH(" MAC "," "&SUBSTITUTE($I29,","," ")&" ")),ISNUMBER($L29)),$L29,"") | AK29: =IF(AND(ISNUMBER(SEARCH(" UAH "," "&SUBSTITUTE($I29,","," ")&" ")),ISNUMBER($L29)),$L29,"") | AL29: =IF(AND(ISNUMBER(SEARCH(" RB "," "&SUBSTITUTE($I29,","," ")&" ")),ISNUMBER($L29)),$L29,"")
A30: M365-12 | B30: M365 | C30: Microsoft 365 & Email Security | D30: Alert routing: security/compliance alerts and tenant notifications go to a monitored mailbox or MDR (Huntress ITDR / Rapid7), technical contact current | E30: Alerts sent to a departed admin's mailbox are alerts nobody sees. | F30: Defender > Settings > Email notifications; Entra > Properties (technical contact); Huntress M365 integration status | G30: Notification recipients are role mailboxes or bA; Huntress/Rapid7 M365 connector healthy; technical and notification contacts not ex-staff. | H30: All alerts reach a monitored destination. | J30: BAU | K30: 2 | M30: =IF(ISNUMBER(L30),IF(L30<K30,"Gap","OK"),IF(L30="N/A","N/A","")) | P30: =IF(AND(M30="Gap",N30<>"",O30<>""),VLOOKUP(N30&O30,Lists!$H$4:$I$12,2,FALSE()),"") | Q30: =IF(AND(M30="Gap",O30="S",OR(N30="H",N30="M")),"Yes","") | R30: BAU | S30: =IF(A30="","",IFERROR(IF(OR(VLOOKUP(A30,AutoEvidence!$A$2:$G$400,2,FALSE())="Collected",VLOOKUP(A30,AutoEvidence!$A$2:$G$400,2,FALSE())="Partial"),VLOOKUP(A30,AutoEvidence!$A$2:$G$400,3,FALSE())&" ("&VLOOKUP(A30,AutoEvidence!$A$2:$G$400,2,FALSE())&")",VLOOKUP(A30,AutoEvidence!$A$2:$G$400,2,FALSE())),"")) | T30: =IF(A30="","",IFERROR(VLOOKUP(A30,AutoEvidence!$A$2:$G$400,4,FALSE())&"","")) | AB30: =IF(M30="Gap",1,IF(M30="OK",0,"")) | AC30: =IF(P30<>"",VALUE(RIGHT(P30,1))*1000+ROW(),"") | AD30: =IF(ISNUMBER(L30),MIN(L30,K30),"") | AE30: =IF(AND(ISNUMBER(SEARCH(" PA "," "&SUBSTITUTE($I30,","," ")&" ")),ISNUMBER($L30)),$L30,"") | AF30: =IF(AND(ISNUMBER(SEARCH(" PO "," "&SUBSTITUTE($I30,","," ")&" ")),ISNUMBER($L30)),$L30,"") | AG30: =IF(AND(ISNUMBER(SEARCH(" MFA "," "&SUBSTITUTE($I30,","," ")&" ")),ISNUMBER($L30)),$L30,"") | AH30: =IF(AND(ISNUMBER(SEARCH(" RAP "," "&SUBSTITUTE($I30,","," ")&" ")),ISNUMBER($L30)),$L30,"") | AI30: =IF(AND(ISNUMBER(SEARCH(" AC "," "&SUBSTITUTE($I30,","," ")&" ")),ISNUMBER($L30)),$L30,"") | AJ30: =IF(AND(ISNUMBER(SEARCH(" MAC "," "&SUBSTITUTE($I30,","," ")&" ")),ISNUMBER($L30)),$L30,"") | AK30: =IF(AND(ISNUMBER(SEARCH(" UAH "," "&SUBSTITUTE($I30,","," ")&" ")),ISNUMBER($L30)),$L30,"") | AL30: =IF(AND(ISNUMBER(SEARCH(" RB "," "&SUBSTITUTE($I30,","," ")&" ")),ISNUMBER($L30)),$L30,"")
A31: END-01 | B31: END | C31: Endpoint | D31: Device inventory and management coverage: every workstation/laptop/mobile enrolled in Intune (or GPO/ConfigMgr) and in RMM; unmanaged device count | E31: You cannot patch, protect or wipe what you do not manage; coverage gaps are also BAMS billing gaps. | F31: Intune > Devices; Entra > Devices; N-Central / NinjaOne device list; LionGard; HR headcount from PROFILE | G31: Reconcile counts across Intune, Entra, RMM and EDR; list devices in one and not the others; identify personally-owned devices accessing corporate data. | H31: Counts reconcile within 2%; every corporate device in MDM + RMM + EDR. | J31: BAU | K31: 2 | M31: =IF(ISNUMBER(L31),IF(L31<K31,"Gap","OK"),IF(L31="N/A","N/A","")) | P31: =IF(AND(M31="Gap",N31<>"",O31<>""),VLOOKUP(N31&O31,Lists!$H$4:$I$12,2,FALSE()),"") | Q31: =IF(AND(M31="Gap",O31="S",OR(N31="H",N31="M")),"Yes","") | R31: BAU | S31: =IF(A31="","",IFERROR(IF(OR(VLOOKUP(A31,AutoEvidence!$A$2:$G$400,2,FALSE())="Collected",VLOOKUP(A31,AutoEvidence!$A$2:$G$400,2,FALSE())="Partial"),VLOOKUP(A31,AutoEvidence!$A$2:$G$400,3,FALSE())&" ("&VLOOKUP(A31,AutoEvidence!$A$2:$G$400,2,FALSE())&")",VLOOKUP(A31,AutoEvidence!$A$2:$G$400,2,FALSE())),"")) | T31: =IF(A31="","",IFERROR(VLOOKUP(A31,AutoEvidence!$A$2:$G$400,4,FALSE())&"","")) | AB31: =IF(M31="Gap",1,IF(M31="OK",0,"")) | AC31: =IF(P31<>"",VALUE(RIGHT(P31,1))*1000+ROW(),"") | AD31: =IF(ISNUMBER(L31),MIN(L31,K31),"") | AE31: =IF(AND(ISNUMBER(SEARCH(" PA "," "&SUBSTITUTE($I31,","," ")&" ")),ISNUMBER($L31)),$L31,"") | AF31: =IF(AND(ISNUMBER(SEARCH(" PO "," "&SUBSTITUTE($I31,","," ")&" ")),ISNUMBER($L31)),$L31,"") | AG31: =IF(AND(ISNUMBER(SEARCH(" MFA "," "&SUBSTITUTE($I31,","," ")&" ")),ISNUMBER($L31)),$L31,"") | AH31: =IF(AND(ISNUMBER(SEARCH(" RAP "," "&SUBSTITUTE($I31,","," ")&" ")),ISNUMBER($L31)),$L31,"") | AI31: =IF(AND(ISNUMBER(SEARCH(" AC "," "&SUBSTITUTE($I31,","," ")&" ")),ISNUMBER($L31)),$L31,"") | AJ31: =IF(AND(ISNUMBER(SEARCH(" MAC "," "&SUBSTITUTE($I31,","," ")&" ")),ISNUMBER($L31)),$L31,"") | AK31: =IF(AND(ISNUMBER(SEARCH(" UAH "," "&SUBSTITUTE($I31,","," ")&" ")),ISNUMBER($L31)),$L31,"") | AL31: =IF(AND(ISNUMBER(SEARCH(" RB "," "&SUBSTITUTE($I31,","," ")&" ")),ISNUMBER($L31)),$L31,"")
A32: END-02 | B32: END | C32: Endpoint | D32: OS currency: Windows 11 only (Windows 10 EoS 14 Oct 2025; ESU only as documented exception), macOS n/n-1, feature update rings defined | E32: Unsupported OS = no security updates (E8 PO ML1: unsupported OS replaced). | F32: Intune > Reports > Windows feature update; N-Central OS report; Intune Windows 11 hardware readiness report | G32: Count Windows 10 devices and ESU status; list Win11-ineligible hardware; confirm feature-update deployment rings and deferrals. | H32: Zero unsupported OS without documented ESU/exception; rings defined. | I32: PO | J32: Billable | K32: 2 | M32: =IF(ISNUMBER(L32),IF(L32<K32,"Gap","OK"),IF(L32="N/A","N/A","")) | P32: =IF(AND(M32="Gap",N32<>"",O32<>""),VLOOKUP(N32&O32,Lists!$H$4:$I$12,2,FALSE()),"") | Q32: =IF(AND(M32="Gap",O32="S",OR(N32="H",N32="M")),"Yes","") | R32: Billable | S32: =IF(A32="","",IFERROR(IF(OR(VLOOKUP(A32,AutoEvidence!$A$2:$G$400,2,FALSE())="Collected",VLOOKUP(A32,AutoEvidence!$A$2:$G$400,2,FALSE())="Partial"),VLOOKUP(A32,AutoEvidence!$A$2:$G$400,3,FALSE())&" ("&VLOOKUP(A32,AutoEvidence!$A$2:$G$400,2,FALSE())&")",VLOOKUP(A32,AutoEvidence!$A$2:$G$400,2,FALSE())),"")) | T32: =IF(A32="","",IFERROR(VLOOKUP(A32,AutoEvidence!$A$2:$G$400,4,FALSE())&"","")) | AB32: =IF(M32="Gap",1,IF(M32="OK",0,"")) | AC32: =IF(P32<>"",VALUE(RIGHT(P32,1))*1000+ROW(),"") | AD32: =IF(ISNUMBER(L32),MIN(L32,K32),"") | AE32: =IF(AND(ISNUMBER(SEARCH(" PA "," "&SUBSTITUTE($I32,","," ")&" ")),ISNUMBER($L32)),$L32,"") | AF32: =IF(AND(ISNUMBER(SEARCH(" PO "," "&SUBSTITUTE($I32,","," ")&" ")),ISNUMBER($L32)),$L32,"") | AG32: =IF(AND(ISNUMBER(SEARCH(" MFA "," "&SUBSTITUTE($I32,","," ")&" ")),ISNUMBER($L32)),$L32,"") | AH32: =IF(AND(ISNUMBER(SEARCH(" RAP "," "&SUBSTITUTE($I32,","," ")&" ")),ISNUMBER($L32)),$L32,"") | AI32: =IF(AND(ISNUMBER(SEARCH(" AC "," "&SUBSTITUTE($I32,","," ")&" ")),ISNUMBER($L32)),$L32,"") | AJ32: =IF(AND(ISNUMBER(SEARCH(" MAC "," "&SUBSTITUTE($I32,","," ")&" ")),ISNUMBER($L32)),$L32,"") | AK32: =IF(AND(ISNUMBER(SEARCH(" UAH "," "&SUBSTITUTE($I32,","," ")&" ")),ISNUMBER($L32)),$L32,"") | AL32: =IF(AND(ISNUMBER(SEARCH(" RB "," "&SUBSTITUTE($I32,","," ")&" ")),ISNUMBER($L32)),$L32,"")
A33: END-03 | B33: END | C33: Endpoint | D33: OS patch compliance: workstations patched within 1 month (E8 ML1), critical/exploited within 48 h where internet-facing; reboot compliance; reporting | E33: Patch latency is the single largest measurable exposure. | F33: Intune > Reports > Windows update rings / Expedited; N-Central patch status report | G33: % devices compliant with latest cumulative update at 30 days; devices not checked in > 14 days; pending-reboot count; patch policy and rings documented. | H33: >= 95% within 30 days; < 5% stale; process documented. | I33: PO | J33: BAU | K33: 2 | M33: =IF(ISNUMBER(L33),IF(L33<K33,"Gap","OK"),IF(L33="N/A","N/A","")) | P33: =IF(AND(M33="Gap",N33<>"",O33<>""),VLOOKUP(N33&O33,Lists!$H$4:$I$12,2,FALSE()),"") | Q33: =IF(AND(M33="Gap",O33="S",OR(N33="H",N33="M")),"Yes","") | R33: BAU | S33: =IF(A33="","",IFERROR(IF(OR(VLOOKUP(A33,AutoEvidence!$A$2:$G$400,2,FALSE())="Collected",VLOOKUP(A33,AutoEvidence!$A$2:$G$400,2,FALSE())="Partial"),VLOOKUP(A33,AutoEvidence!$A$2:$G$400,3,FALSE())&" ("&VLOOKUP(A33,AutoEvidence!$A$2:$G$400,2,FALSE())&")",VLOOKUP(A33,AutoEvidence!$A$2:$G$400,2,FALSE())),"")) | T33: =IF(A33="","",IFERROR(VLOOKUP(A33,AutoEvidence!$A$2:$G$400,4,FALSE())&"","")) | AB33: =IF(M33="Gap",1,IF(M33="OK",0,"")) | AC33: =IF(P33<>"",VALUE(RIGHT(P33,1))*1000+ROW(),"") | AD33: =IF(ISNUMBER(L33),MIN(L33,K33),"") | AE33: =IF(AND(ISNUMBER(SEARCH(" PA "," "&SUBSTITUTE($I33,","," ")&" ")),ISNUMBER($L33)),$L33,"") | AF33: =IF(AND(ISNUMBER(SEARCH(" PO "," "&SUBSTITUTE($I33,","," ")&" ")),ISNUMBER($L33)),$L33,"") | AG33: =IF(AND(ISNUMBER(SEARCH(" MFA "," "&SUBSTITUTE($I33,","," ")&" ")),ISNUMBER($L33)),$L33,"") | AH33: =IF(AND(ISNUMBER(SEARCH(" RAP "," "&SUBSTITUTE($I33,","," ")&" ")),ISNUMBER($L33)),$L33,"") | AI33: =IF(AND(ISNUMBER(SEARCH(" AC "," "&SUBSTITUTE($I33,","," ")&" ")),ISNUMBER($L33)),$L33,"") | AJ33: =IF(AND(ISNUMBER(SEARCH(" MAC "," "&SUBSTITUTE($I33,","," ")&" ")),ISNUMBER($L33)),$L33,"") | AK33: =IF(AND(ISNUMBER(SEARCH(" UAH "," "&SUBSTITUTE($I33,","," ")&" ")),ISNUMBER($L33)),$L33,"") | AL33: =IF(AND(ISNUMBER(SEARCH(" RB "," "&SUBSTITUTE($I33,","," ")&" ")),ISNUMBER($L33)),$L33,"")
A34: END-04 | B34: END | C34: Endpoint | D34: Third-party application patching: browsers, Office/M365 Apps, PDF, Java, collaboration clients patched within 2 weeks (E8 PA ML1); unsupported apps removed | E34: Browsers and PDF readers are the applications actually exploited on endpoints. | F34: N-Central / NinjaOne third-party patching; Intune Enterprise App Management or winget policy; Defender Vulnerability Management software inventory | G34: Tool in place and covering all devices; compliance % at 14 days for the E8 application classes; inventory shows no Flash, IE11, EoL Java/Adobe/7-Zip versions. | H34: Automated 3rd-party patching, >= 90% within 14 days, EoL apps removed. | I34: PA | J34: BAU | K34: 2 | M34: =IF(ISNUMBER(L34),IF(L34<K34,"Gap","OK"),IF(L34="N/A","N/A","")) | P34: =IF(AND(M34="Gap",N34<>"",O34<>""),VLOOKUP(N34&O34,Lists!$H$4:$I$12,2,FALSE()),"") | Q34: =IF(AND(M34="Gap",O34="S",OR(N34="H",N34="M")),"Yes","") | R34: BAU | S34: =IF(A34="","",IFERROR(IF(OR(VLOOKUP(A34,AutoEvidence!$A$2:$G$400,2,FALSE())="Collected",VLOOKUP(A34,AutoEvidence!$A$2:$G$400,2,FALSE())="Partial"),VLOOKUP(A34,AutoEvidence!$A$2:$G$400,3,FALSE())&" ("&VLOOKUP(A34,AutoEvidence!$A$2:$G$400,2,FALSE())&")",VLOOKUP(A34,AutoEvidence!$A$2:$G$400,2,FALSE())),"")) | T34: =IF(A34="","",IFERROR(VLOOKUP(A34,AutoEvidence!$A$2:$G$400,4,FALSE())&"","")) | AB34: =IF(M34="Gap",1,IF(M34="OK",0,"")) | AC34: =IF(P34<>"",VALUE(RIGHT(P34,1))*1000+ROW(),"") | AD34: =IF(ISNUMBER(L34),MIN(L34,K34),"") | AE34: =IF(AND(ISNUMBER(SEARCH(" PA "," "&SUBSTITUTE($I34,","," ")&" ")),ISNUMBER($L34)),$L34,"") | AF34: =IF(AND(ISNUMBER(SEARCH(" PO "," "&SUBSTITUTE($I34,","," ")&" ")),ISNUMBER($L34)),$L34,"") | AG34: =IF(AND(ISNUMBER(SEARCH(" MFA "," "&SUBSTITUTE($I34,","," ")&" ")),ISNUMBER($L34)),$L34,"") | AH34: =IF(AND(ISNUMBER(SEARCH(" RAP "," "&SUBSTITUTE($I34,","," ")&" ")),ISNUMBER($L34)),$L34,"") | AI34: =IF(AND(ISNUMBER(SEARCH(" AC "," "&SUBSTITUTE($I34,","," ")&" ")),ISNUMBER($L34)),$L34,"") | AJ34: =IF(AND(ISNUMBER(SEARCH(" MAC "," "&SUBSTITUTE($I34,","," ")&" ")),ISNUMBER($L34)),$L34,"") | AK34: =IF(AND(ISNUMBER(SEARCH(" UAH "," "&SUBSTITUTE($I34,","," ")&" ")),ISNUMBER($L34)),$L34,"") | AL34: =IF(AND(ISNUMBER(SEARCH(" RB "," "&SUBSTITUTE($I34,","," ")&" ")),ISNUMBER($L34)),$L34,"")
A35: END-05 | B35: END | C35: Endpoint | D35: Endpoint vulnerability scanning: Defender Vulnerability Management or Rapid7 IVM agent on all devices; cadence per E8 ML1; critical findings aged < 30 days | E35: E8 ML1 requires scanning (weekly apps, fortnightly OS) - patching without scanning is unverified. | F35: Defender portal > Vulnerability management; Rapid7 IVM console | G35: Agent coverage %; last scan dates; count of critical/high CVEs with known exploits older than 30 days; exception register. | H35: >= 98% coverage; no exploited criticals > 30 days. | I35: PA, PO | J35: Billable | K35: 2 | M35: =IF(ISNUMBER(L35),IF(L35<K35,"Gap","OK"),IF(L35="N/A","N/A","")) | P35: =IF(AND(M35="Gap",N35<>"",O35<>""),VLOOKUP(N35&O35,Lists!$H$4:$I$12,2,FALSE()),"") | Q35: =IF(AND(M35="Gap",O35="S",OR(N35="H",N35="M")),"Yes","") | R35: Billable | S35: =IF(A35="","",IFERROR(IF(OR(VLOOKUP(A35,AutoEvidence!$A$2:$G$400,2,FALSE())="Collected",VLOOKUP(A35,AutoEvidence!$A$2:$G$400,2,FALSE())="Partial"),VLOOKUP(A35,AutoEvidence!$A$2:$G$400,3,FALSE())&" ("&VLOOKUP(A35,AutoEvidence!$A$2:$G$400,2,FALSE())&")",VLOOKUP(A35,AutoEvidence!$A$2:$G$400,2,FALSE())),"")) | T35: =IF(A35="","",IFERROR(VLOOKUP(A35,AutoEvidence!$A$2:$G$400,4,FALSE())&"","")) | AB35: =IF(M35="Gap",1,IF(M35="OK",0,"")) | AC35: =IF(P35<>"",VALUE(RIGHT(P35,1))*1000+ROW(),"") | AD35: =IF(ISNUMBER(L35),MIN(L35,K35),"") | AE35: =IF(AND(ISNUMBER(SEARCH(" PA "," "&SUBSTITUTE($I35,","," ")&" ")),ISNUMBER($L35)),$L35,"") | AF35: =IF(AND(ISNUMBER(SEARCH(" PO "," "&SUBSTITUTE($I35,","," ")&" ")),ISNUMBER($L35)),$L35,"") | AG35: =IF(AND(ISNUMBER(SEARCH(" MFA "," "&SUBSTITUTE($I35,","," ")&" ")),ISNUMBER($L35)),$L35,"") | AH35: =IF(AND(ISNUMBER(SEARCH(" RAP "," "&SUBSTITUTE($I35,","," ")&" ")),ISNUMBER($L35)),$L35,"") | AI35: =IF(AND(ISNUMBER(SEARCH(" AC "," "&SUBSTITUTE($I35,","," ")&" ")),ISNUMBER($L35)),$L35,"") | AJ35: =IF(AND(ISNUMBER(SEARCH(" MAC "," "&SUBSTITUTE($I35,","," ")&" ")),ISNUMBER($L35)),$L35,"") | AK35: =IF(AND(ISNUMBER(SEARCH(" UAH "," "&SUBSTITUTE($I35,","," ")&" ")),ISNUMBER($L35)),$L35,"") | AL35: =IF(AND(ISNUMBER(SEARCH(" RB "," "&SUBSTITUTE($I35,","," ")&" ")),ISNUMBER($L35)),$L35,"")
A36: END-06 | B36: END | C36: Endpoint | D36: EDR/AV coverage and health: Trend / CrowdStrike / Defender for Endpoint on 100% of devices, sensors healthy (reported <= 7 days), tamper protection on, Huntress agent alongside | E36: EDR is the control that turns a breach into an alert; unhealthy sensors are invisible gaps. CrowdStrike removal needs a customer-generated key - know the process before a P1. | F36: EDR console device health; Huntress portal agent list; Intune AV status report | G36: Devices in MDM/RMM vs EDR; inactive sensors > 7 days; tamper protection and cloud-delivered protection enforced; alert routing to MDR/NOC confirmed. | H36: 100% coverage, < 2% inactive, tamper protection on. | J36: BAU | K36: 2 | M36: =IF(ISNUMBER(L36),IF(L36<K36,"Gap","OK"),IF(L36="N/A","N/A","")) | P36: =IF(AND(M36="Gap",N36<>"",O36<>""),VLOOKUP(N36&O36,Lists!$H$4:$I$12,2,FALSE()),"") | Q36: =IF(AND(M36="Gap",O36="S",OR(N36="H",N36="M")),"Yes","") | R36: BAU | S36: =IF(A36="","",IFERROR(IF(OR(VLOOKUP(A36,AutoEvidence!$A$2:$G$400,2,FALSE())="Collected",VLOOKUP(A36,AutoEvidence!$A$2:$G$400,2,FALSE())="Partial"),VLOOKUP(A36,AutoEvidence!$A$2:$G$400,3,FALSE())&" ("&VLOOKUP(A36,AutoEvidence!$A$2:$G$400,2,FALSE())&")",VLOOKUP(A36,AutoEvidence!$A$2:$G$400,2,FALSE())),"")) | T36: =IF(A36="","",IFERROR(VLOOKUP(A36,AutoEvidence!$A$2:$G$400,4,FALSE())&"","")) | AB36: =IF(M36="Gap",1,IF(M36="OK",0,"")) | AC36: =IF(P36<>"",VALUE(RIGHT(P36,1))*1000+ROW(),"") | AD36: =IF(ISNUMBER(L36),MIN(L36,K36),"") | AE36: =IF(AND(ISNUMBER(SEARCH(" PA "," "&SUBSTITUTE($I36,","," ")&" ")),ISNUMBER($L36)),$L36,"") | AF36: =IF(AND(ISNUMBER(SEARCH(" PO "," "&SUBSTITUTE($I36,","," ")&" ")),ISNUMBER($L36)),$L36,"") | AG36: =IF(AND(ISNUMBER(SEARCH(" MFA "," "&SUBSTITUTE($I36,","," ")&" ")),ISNUMBER($L36)),$L36,"") | AH36: =IF(AND(ISNUMBER(SEARCH(" RAP "," "&SUBSTITUTE($I36,","," ")&" ")),ISNUMBER($L36)),$L36,"") | AI36: =IF(AND(ISNUMBER(SEARCH(" AC "," "&SUBSTITUTE($I36,","," ")&" ")),ISNUMBER($L36)),$L36,"") | AJ36: =IF(AND(ISNUMBER(SEARCH(" MAC "," "&SUBSTITUTE($I36,","," ")&" ")),ISNUMBER($L36)),$L36,"") | AK36: =IF(AND(ISNUMBER(SEARCH(" UAH "," "&SUBSTITUTE($I36,","," ")&" ")),ISNUMBER($L36)),$L36,"") | AL36: =IF(AND(ISNUMBER(SEARCH(" RB "," "&SUBSTITUTE($I36,","," ")&" ")),ISNUMBER($L36)),$L36,"")
A37: END-07 | B37: END | C37: Endpoint | D37: Disk encryption: BitLocker enforced with recovery keys escrowed to Entra/Intune (or AD); FileVault on macOS; compliance report | E37: Lost laptops become notifiable data breaches without encryption evidence. | F37: Intune > Reports > Encryption report; Entra device BitLocker keys; Intune compliance policy | G37: % encrypted; % with key escrowed; compliance policy requires encryption; TPM+PIN or silent enablement decision documented. | H37: >= 98% encrypted with escrowed keys. | J37: BAU | K37: 2 | M37: =IF(ISNUMBER(L37),IF(L37<K37,"Gap","OK"),IF(L37="N/A","N/A","")) | P37: =IF(AND(M37="Gap",N37<>"",O37<>""),VLOOKUP(N37&O37,Lists!$H$4:$I$12,2,FALSE()),"") | Q37: =IF(AND(M37="Gap",O37="S",OR(N37="H",N37="M")),"Yes","") | R37: BAU | S37: =IF(A37="","",IFERROR(IF(OR(VLOOKUP(A37,AutoEvidence!$A$2:$G$400,2,FALSE())="Collected",VLOOKUP(A37,AutoEvidence!$A$2:$G$400,2,FALSE())="Partial"),VLOOKUP(A37,AutoEvidence!$A$2:$G$400,3,FALSE())&" ("&VLOOKUP(A37,AutoEvidence!$A$2:$G$400,2,FALSE())&")",VLOOKUP(A37,AutoEvidence!$A$2:$G$400,2,FALSE())),"")) | T37: =IF(A37="","",IFERROR(VLOOKUP(A37,AutoEvidence!$A$2:$G$400,4,FALSE())&"","")) | AB37: =IF(M37="Gap",1,IF(M37="OK",0,"")) | AC37: =IF(P37<>"",VALUE(RIGHT(P37,1))*1000+ROW(),"") | AD37: =IF(ISNUMBER(L37),MIN(L37,K37),"") | AE37: =IF(AND(ISNUMBER(SEARCH(" PA "," "&SUBSTITUTE($I37,","," ")&" ")),ISNUMBER($L37)),$L37,"") | AF37: =IF(AND(ISNUMBER(SEARCH(" PO "," "&SUBSTITUTE($I37,","," ")&" ")),ISNUMBER($L37)),$L37,"") | AG37: =IF(AND(ISNUMBER(SEARCH(" MFA "," "&SUBSTITUTE($I37,","," ")&" ")),ISNUMBER($L37)),$L37,"") | AH37: =IF(AND(ISNUMBER(SEARCH(" RAP "," "&SUBSTITUTE($I37,","," ")&" ")),ISNUMBER($L37)),$L37,"") | AI37: =IF(AND(ISNUMBER(SEARCH(" AC "," "&SUBSTITUTE($I37,","," ")&" ")),ISNUMBER($L37)),$L37,"") | AJ37: =IF(AND(ISNUMBER(SEARCH(" MAC "," "&SUBSTITUTE($I37,","," ")&" ")),ISNUMBER($L37)),$L37,"") | AK37: =IF(AND(ISNUMBER(SEARCH(" UAH "," "&SUBSTITUTE($I37,","," ")&" ")),ISNUMBER($L37)),$L37,"") | AL37: =IF(AND(ISNUMBER(SEARCH(" RB "," "&SUBSTITUTE($I37,","," ")&" ")),ISNUMBER($L37)),$L37,"")
A38: END-08 | B38: END | C38: Endpoint | D38: Local administrator restriction: users are not local admins; Windows LAPS on every device; documented elevation path (EPM / RMM / temporary) | E38: Local admin defeats application control, EDR tamper protection and macro settings (E8 RAP). | F38: Intune LAPS policy and report; Entra 'Local admin' settings; RMM script listing local Administrators group members | G38: Sample or script the local Administrators group across devices; LAPS coverage %; elevation request process exists and is used. | H38: No standard users as local admin; LAPS 100%. | I38: RAP | J38: BAU | K38: 2 | M38: =IF(ISNUMBER(L38),IF(L38<K38,"Gap","OK"),IF(L38="N/A","N/A","")) | P38: =IF(AND(M38="Gap",N38<>"",O38<>""),VLOOKUP(N38&O38,Lists!$H$4:$I$12,2,FALSE()),"") | Q38: =IF(AND(M38="Gap",O38="S",OR(N38="H",N38="M")),"Yes","") | R38: BAU | S38: =IF(A38="","",IFERROR(IF(OR(VLOOKUP(A38,AutoEvidence!$A$2:$G$400,2,FALSE())="Collected",VLOOKUP(A38,AutoEvidence!$A$2:$G$400,2,FALSE())="Partial"),VLOOKUP(A38,AutoEvidence!$A$2:$G$400,3,FALSE())&" ("&VLOOKUP(A38,AutoEvidence!$A$2:$G$400,2,FALSE())&")",VLOOKUP(A38,AutoEvidence!$A$2:$G$400,2,FALSE())),"")) | T38: =IF(A38="","",IFERROR(VLOOKUP(A38,AutoEvidence!$A$2:$G$400,4,FALSE())&"","")) | AB38: =IF(M38="Gap",1,IF(M38="OK",0,"")) | AC38: =IF(P38<>"",VALUE(RIGHT(P38,1))*1000+ROW(),"") | AD38: =IF(ISNUMBER(L38),MIN(L38,K38),"") | AE38: =IF(AND(ISNUMBER(SEARCH(" PA "," "&SUBSTITUTE($I38,","," ")&" ")),ISNUMBER($L38)),$L38,"") | AF38: =IF(AND(ISNUMBER(SEARCH(" PO "," "&SUBSTITUTE($I38,","," ")&" ")),ISNUMBER($L38)),$L38,"") | AG38: =IF(AND(ISNUMBER(SEARCH(" MFA "," "&SUBSTITUTE($I38,","," ")&" ")),ISNUMBER($L38)),$L38,"") | AH38: =IF(AND(ISNUMBER(SEARCH(" RAP "," "&SUBSTITUTE($I38,","," ")&" ")),ISNUMBER($L38)),$L38,"") | AI38: =IF(AND(ISNUMBER(SEARCH(" AC "," "&SUBSTITUTE($I38,","," ")&" ")),ISNUMBER($L38)),$L38,"") | AJ38: =IF(AND(ISNUMBER(SEARCH(" MAC "," "&SUBSTITUTE($I38,","," ")&" ")),ISNUMBER($L38)),$L38,"") | AK38: =IF(AND(ISNUMBER(SEARCH(" UAH "," "&SUBSTITUTE($I38,","," ")&" ")),ISNUMBER($L38)),$L38,"") | AL38: =IF(AND(ISNUMBER(SEARCH(" RB "," "&SUBSTITUTE($I38,","," ")&" ")),ISNUMBER($L38)),$L38,"")
A39: END-09 | B39: END | C39: Endpoint | D39: Application control on workstations (Airlock / WDAC / AppLocker): executables, scripts, installers, DLLs, HTA/CHM/CPL restricted; user profile and temp paths covered (E8 AC ML1) | E39: Application control is the E8 control with the highest ransomware-prevention value and the one most often missing. | F39: Airlock portal (portal.au.appenforcement.com); Intune WDAC/AppLocker policy; Airlock best-practice checklist | G39: Mode (audit vs enforce) per device group; % devices enforced; policy scope includes all E8 file types; blocked-event review process; exception handling documented. | H39: Enforced on all workstations for the E8 file types; audit-mode only as a time-boxed step. | I39: AC | J39: Billable | K39: 2 | M39: =IF(ISNUMBER(L39),IF(L39<K39,"Gap","OK"),IF(L39="N/A","N/A","")) | P39: =IF(AND(M39="Gap",N39<>"",O39<>""),VLOOKUP(N39&O39,Lists!$H$4:$I$12,2,FALSE()),"") | Q39: =IF(AND(M39="Gap",O39="S",OR(N39="H",N39="M")),"Yes","") | R39: Billable | S39: =IF(A39="","",IFERROR(IF(OR(VLOOKUP(A39,AutoEvidence!$A$2:$G$400,2,FALSE())="Collected",VLOOKUP(A39,AutoEvidence!$A$2:$G$400,2,FALSE())="Partial"),VLOOKUP(A39,AutoEvidence!$A$2:$G$400,3,FALSE())&" ("&VLOOKUP(A39,AutoEvidence!$A$2:$G$400,2,FALSE())&")",VLOOKUP(A39,AutoEvidence!$A$2:$G$400,2,FALSE())),"")) | T39: =IF(A39="","",IFERROR(VLOOKUP(A39,AutoEvidence!$A$2:$G$400,4,FALSE())&"","")) | AB39: =IF(M39="Gap",1,IF(M39="OK",0,"")) | AC39: =IF(P39<>"",VALUE(RIGHT(P39,1))*1000+ROW(),"") | AD39: =IF(ISNUMBER(L39),MIN(L39,K39),"") | AE39: =IF(AND(ISNUMBER(SEARCH(" PA "," "&SUBSTITUTE($I39,","," ")&" ")),ISNUMBER($L39)),$L39,"") | AF39: =IF(AND(ISNUMBER(SEARCH(" PO "," "&SUBSTITUTE($I39,","," ")&" ")),ISNUMBER($L39)),$L39,"") | AG39: =IF(AND(ISNUMBER(SEARCH(" MFA "," "&SUBSTITUTE($I39,","," ")&" ")),ISNUMBER($L39)),$L39,"") | AH39: =IF(AND(ISNUMBER(SEARCH(" RAP "," "&SUBSTITUTE($I39,","," ")&" ")),ISNUMBER($L39)),$L39,"") | AI39: =IF(AND(ISNUMBER(SEARCH(" AC "," "&SUBSTITUTE($I39,","," ")&" ")),ISNUMBER($L39)),$L39,"") | AJ39: =IF(AND(ISNUMBER(SEARCH(" MAC "," "&SUBSTITUTE($I39,","," ")&" ")),ISNUMBER($L39)),$L39,"") | AK39: =IF(AND(ISNUMBER(SEARCH(" UAH "," "&SUBSTITUTE($I39,","," ")&" ")),ISNUMBER($L39)),$L39,"") | AL39: =IF(AND(ISNUMBER(SEARCH(" RB "," "&SUBSTITUTE($I39,","," ")&" ")),ISNUMBER($L39)),$L39,"")
A40: END-10 | B40: END | C40: Endpoint | D40: Microsoft Office macros: blocked from the internet, disabled for users without business need, AV scanning on, settings locked (E8 MAC ML1); Win32 API calls blocked (ML2) | E40: Macro-borne malware is still a leading delivery mechanism; user-changeable settings make the control cosmetic. | F40: Intune Settings Catalog / GPO (Office macro policies); Defender ASR rule 'Block Win32 API calls from Office macros' | G40: Policies present and enforced for Word/Excel/PowerPoint/Access/Outlook: block macros from internet, disable all except digitally signed or per-group allow, prevent user override; ASR macro rules in block mode. | H40: All four ML1 requirements enforced; ML2 Win32 block on. | I40: MAC | J40: Value-add | K40: 2 | M40: =IF(ISNUMBER(L40),IF(L40<K40,"Gap","OK"),IF(L40="N/A","N/A","")) | P40: =IF(AND(M40="Gap",N40<>"",O40<>""),VLOOKUP(N40&O40,Lists!$H$4:$I$12,2,FALSE()),"") | Q40: =IF(AND(M40="Gap",O40="S",OR(N40="H",N40="M")),"Yes","") | R40: Value-add | S40: =IF(A40="","",IFERROR(IF(OR(VLOOKUP(A40,AutoEvidence!$A$2:$G$400,2,FALSE())="Collected",VLOOKUP(A40,AutoEvidence!$A$2:$G$400,2,FALSE())="Partial"),VLOOKUP(A40,AutoEvidence!$A$2:$G$400,3,FALSE())&" ("&VLOOKUP(A40,AutoEvidence!$A$2:$G$400,2,FALSE())&")",VLOOKUP(A40,AutoEvidence!$A$2:$G$400,2,FALSE())),"")) | T40: =IF(A40="","",IFERROR(VLOOKUP(A40,AutoEvidence!$A$2:$G$400,4,FALSE())&"","")) | AB40: =IF(M40="Gap",1,IF(M40="OK",0,"")) | AC40: =IF(P40<>"",VALUE(RIGHT(P40,1))*1000+ROW(),"") | AD40: =IF(ISNUMBER(L40),MIN(L40,K40),"") | AE40: =IF(AND(ISNUMBER(SEARCH(" PA "," "&SUBSTITUTE($I40,","," ")&" ")),ISNUMBER($L40)),$L40,"") | AF40: =IF(AND(ISNUMBER(SEARCH(" PO "," "&SUBSTITUTE($I40,","," ")&" ")),ISNUMBER($L40)),$L40,"") | AG40: =IF(AND(ISNUMBER(SEARCH(" MFA "," "&SUBSTITUTE($I40,","," ")&" ")),ISNUMBER($L40)),$L40,"") | AH40: =IF(AND(ISNUMBER(SEARCH(" RAP "," "&SUBSTITUTE($I40,","," ")&" ")),ISNUMBER($L40)),$L40,"") | AI40: =IF(AND(ISNUMBER(SEARCH(" AC "," "&SUBSTITUTE($I40,","," ")&" ")),ISNUMBER($L40)),$L40,"") | AJ40: =IF(AND(ISNUMBER(SEARCH(" MAC "," "&SUBSTITUTE($I40,","," ")&" ")),ISNUMBER($L40)),$L40,"") | AK40: =IF(AND(ISNUMBER(SEARCH(" UAH "," "&SUBSTITUTE($I40,","," ")&" ")),ISNUMBER($L40)),$L40,"") | AL40: =IF(AND(ISNUMBER(SEARCH(" RB "," "&SUBSTITUTE($I40,","," ")&" ")),ISNUMBER($L40)),$L40,"")
A41: END-11 | B41: END | C41: Endpoint | D41: User application hardening: browser hardening (no Java/ads from internet, settings locked), IE11 removed, ASR rules for Office/PDF child processes and injection, PowerShell v2 removed, script block/command-line logging (E8 UAH ML1/ML2) | E41: Closes the paths exploits and macros use to get from a document to a shell. | F41: Intune Settings Catalog (Edge/Chrome policies, ASR rules); Defender ASR report; GPO | G41: ASR rules 'Block Office child processes / executable content / injection / OLE', 'Block Adobe Reader child processes' in block mode; browser policies enforced; IE11 and PowerShell 2.0 feature disabled; PowerShell logging to SIEM. | H41: ML1 browser controls + core ASR rules in block mode; logging on. | I41: UAH | J41: Value-add | K41: 2 | M41: =IF(ISNUMBER(L41),IF(L41<K41,"Gap","OK"),IF(L41="N/A","N/A","")) | P41: =IF(AND(M41="Gap",N41<>"",O41<>""),VLOOKUP(N41&O41,Lists!$H$4:$I$12,2,FALSE()),"") | Q41: =IF(AND(M41="Gap",O41="S",OR(N41="H",N41="M")),"Yes","") | R41: Value-add | S41: =IF(A41="","",IFERROR(IF(OR(VLOOKUP(A41,AutoEvidence!$A$2:$G$400,2,FALSE())="Collected",VLOOKUP(A41,AutoEvidence!$A$2:$G$400,2,FALSE())="Partial"),VLOOKUP(A41,AutoEvidence!$A$2:$G$400,3,FALSE())&" ("&VLOOKUP(A41,AutoEvidence!$A$2:$G$400,2,FALSE())&")",VLOOKUP(A41,AutoEvidence!$A$2:$G$400,2,FALSE())),"")) | T41: =IF(A41="","",IFERROR(VLOOKUP(A41,AutoEvidence!$A$2:$G$400,4,FALSE())&"","")) | AB41: =IF(M41="Gap",1,IF(M41="OK",0,"")) | AC41: =IF(P41<>"",VALUE(RIGHT(P41,1))*1000+ROW(),"") | AD41: =IF(ISNUMBER(L41),MIN(L41,K41),"") | AE41: =IF(AND(ISNUMBER(SEARCH(" PA "," "&SUBSTITUTE($I41,","," ")&" ")),ISNUMBER($L41)),$L41,"") | AF41: =IF(AND(ISNUMBER(SEARCH(" PO "," "&SUBSTITUTE($I41,","," ")&" ")),ISNUMBER($L41)),$L41,"") | AG41: =IF(AND(ISNUMBER(SEARCH(" MFA "," "&SUBSTITUTE($I41,","," ")&" ")),ISNUMBER($L41)),$L41,"") | AH41: =IF(AND(ISNUMBER(SEARCH(" RAP "," "&SUBSTITUTE($I41,","," ")&" ")),ISNUMBER($L41)),$L41,"") | AI41: =IF(AND(ISNUMBER(SEARCH(" AC "," "&SUBSTITUTE($I41,","," ")&" ")),ISNUMBER($L41)),$L41,"") | AJ41: =IF(AND(ISNUMBER(SEARCH(" MAC "," "&SUBSTITUTE($I41,","," ")&" ")),ISNUMBER($L41)),$L41,"") | AK41: =IF(AND(ISNUMBER(SEARCH(" UAH "," "&SUBSTITUTE($I41,","," ")&" ")),ISNUMBER($L41)),$L41,"") | AL41: =IF(AND(ISNUMBER(SEARCH(" RB "," "&SUBSTITUTE($I41,","," ")&" ")),ISNUMBER($L41)),$L41,"")
A42: END-12 | B42: END | C42: Endpoint | D42: Compliance policies integrated with Conditional Access: encryption, AV, firewall, OS minimum, Defender risk score; non-compliant device count and grace periods | E42: Compliance policies make device state enforceable through CA rather than advisory. | F42: Intune > Devices > Compliance policies and report; CA 'Require compliant device' policy | G42: Policies exist per platform; non-compliant % and reasons; grace period <= 7 days; CA actually references compliance. | H42: < 5% non-compliant; CA-enforced. | J42: Value-add | K42: 2 | M42: =IF(ISNUMBER(L42),IF(L42<K42,"Gap","OK"),IF(L42="N/A","N/A","")) | P42: =IF(AND(M42="Gap",N42<>"",O42<>""),VLOOKUP(N42&O42,Lists!$H$4:$I$12,2,FALSE()),"") | Q42: =IF(AND(M42="Gap",O42="S",OR(N42="H",N42="M")),"Yes","") | R42: Value-add | S42: =IF(A42="","",IFERROR(IF(OR(VLOOKUP(A42,AutoEvidence!$A$2:$G$400,2,FALSE())="Collected",VLOOKUP(A42,AutoEvidence!$A$2:$G$400,2,FALSE())="Partial"),VLOOKUP(A42,AutoEvidence!$A$2:$G$400,3,FALSE())&" ("&VLOOKUP(A42,AutoEvidence!$A$2:$G$400,2,FALSE())&")",VLOOKUP(A42,AutoEvidence!$A$2:$G$400,2,FALSE())),"")) | T42: =IF(A42="","",IFERROR(VLOOKUP(A42,AutoEvidence!$A$2:$G$400,4,FALSE())&"","")) | AB42: =IF(M42="Gap",1,IF(M42="OK",0,"")) | AC42: =IF(P42<>"",VALUE(RIGHT(P42,1))*1000+ROW(),"") | AD42: =IF(ISNUMBER(L42),MIN(L42,K42),"") | AE42: =IF(AND(ISNUMBER(SEARCH(" PA "," "&SUBSTITUTE($I42,","," ")&" ")),ISNUMBER($L42)),$L42,"") | AF42: =IF(AND(ISNUMBER(SEARCH(" PO "," "&SUBSTITUTE($I42,","," ")&" ")),ISNUMBER($L42)),$L42,"") | AG42: =IF(AND(ISNUMBER(SEARCH(" MFA "," "&SUBSTITUTE($I42,","," ")&" ")),ISNUMBER($L42)),$L42,"") | AH42: =IF(AND(ISNUMBER(SEARCH(" RAP "," "&SUBSTITUTE($I42,","," ")&" ")),ISNUMBER($L42)),$L42,"") | AI42: =IF(AND(ISNUMBER(SEARCH(" AC "," "&SUBSTITUTE($I42,","," ")&" ")),ISNUMBER($L42)),$L42,"") | AJ42: =IF(AND(ISNUMBER(SEARCH(" MAC "," "&SUBSTITUTE($I42,","," ")&" ")),ISNUMBER($L42)),$L42,"") | AK42: =IF(AND(ISNUMBER(SEARCH(" UAH "," "&SUBSTITUTE($I42,","," ")&" ")),ISNUMBER($L42)),$L42,"") | AL42: =IF(AND(ISNUMBER(SEARCH(" RB "," "&SUBSTITUTE($I42,","," ")&" ")),ISNUMBER($L42)),$L42,"")
A43: END-13 | B43: END | C43: Endpoint | D43: Provisioning and SOE: Autopilot registration for new devices, baseline profile documented, naming standard, Autopilot & Intune best-practice checklist applied | E43: Consistent builds are the foundation for every other endpoint control and cut ticket volume. | F43: Intune > Enrollment > Windows Autopilot; SOE doc in SNOW KB/SharePoint; bA Autopilot & Intune checklist | G43: Autopilot profile assigned; ESP configured; hardware hash registration process with the reseller; SOE document current; deviations from the bA checklist justified. | H43: Autopilot in use; SOE documented < 12 months old. | J43: Value-add | K43: 2 | M43: =IF(ISNUMBER(L43),IF(L43<K43,"Gap","OK"),IF(L43="N/A","N/A","")) | P43: =IF(AND(M43="Gap",N43<>"",O43<>""),VLOOKUP(N43&O43,Lists!$H$4:$I$12,2,FALSE()),"") | Q43: =IF(AND(M43="Gap",O43="S",OR(N43="H",N43="M")),"Yes","") | R43: Value-add | S43: =IF(A43="","",IFERROR(IF(OR(VLOOKUP(A43,AutoEvidence!$A$2:$G$400,2,FALSE())="Collected",VLOOKUP(A43,AutoEvidence!$A$2:$G$400,2,FALSE())="Partial"),VLOOKUP(A43,AutoEvidence!$A$2:$G$400,3,FALSE())&" ("&VLOOKUP(A43,AutoEvidence!$A$2:$G$400,2,FALSE())&")",VLOOKUP(A43,AutoEvidence!$A$2:$G$400,2,FALSE())),"")) | T43: =IF(A43="","",IFERROR(VLOOKUP(A43,AutoEvidence!$A$2:$G$400,4,FALSE())&"","")) | AB43: =IF(M43="Gap",1,IF(M43="OK",0,"")) | AC43: =IF(P43<>"",VALUE(RIGHT(P43,1))*1000+ROW(),"") | AD43: =IF(ISNUMBER(L43),MIN(L43,K43),"") | AE43: =IF(AND(ISNUMBER(SEARCH(" PA "," "&SUBSTITUTE($I43,","," ")&" ")),ISNUMBER($L43)),$L43,"") | AF43: =IF(AND(ISNUMBER(SEARCH(" PO "," "&SUBSTITUTE($I43,","," ")&" ")),ISNUMBER($L43)),$L43,"") | AG43: =IF(AND(ISNUMBER(SEARCH(" MFA "," "&SUBSTITUTE($I43,","," ")&" ")),ISNUMBER($L43)),$L43,"") | AH43: =IF(AND(ISNUMBER(SEARCH(" RAP "," "&SUBSTITUTE($I43,","," ")&" ")),ISNUMBER($L43)),$L43,"") | AI43: =IF(AND(ISNUMBER(SEARCH(" AC "," "&SUBSTITUTE($I43,","," ")&" ")),ISNUMBER($L43)),$L43,"") | AJ43: =IF(AND(ISNUMBER(SEARCH(" MAC "," "&SUBSTITUTE($I43,","," ")&" ")),ISNUMBER($L43)),$L43,"") | AK43: =IF(AND(ISNUMBER(SEARCH(" UAH "," "&SUBSTITUTE($I43,","," ")&" ")),ISNUMBER($L43)),$L43,"") | AL43: =IF(AND(ISNUMBER(SEARCH(" RB "," "&SUBSTITUTE($I43,","," ")&" ")),ISNUMBER($L43)),$L43,"")
A44: END-14 | B44: END | C44: Endpoint | D44: Mobile devices: iOS/Android access controlled by MAM/app protection (or MDM), PIN/biometric, selective wipe tested, BYOD stance documented | E44: Corporate mail on unmanaged phones is the most common uncontrolled data copy. | F44: Intune > Apps > App protection policies; CA 'Require app protection policy'; Intune mobile device list | G44: App protection policy targeting Outlook/Teams/OneDrive on both platforms; CA enforcing it; % of mobile sign-ins from protected apps. | H44: App protection enforced via CA for all mobile access. | J44: Value-add | K44: 2 | M44: =IF(ISNUMBER(L44),IF(L44<K44,"Gap","OK"),IF(L44="N/A","N/A","")) | P44: =IF(AND(M44="Gap",N44<>"",O44<>""),VLOOKUP(N44&O44,Lists!$H$4:$I$12,2,FALSE()),"") | Q44: =IF(AND(M44="Gap",O44="S",OR(N44="H",N44="M")),"Yes","") | R44: Value-add | S44: =IF(A44="","",IFERROR(IF(OR(VLOOKUP(A44,AutoEvidence!$A$2:$G$400,2,FALSE())="Collected",VLOOKUP(A44,AutoEvidence!$A$2:$G$400,2,FALSE())="Partial"),VLOOKUP(A44,AutoEvidence!$A$2:$G$400,3,FALSE())&" ("&VLOOKUP(A44,AutoEvidence!$A$2:$G$400,2,FALSE())&")",VLOOKUP(A44,AutoEvidence!$A$2:$G$400,2,FALSE())),"")) | T44: =IF(A44="","",IFERROR(VLOOKUP(A44,AutoEvidence!$A$2:$G$400,4,FALSE())&"","")) | AB44: =IF(M44="Gap",1,IF(M44="OK",0,"")) | AC44: =IF(P44<>"",VALUE(RIGHT(P44,1))*1000+ROW(),"") | AD44: =IF(ISNUMBER(L44),MIN(L44,K44),"") | AE44: =IF(AND(ISNUMBER(SEARCH(" PA "," "&SUBSTITUTE($I44,","," ")&" ")),ISNUMBER($L44)),$L44,"") | AF44: =IF(AND(ISNUMBER(SEARCH(" PO "," "&SUBSTITUTE($I44,","," ")&" ")),ISNUMBER($L44)),$L44,"") | AG44: =IF(AND(ISNUMBER(SEARCH(" MFA "," "&SUBSTITUTE($I44,","," ")&" ")),ISNUMBER($L44)),$L44,"") | AH44: =IF(AND(ISNUMBER(SEARCH(" RAP "," "&SUBSTITUTE($I44,","," ")&" ")),ISNUMBER($L44)),$L44,"") | AI44: =IF(AND(ISNUMBER(SEARCH(" AC "," "&SUBSTITUTE($I44,","," ")&" ")),ISNUMBER($L44)),$L44,"") | AJ44: =IF(AND(ISNUMBER(SEARCH(" MAC "," "&SUBSTITUTE($I44,","," ")&" ")),ISNUMBER($L44)),$L44,"") | AK44: =IF(AND(ISNUMBER(SEARCH(" UAH "," "&SUBSTITUTE($I44,","," ")&" ")),ISNUMBER($L44)),$L44,"") | AL44: =IF(AND(ISNUMBER(SEARCH(" RB "," "&SUBSTITUTE($I44,","," ")&" ")),ISNUMBER($L44)),$L44,"")
A45: END-15 | B45: END | C45: Endpoint | D45: Peripheral and host controls: USB removable storage policy, Windows Firewall enforced on all profiles, screen lock <= 15 min, printer driver policy (Point and Print restrictions) | E45: Cheap controls that close common audit findings and lateral-movement paths. | F45: Intune Settings Catalog / GPO; Defender device control policy | G45: Check policy presence and assignment; sample a device for effective settings (Get-NetFirewallProfile, device control events). | H45: Policies deployed to all devices. | I45: UAH | J45: Value-add | K45: 2 | M45: =IF(ISNUMBER(L45),IF(L45<K45,"Gap","OK"),IF(L45="N/A","N/A","")) | P45: =IF(AND(M45="Gap",N45<>"",O45<>""),VLOOKUP(N45&O45,Lists!$H$4:$I$12,2,FALSE()),"") | Q45: =IF(AND(M45="Gap",O45="S",OR(N45="H",N45="M")),"Yes","") | R45: Value-add | S45: =IF(A45="","",IFERROR(IF(OR(VLOOKUP(A45,AutoEvidence!$A$2:$G$400,2,FALSE())="Collected",VLOOKUP(A45,AutoEvidence!$A$2:$G$400,2,FALSE())="Partial"),VLOOKUP(A45,AutoEvidence!$A$2:$G$400,3,FALSE())&" ("&VLOOKUP(A45,AutoEvidence!$A$2:$G$400,2,FALSE())&")",VLOOKUP(A45,AutoEvidence!$A$2:$G$400,2,FALSE())),"")) | T45: =IF(A45="","",IFERROR(VLOOKUP(A45,AutoEvidence!$A$2:$G$400,4,FALSE())&"","")) | AB45: =IF(M45="Gap",1,IF(M45="OK",0,"")) | AC45: =IF(P45<>"",VALUE(RIGHT(P45,1))*1000+ROW(),"") | AD45: =IF(ISNUMBER(L45),MIN(L45,K45),"") | AE45: =IF(AND(ISNUMBER(SEARCH(" PA "," "&SUBSTITUTE($I45,","," ")&" ")),ISNUMBER($L45)),$L45,"") | AF45: =IF(AND(ISNUMBER(SEARCH(" PO "," "&SUBSTITUTE($I45,","," ")&" ")),ISNUMBER($L45)),$L45,"") | AG45: =IF(AND(ISNUMBER(SEARCH(" MFA "," "&SUBSTITUTE($I45,","," ")&" ")),ISNUMBER($L45)),$L45,"") | AH45: =IF(AND(ISNUMBER(SEARCH(" RAP "," "&SUBSTITUTE($I45,","," ")&" ")),ISNUMBER($L45)),$L45,"") | AI45: =IF(AND(ISNUMBER(SEARCH(" AC "," "&SUBSTITUTE($I45,","," ")&" ")),ISNUMBER($L45)),$L45,"") | AJ45: =IF(AND(ISNUMBER(SEARCH(" MAC "," "&SUBSTITUTE($I45,","," ")&" ")),ISNUMBER($L45)),$L45,"") | AK45: =IF(AND(ISNUMBER(SEARCH(" UAH "," "&SUBSTITUTE($I45,","," ")&" ")),ISNUMBER($L45)),$L45,"") | AL45: =IF(AND(ISNUMBER(SEARCH(" RB "," "&SUBSTITUTE($I45,","," ")&" ")),ISNUMBER($L45)),$L45,"")
A46: END-16 | B46: END | C46: Endpoint | D46: Endpoint lifecycle: device age, warranty status, Windows 11 ineligible units, refresh plan and budget signalled to SDM/CAM | E46: Ageing fleets generate tickets and block OS currency; refresh is billable project work. | F46: Intune/RMM hardware inventory; Dell/HP warranty lookups; LIC-01 register | G46: Count devices > 5 years or out of warranty; map to refresh year; raise as eFO lead if no plan exists. | H46: Register exists; refresh plan agreed; no device > 6 years in production. | J46: Billable | K46: 2 | M46: =IF(ISNUMBER(L46),IF(L46<K46,"Gap","OK"),IF(L46="N/A","N/A","")) | P46: =IF(AND(M46="Gap",N46<>"",O46<>""),VLOOKUP(N46&O46,Lists!$H$4:$I$12,2,FALSE()),"") | Q46: =IF(AND(M46="Gap",O46="S",OR(N46="H",N46="M")),"Yes","") | R46: Billable | S46: =IF(A46="","",IFERROR(IF(OR(VLOOKUP(A46,AutoEvidence!$A$2:$G$400,2,FALSE())="Collected",VLOOKUP(A46,AutoEvidence!$A$2:$G$400,2,FALSE())="Partial"),VLOOKUP(A46,AutoEvidence!$A$2:$G$400,3,FALSE())&" ("&VLOOKUP(A46,AutoEvidence!$A$2:$G$400,2,FALSE())&")",VLOOKUP(A46,AutoEvidence!$A$2:$G$400,2,FALSE())),"")) | T46: =IF(A46="","",IFERROR(VLOOKUP(A46,AutoEvidence!$A$2:$G$400,4,FALSE())&"","")) | AB46: =IF(M46="Gap",1,IF(M46="OK",0,"")) | AC46: =IF(P46<>"",VALUE(RIGHT(P46,1))*1000+ROW(),"") | AD46: =IF(ISNUMBER(L46),MIN(L46,K46),"") | AE46: =IF(AND(ISNUMBER(SEARCH(" PA "," "&SUBSTITUTE($I46,","," ")&" ")),ISNUMBER($L46)),$L46,"") | AF46: =IF(AND(ISNUMBER(SEARCH(" PO "," "&SUBSTITUTE($I46,","," ")&" ")),ISNUMBER($L46)),$L46,"") | AG46: =IF(AND(ISNUMBER(SEARCH(" MFA "," "&SUBSTITUTE($I46,","," ")&" ")),ISNUMBER($L46)),$L46,"") | AH46: =IF(AND(ISNUMBER(SEARCH(" RAP "," "&SUBSTITUTE($I46,","," ")&" ")),ISNUMBER($L46)),$L46,"") | AI46: =IF(AND(ISNUMBER(SEARCH(" AC "," "&SUBSTITUTE($I46,","," ")&" ")),ISNUMBER($L46)),$L46,"") | AJ46: =IF(AND(ISNUMBER(SEARCH(" MAC "," "&SUBSTITUTE($I46,","," ")&" ")),ISNUMBER($L46)),$L46,"") | AK46: =IF(AND(ISNUMBER(SEARCH(" UAH "," "&SUBSTITUTE($I46,","," ")&" ")),ISNUMBER($L46)),$L46,"") | AL46: =IF(AND(ISNUMBER(SEARCH(" RB "," "&SUBSTITUTE($I46,","," ")&" ")),ISNUMBER($L46)),$L46,"")
A47: SRV-01 | B47: SRV | C47: Servers & Virtualisation | D47: Server inventory accurate across SNOW CIs, eFO, Orion and vCenter/emPOWER: counts match, IP/NAT IP present, role and owner documented | E47: CI gaps break monitoring, billing and P1 response (handbook: CI discrepancies form). | F47: SNOW CI list (customer account); eFO Cloud Services; Orion node list; vminfo.empowercloud.net.au; vCenter | G47: Export each list; diff hostnames; note CIs missing IP/NAT IP; raise 'Add Configuration Item to Account' requests for fixes. | H47: Zero unexplained differences; all CIs complete. | J47: BAU | K47: 2 | M47: =IF(ISNUMBER(L47),IF(L47<K47,"Gap","OK"),IF(L47="N/A","N/A","")) | P47: =IF(AND(M47="Gap",N47<>"",O47<>""),VLOOKUP(N47&O47,Lists!$H$4:$I$12,2,FALSE()),"") | Q47: =IF(AND(M47="Gap",O47="S",OR(N47="H",N47="M")),"Yes","") | R47: BAU | S47: =IF(A47="","",IFERROR(IF(OR(VLOOKUP(A47,AutoEvidence!$A$2:$G$400,2,FALSE())="Collected",VLOOKUP(A47,AutoEvidence!$A$2:$G$400,2,FALSE())="Partial"),VLOOKUP(A47,AutoEvidence!$A$2:$G$400,3,FALSE())&" ("&VLOOKUP(A47,AutoEvidence!$A$2:$G$400,2,FALSE())&")",VLOOKUP(A47,AutoEvidence!$A$2:$G$400,2,FALSE())),"")) | T47: =IF(A47="","",IFERROR(VLOOKUP(A47,AutoEvidence!$A$2:$G$400,4,FALSE())&"","")) | AB47: =IF(M47="Gap",1,IF(M47="OK",0,"")) | AC47: =IF(P47<>"",VALUE(RIGHT(P47,1))*1000+ROW(),"") | AD47: =IF(ISNUMBER(L47),MIN(L47,K47),"") | AE47: =IF(AND(ISNUMBER(SEARCH(" PA "," "&SUBSTITUTE($I47,","," ")&" ")),ISNUMBER($L47)),$L47,"") | AF47: =IF(AND(ISNUMBER(SEARCH(" PO "," "&SUBSTITUTE($I47,","," ")&" ")),ISNUMBER($L47)),$L47,"") | AG47: =IF(AND(ISNUMBER(SEARCH(" MFA "," "&SUBSTITUTE($I47,","," ")&" ")),ISNUMBER($L47)),$L47,"") | AH47: =IF(AND(ISNUMBER(SEARCH(" RAP "," "&SUBSTITUTE($I47,","," ")&" ")),ISNUMBER($L47)),$L47,"") | AI47: =IF(AND(ISNUMBER(SEARCH(" AC "," "&SUBSTITUTE($I47,","," ")&" ")),ISNUMBER($L47)),$L47,"") | AJ47: =IF(AND(ISNUMBER(SEARCH(" MAC "," "&SUBSTITUTE($I47,","," ")&" ")),ISNUMBER($L47)),$L47,"") | AK47: =IF(AND(ISNUMBER(SEARCH(" UAH "," "&SUBSTITUTE($I47,","," ")&" ")),ISNUMBER($L47)),$L47,"") | AL47: =IF(AND(ISNUMBER(SEARCH(" RB "," "&SUBSTITUTE($I47,","," ")&" ")),ISNUMBER($L47)),$L47,"")
A48: SRV-02 | B48: SRV | C48: Servers & Virtualisation | D48: Server OS support status: no Windows Server 2012/2012 R2 (ESU ends Oct 2026), Server 2016 plan (EoS 12 Jan 2027), Server 2022 mainstream ends 13 Oct 2026; Linux distros in support | E48: Unsupported OS breaches E8 PO ML1 and cyber-insurance conditions; 2016 is the next cliff for most clients. | F48: N-Central OS report; vCenter guest OS; SNOW CIs; Microsoft Lifecycle (learn.microsoft.com/lifecycle) | G48: List servers by OS/version; flag anything past EoS or within 12 months; for each, note the app it hosts and the upgrade/migrate/decom option. | H48: No EoS OS; migration plan with dates for anything within 12 months. | I48: PO | J48: Billable | K48: 2 | M48: =IF(ISNUMBER(L48),IF(L48<K48,"Gap","OK"),IF(L48="N/A","N/A","")) | P48: =IF(AND(M48="Gap",N48<>"",O48<>""),VLOOKUP(N48&O48,Lists!$H$4:$I$12,2,FALSE()),"") | Q48: =IF(AND(M48="Gap",O48="S",OR(N48="H",N48="M")),"Yes","") | R48: Billable | S48: =IF(A48="","",IFERROR(IF(OR(VLOOKUP(A48,AutoEvidence!$A$2:$G$400,2,FALSE())="Collected",VLOOKUP(A48,AutoEvidence!$A$2:$G$400,2,FALSE())="Partial"),VLOOKUP(A48,AutoEvidence!$A$2:$G$400,3,FALSE())&" ("&VLOOKUP(A48,AutoEvidence!$A$2:$G$400,2,FALSE())&")",VLOOKUP(A48,AutoEvidence!$A$2:$G$400,2,FALSE())),"")) | T48: =IF(A48="","",IFERROR(VLOOKUP(A48,AutoEvidence!$A$2:$G$400,4,FALSE())&"","")) | AB48: =IF(M48="Gap",1,IF(M48="OK",0,"")) | AC48: =IF(P48<>"",VALUE(RIGHT(P48,1))*1000+ROW(),"") | AD48: =IF(ISNUMBER(L48),MIN(L48,K48),"") | AE48: =IF(AND(ISNUMBER(SEARCH(" PA "," "&SUBSTITUTE($I48,","," ")&" ")),ISNUMBER($L48)),$L48,"") | AF48: =IF(AND(ISNUMBER(SEARCH(" PO "," "&SUBSTITUTE($I48,","," ")&" ")),ISNUMBER($L48)),$L48,"") | AG48: =IF(AND(ISNUMBER(SEARCH(" MFA "," "&SUBSTITUTE($I48,","," ")&" ")),ISNUMBER($L48)),$L48,"") | AH48: =IF(AND(ISNUMBER(SEARCH(" RAP "," "&SUBSTITUTE($I48,","," ")&" ")),ISNUMBER($L48)),$L48,"") | AI48: =IF(AND(ISNUMBER(SEARCH(" AC "," "&SUBSTITUTE($I48,","," ")&" ")),ISNUMBER($L48)),$L48,"") | AJ48: =IF(AND(ISNUMBER(SEARCH(" MAC "," "&SUBSTITUTE($I48,","," ")&" ")),ISNUMBER($L48)),$L48,"") | AK48: =IF(AND(ISNUMBER(SEARCH(" UAH "," "&SUBSTITUTE($I48,","," ")&" ")),ISNUMBER($L48)),$L48,"") | AL48: =IF(AND(ISNUMBER(SEARCH(" RB "," "&SUBSTITUTE($I48,","," ")&" ")),ISNUMBER($L48)),$L48,"")
A49: SRV-03 | B49: SRV | C49: Servers & Virtualisation | D49: Server patch compliance: monthly cadence within 1 month (E8 ML1), internet-facing within 48 h for critical/exploited; maintenance windows agreed; failed/pending reboots | E49: Servers are patched less consistently than endpoints and are the higher-value target. | F49: N-Central patch status by server; change records for patch windows; STACK.md maintenance window | G49: % servers on current month's updates; servers with failed patches or pending reboot > 30 days; documented approval and window per client. | H49: >= 95% within 30 days; windows documented; exceptions listed. | I49: PO | J49: BAU | K49: 2 | M49: =IF(ISNUMBER(L49),IF(L49<K49,"Gap","OK"),IF(L49="N/A","N/A","")) | P49: =IF(AND(M49="Gap",N49<>"",O49<>""),VLOOKUP(N49&O49,Lists!$H$4:$I$12,2,FALSE()),"") | Q49: =IF(AND(M49="Gap",O49="S",OR(N49="H",N49="M")),"Yes","") | R49: BAU | S49: =IF(A49="","",IFERROR(IF(OR(VLOOKUP(A49,AutoEvidence!$A$2:$G$400,2,FALSE())="Collected",VLOOKUP(A49,AutoEvidence!$A$2:$G$400,2,FALSE())="Partial"),VLOOKUP(A49,AutoEvidence!$A$2:$G$400,3,FALSE())&" ("&VLOOKUP(A49,AutoEvidence!$A$2:$G$400,2,FALSE())&")",VLOOKUP(A49,AutoEvidence!$A$2:$G$400,2,FALSE())),"")) | T49: =IF(A49="","",IFERROR(VLOOKUP(A49,AutoEvidence!$A$2:$G$400,4,FALSE())&"","")) | AB49: =IF(M49="Gap",1,IF(M49="OK",0,"")) | AC49: =IF(P49<>"",VALUE(RIGHT(P49,1))*1000+ROW(),"") | AD49: =IF(ISNUMBER(L49),MIN(L49,K49),"") | AE49: =IF(AND(ISNUMBER(SEARCH(" PA "," "&SUBSTITUTE($I49,","," ")&" ")),ISNUMBER($L49)),$L49,"") | AF49: =IF(AND(ISNUMBER(SEARCH(" PO "," "&SUBSTITUTE($I49,","," ")&" ")),ISNUMBER($L49)),$L49,"") | AG49: =IF(AND(ISNUMBER(SEARCH(" MFA "," "&SUBSTITUTE($I49,","," ")&" ")),ISNUMBER($L49)),$L49,"") | AH49: =IF(AND(ISNUMBER(SEARCH(" RAP "," "&SUBSTITUTE($I49,","," ")&" ")),ISNUMBER($L49)),$L49,"") | AI49: =IF(AND(ISNUMBER(SEARCH(" AC "," "&SUBSTITUTE($I49,","," ")&" ")),ISNUMBER($L49)),$L49,"") | AJ49: =IF(AND(ISNUMBER(SEARCH(" MAC "," "&SUBSTITUTE($I49,","," ")&" ")),ISNUMBER($L49)),$L49,"") | AK49: =IF(AND(ISNUMBER(SEARCH(" UAH "," "&SUBSTITUTE($I49,","," ")&" ")),ISNUMBER($L49)),$L49,"") | AL49: =IF(AND(ISNUMBER(SEARCH(" RB "," "&SUBSTITUTE($I49,","," ")&" ")),ISNUMBER($L49)),$L49,"")
A50: SRV-04 | B50: SRV | C50: Servers & Virtualisation | D50: Server hardening baseline: CIS/Microsoft baseline, SMBv1 off, TLS 1.0/1.1 off, RDP not internet-exposed + NLA, EDR on servers, unnecessary roles removed, application control on internet-facing servers (E8 ML2) | E50: Default builds carry known-weak protocols; internet-facing servers are the E8 ML2 application-control scope. | F50: RMM script/CIS-CAT output; GPO baseline; EDR console (server coverage); firewall NAT rules | G50: Sample tier-0/internet-facing servers: protocol settings, EDR presence, listening services, local admin membership; check external NAT rules for RDP/SMB. | H50: Baseline applied and evidenced; no exposed RDP; EDR 100% on servers. | I50: AC, RAP | J50: Value-add | K50: 2 | M50: =IF(ISNUMBER(L50),IF(L50<K50,"Gap","OK"),IF(L50="N/A","N/A","")) | P50: =IF(AND(M50="Gap",N50<>"",O50<>""),VLOOKUP(N50&O50,Lists!$H$4:$I$12,2,FALSE()),"") | Q50: =IF(AND(M50="Gap",O50="S",OR(N50="H",N50="M")),"Yes","") | R50: Value-add | S50: =IF(A50="","",IFERROR(IF(OR(VLOOKUP(A50,AutoEvidence!$A$2:$G$400,2,FALSE())="Collected",VLOOKUP(A50,AutoEvidence!$A$2:$G$400,2,FALSE())="Partial"),VLOOKUP(A50,AutoEvidence!$A$2:$G$400,3,FALSE())&" ("&VLOOKUP(A50,AutoEvidence!$A$2:$G$400,2,FALSE())&")",VLOOKUP(A50,AutoEvidence!$A$2:$G$400,2,FALSE())),"")) | T50: =IF(A50="","",IFERROR(VLOOKUP(A50,AutoEvidence!$A$2:$G$400,4,FALSE())&"","")) | AB50: =IF(M50="Gap",1,IF(M50="OK",0,"")) | AC50: =IF(P50<>"",VALUE(RIGHT(P50,1))*1000+ROW(),"") | AD50: =IF(ISNUMBER(L50),MIN(L50,K50),"") | AE50: =IF(AND(ISNUMBER(SEARCH(" PA "," "&SUBSTITUTE($I50,","," ")&" ")),ISNUMBER($L50)),$L50,"") | AF50: =IF(AND(ISNUMBER(SEARCH(" PO "," "&SUBSTITUTE($I50,","," ")&" ")),ISNUMBER($L50)),$L50,"") | AG50: =IF(AND(ISNUMBER(SEARCH(" MFA "," "&SUBSTITUTE($I50,","," ")&" ")),ISNUMBER($L50)),$L50,"") | AH50: =IF(AND(ISNUMBER(SEARCH(" RAP "," "&SUBSTITUTE($I50,","," ")&" ")),ISNUMBER($L50)),$L50,"") | AI50: =IF(AND(ISNUMBER(SEARCH(" AC "," "&SUBSTITUTE($I50,","," ")&" ")),ISNUMBER($L50)),$L50,"") | AJ50: =IF(AND(ISNUMBER(SEARCH(" MAC "," "&SUBSTITUTE($I50,","," ")&" ")),ISNUMBER($L50)),$L50,"") | AK50: =IF(AND(ISNUMBER(SEARCH(" UAH "," "&SUBSTITUTE($I50,","," ")&" ")),ISNUMBER($L50)),$L50,"") | AL50: =IF(AND(ISNUMBER(SEARCH(" RB "," "&SUBSTITUTE($I50,","," ")&" ")),ISNUMBER($L50)),$L50,"")
A51: SRV-05 | B51: SRV | C51: Servers & Virtualisation | D51: Privileged access to servers: admin via jump host/RDM with CyberArk-sourced credentials, no direct RDP from user VLAN, tiered admin accounts, gMSA/managed service accounts | E51: E8 ML2 requires jump servers and separate privileged environments; flat admin access is how ransomware spreads. | F51: Firewall policy (user VLAN -> server RDP); RDM/CyberArk configuration; AD admin group membership; Protected Users | G51: Check firewall rule for RDP from user subnets; list Domain Admins/Enterprise Admins (should be <= 5, all dedicated accounts); service accounts with interactive logon rights. | H51: Jump-host-only admin, dedicated tiered accounts, DA <= 5. | I51: RAP | J51: Value-add | K51: 2 | M51: =IF(ISNUMBER(L51),IF(L51<K51,"Gap","OK"),IF(L51="N/A","N/A","")) | P51: =IF(AND(M51="Gap",N51<>"",O51<>""),VLOOKUP(N51&O51,Lists!$H$4:$I$12,2,FALSE()),"") | Q51: =IF(AND(M51="Gap",O51="S",OR(N51="H",N51="M")),"Yes","") | R51: Value-add | S51: =IF(A51="","",IFERROR(IF(OR(VLOOKUP(A51,AutoEvidence!$A$2:$G$400,2,FALSE())="Collected",VLOOKUP(A51,AutoEvidence!$A$2:$G$400,2,FALSE())="Partial"),VLOOKUP(A51,AutoEvidence!$A$2:$G$400,3,FALSE())&" ("&VLOOKUP(A51,AutoEvidence!$A$2:$G$400,2,FALSE())&")",VLOOKUP(A51,AutoEvidence!$A$2:$G$400,2,FALSE())),"")) | T51: =IF(A51="","",IFERROR(VLOOKUP(A51,AutoEvidence!$A$2:$G$400,4,FALSE())&"","")) | AB51: =IF(M51="Gap",1,IF(M51="OK",0,"")) | AC51: =IF(P51<>"",VALUE(RIGHT(P51,1))*1000+ROW(),"") | AD51: =IF(ISNUMBER(L51),MIN(L51,K51),"") | AE51: =IF(AND(ISNUMBER(SEARCH(" PA "," "&SUBSTITUTE($I51,","," ")&" ")),ISNUMBER($L51)),$L51,"") | AF51: =IF(AND(ISNUMBER(SEARCH(" PO "," "&SUBSTITUTE($I51,","," ")&" ")),ISNUMBER($L51)),$L51,"") | AG51: =IF(AND(ISNUMBER(SEARCH(" MFA "," "&SUBSTITUTE($I51,","," ")&" ")),ISNUMBER($L51)),$L51,"") | AH51: =IF(AND(ISNUMBER(SEARCH(" RAP "," "&SUBSTITUTE($I51,","," ")&" ")),ISNUMBER($L51)),$L51,"") | AI51: =IF(AND(ISNUMBER(SEARCH(" AC "," "&SUBSTITUTE($I51,","," ")&" ")),ISNUMBER($L51)),$L51,"") | AJ51: =IF(AND(ISNUMBER(SEARCH(" MAC "," "&SUBSTITUTE($I51,","," ")&" ")),ISNUMBER($L51)),$L51,"") | AK51: =IF(AND(ISNUMBER(SEARCH(" UAH "," "&SUBSTITUTE($I51,","," ")&" ")),ISNUMBER($L51)),$L51,"") | AL51: =IF(AND(ISNUMBER(SEARCH(" RB "," "&SUBSTITUTE($I51,","," ")&" ")),ISNUMBER($L51)),$L51,"")
A52: SRV-06 | B52: SRV | C52: Servers & Virtualisation | D52: Hypervisor platform health: vSphere/Hyper-V version in support (vSphere 7 end of general support was 2 Oct 2025), host firmware currency, HA/DRS configured, N+1 capacity, datastore free >= 20%, stale snapshots, VMware licensing status post-Broadcom | E52: The hypervisor is a single point of failure for the whole estate and a licensing cost risk. | F52: vCenter (Skyline/Health); emPOWER VCD / vCenter (M1/S1) for hosted; Hyper-V Manager/WAC; vendor lifecycle pages | G52: Record version/build; host count and failure tolerance; snapshots > 72 h; datastore utilisation; subscription/licence expiry and renewal owner. | H52: Supported version, N+1, no stale snapshots, licensing current. | I52: PO | J52: Billable | K52: 2 | M52: =IF(ISNUMBER(L52),IF(L52<K52,"Gap","OK"),IF(L52="N/A","N/A","")) | P52: =IF(AND(M52="Gap",N52<>"",O52<>""),VLOOKUP(N52&O52,Lists!$H$4:$I$12,2,FALSE()),"") | Q52: =IF(AND(M52="Gap",O52="S",OR(N52="H",N52="M")),"Yes","") | R52: Billable | S52: =IF(A52="","",IFERROR(IF(OR(VLOOKUP(A52,AutoEvidence!$A$2:$G$400,2,FALSE())="Collected",VLOOKUP(A52,AutoEvidence!$A$2:$G$400,2,FALSE())="Partial"),VLOOKUP(A52,AutoEvidence!$A$2:$G$400,3,FALSE())&" ("&VLOOKUP(A52,AutoEvidence!$A$2:$G$400,2,FALSE())&")",VLOOKUP(A52,AutoEvidence!$A$2:$G$400,2,FALSE())),"")) | T52: =IF(A52="","",IFERROR(VLOOKUP(A52,AutoEvidence!$A$2:$G$400,4,FALSE())&"","")) | AB52: =IF(M52="Gap",1,IF(M52="OK",0,"")) | AC52: =IF(P52<>"",VALUE(RIGHT(P52,1))*1000+ROW(),"") | AD52: =IF(ISNUMBER(L52),MIN(L52,K52),"") | AE52: =IF(AND(ISNUMBER(SEARCH(" PA "," "&SUBSTITUTE($I52,","," ")&" ")),ISNUMBER($L52)),$L52,"") | AF52: =IF(AND(ISNUMBER(SEARCH(" PO "," "&SUBSTITUTE($I52,","," ")&" ")),ISNUMBER($L52)),$L52,"") | AG52: =IF(AND(ISNUMBER(SEARCH(" MFA "," "&SUBSTITUTE($I52,","," ")&" ")),ISNUMBER($L52)),$L52,"") | AH52: =IF(AND(ISNUMBER(SEARCH(" RAP "," "&SUBSTITUTE($I52,","," ")&" ")),ISNUMBER($L52)),$L52,"") | AI52: =IF(AND(ISNUMBER(SEARCH(" AC "," "&SUBSTITUTE($I52,","," ")&" ")),ISNUMBER($L52)),$L52,"") | AJ52: =IF(AND(ISNUMBER(SEARCH(" MAC "," "&SUBSTITUTE($I52,","," ")&" ")),ISNUMBER($L52)),$L52,"") | AK52: =IF(AND(ISNUMBER(SEARCH(" UAH "," "&SUBSTITUTE($I52,","," ")&" ")),ISNUMBER($L52)),$L52,"") | AL52: =IF(AND(ISNUMBER(SEARCH(" RB "," "&SUBSTITUTE($I52,","," ")&" ")),ISNUMBER($L52)),$L52,"")
A53: SRV-07 | B53: SRV | C53: Servers & Virtualisation | D53: Capacity and performance: CPU/RAM/storage headroom and 12-month growth trend; over/under-provisioned VMs; storage latency alerts | E53: Capacity surprises become emergency purchases; right-sizing is a visible value-add (and billable in emPOWER terms). | F53: Orion capacity/forecast reports; vCenter performance; emPOWER order line items | G53: Pull 90-day utilisation; list VMs < 10% CPU with > 8 vCPU (over) and > 85% sustained (under); storage months-to-full. | H53: >= 6 months headroom; right-sizing recommendations issued. | J53: Value-add | K53: 2 | M53: =IF(ISNUMBER(L53),IF(L53<K53,"Gap","OK"),IF(L53="N/A","N/A","")) | P53: =IF(AND(M53="Gap",N53<>"",O53<>""),VLOOKUP(N53&O53,Lists!$H$4:$I$12,2,FALSE()),"") | Q53: =IF(AND(M53="Gap",O53="S",OR(N53="H",N53="M")),"Yes","") | R53: Value-add | S53: =IF(A53="","",IFERROR(IF(OR(VLOOKUP(A53,AutoEvidence!$A$2:$G$400,2,FALSE())="Collected",VLOOKUP(A53,AutoEvidence!$A$2:$G$400,2,FALSE())="Partial"),VLOOKUP(A53,AutoEvidence!$A$2:$G$400,3,FALSE())&" ("&VLOOKUP(A53,AutoEvidence!$A$2:$G$400,2,FALSE())&")",VLOOKUP(A53,AutoEvidence!$A$2:$G$400,2,FALSE())),"")) | T53: =IF(A53="","",IFERROR(VLOOKUP(A53,AutoEvidence!$A$2:$G$400,4,FALSE())&"","")) | AB53: =IF(M53="Gap",1,IF(M53="OK",0,"")) | AC53: =IF(P53<>"",VALUE(RIGHT(P53,1))*1000+ROW(),"") | AD53: =IF(ISNUMBER(L53),MIN(L53,K53),"") | AE53: =IF(AND(ISNUMBER(SEARCH(" PA "," "&SUBSTITUTE($I53,","," ")&" ")),ISNUMBER($L53)),$L53,"") | AF53: =IF(AND(ISNUMBER(SEARCH(" PO "," "&SUBSTITUTE($I53,","," ")&" ")),ISNUMBER($L53)),$L53,"") | AG53: =IF(AND(ISNUMBER(SEARCH(" MFA "," "&SUBSTITUTE($I53,","," ")&" ")),ISNUMBER($L53)),$L53,"") | AH53: =IF(AND(ISNUMBER(SEARCH(" RAP "," "&SUBSTITUTE($I53,","," ")&" ")),ISNUMBER($L53)),$L53,"") | AI53: =IF(AND(ISNUMBER(SEARCH(" AC "," "&SUBSTITUTE($I53,","," ")&" ")),ISNUMBER($L53)),$L53,"") | AJ53: =IF(AND(ISNUMBER(SEARCH(" MAC "," "&SUBSTITUTE($I53,","," ")&" ")),ISNUMBER($L53)),$L53,"") | AK53: =IF(AND(ISNUMBER(SEARCH(" UAH "," "&SUBSTITUTE($I53,","," ")&" ")),ISNUMBER($L53)),$L53,"") | AL53: =IF(AND(ISNUMBER(SEARCH(" RB "," "&SUBSTITUTE($I53,","," ")&" ")),ISNUMBER($L53)),$L53,"")
A54: SRV-08 | B54: SRV | C54: Servers & Virtualisation | D54: File services: share permissions (no Everyone/Authenticated Users modify), DFS-N/DFS-R health, quotas/FSRM, migration candidates to SharePoint/Azure Files | E54: Open shares are the ransomware blast radius and the data-governance blind spot. | F54: RMM script (Get-SmbShare / NTFS ACL audit); DFS diagnostics; SharePoint Migration Assessment | G54: Audit top-level shares and ACLs; DFS replication backlog; identify data volumes and access patterns for a cloud-migration opportunity. | H54: No broad-write shares; DFS healthy; migration position documented. | J54: Value-add | K54: 2 | M54: =IF(ISNUMBER(L54),IF(L54<K54,"Gap","OK"),IF(L54="N/A","N/A","")) | P54: =IF(AND(M54="Gap",N54<>"",O54<>""),VLOOKUP(N54&O54,Lists!$H$4:$I$12,2,FALSE()),"") | Q54: =IF(AND(M54="Gap",O54="S",OR(N54="H",N54="M")),"Yes","") | R54: Value-add | S54: =IF(A54="","",IFERROR(IF(OR(VLOOKUP(A54,AutoEvidence!$A$2:$G$400,2,FALSE())="Collected",VLOOKUP(A54,AutoEvidence!$A$2:$G$400,2,FALSE())="Partial"),VLOOKUP(A54,AutoEvidence!$A$2:$G$400,3,FALSE())&" ("&VLOOKUP(A54,AutoEvidence!$A$2:$G$400,2,FALSE())&")",VLOOKUP(A54,AutoEvidence!$A$2:$G$400,2,FALSE())),"")) | T54: =IF(A54="","",IFERROR(VLOOKUP(A54,AutoEvidence!$A$2:$G$400,4,FALSE())&"","")) | AB54: =IF(M54="Gap",1,IF(M54="OK",0,"")) | AC54: =IF(P54<>"",VALUE(RIGHT(P54,1))*1000+ROW(),"") | AD54: =IF(ISNUMBER(L54),MIN(L54,K54),"") | AE54: =IF(AND(ISNUMBER(SEARCH(" PA "," "&SUBSTITUTE($I54,","," ")&" ")),ISNUMBER($L54)),$L54,"") | AF54: =IF(AND(ISNUMBER(SEARCH(" PO "," "&SUBSTITUTE($I54,","," ")&" ")),ISNUMBER($L54)),$L54,"") | AG54: =IF(AND(ISNUMBER(SEARCH(" MFA "," "&SUBSTITUTE($I54,","," ")&" ")),ISNUMBER($L54)),$L54,"") | AH54: =IF(AND(ISNUMBER(SEARCH(" RAP "," "&SUBSTITUTE($I54,","," ")&" ")),ISNUMBER($L54)),$L54,"") | AI54: =IF(AND(ISNUMBER(SEARCH(" AC "," "&SUBSTITUTE($I54,","," ")&" ")),ISNUMBER($L54)),$L54,"") | AJ54: =IF(AND(ISNUMBER(SEARCH(" MAC "," "&SUBSTITUTE($I54,","," ")&" ")),ISNUMBER($L54)),$L54,"") | AK54: =IF(AND(ISNUMBER(SEARCH(" UAH "," "&SUBSTITUTE($I54,","," ")&" ")),ISNUMBER($L54)),$L54,"") | AL54: =IF(AND(ISNUMBER(SEARCH(" RB "," "&SUBSTITUTE($I54,","," ")&" ")),ISNUMBER($L54)),$L54,"")
A55: SRV-09 | B55: SRV | C55: Servers & Virtualisation | D55: Database and application servers: SQL versions in support (SQL 2014 and 2016 are out of support - 9 Jul 2024 and 14 Jul 2026; ESU only), backups (full + log) and recovery model, application owners and vendor support contracts documented | E55: Line-of-business apps are why the client exists; SQL EoS and untested backups are the risk. | F55: SQL inventory via RMM; Veeam application-aware processing; PROFILE.md application list | G55: List SQL instances/versions/editions; recovery model vs backup type; last successful DB restore; vendor support status per LoB app. | H55: Supported SQL; backups match recovery model; app owners known. | I55: PO, RB | J55: Billable | K55: 2 | M55: =IF(ISNUMBER(L55),IF(L55<K55,"Gap","OK"),IF(L55="N/A","N/A","")) | P55: =IF(AND(M55="Gap",N55<>"",O55<>""),VLOOKUP(N55&O55,Lists!$H$4:$I$12,2,FALSE()),"") | Q55: =IF(AND(M55="Gap",O55="S",OR(N55="H",N55="M")),"Yes","") | R55: Billable | S55: =IF(A55="","",IFERROR(IF(OR(VLOOKUP(A55,AutoEvidence!$A$2:$G$400,2,FALSE())="Collected",VLOOKUP(A55,AutoEvidence!$A$2:$G$400,2,FALSE())="Partial"),VLOOKUP(A55,AutoEvidence!$A$2:$G$400,3,FALSE())&" ("&VLOOKUP(A55,AutoEvidence!$A$2:$G$400,2,FALSE())&")",VLOOKUP(A55,AutoEvidence!$A$2:$G$400,2,FALSE())),"")) | T55: =IF(A55="","",IFERROR(VLOOKUP(A55,AutoEvidence!$A$2:$G$400,4,FALSE())&"","")) | AB55: =IF(M55="Gap",1,IF(M55="OK",0,"")) | AC55: =IF(P55<>"",VALUE(RIGHT(P55,1))*1000+ROW(),"") | AD55: =IF(ISNUMBER(L55),MIN(L55,K55),"") | AE55: =IF(AND(ISNUMBER(SEARCH(" PA "," "&SUBSTITUTE($I55,","," ")&" ")),ISNUMBER($L55)),$L55,"") | AF55: =IF(AND(ISNUMBER(SEARCH(" PO "," "&SUBSTITUTE($I55,","," ")&" ")),ISNUMBER($L55)),$L55,"") | AG55: =IF(AND(ISNUMBER(SEARCH(" MFA "," "&SUBSTITUTE($I55,","," ")&" ")),ISNUMBER($L55)),$L55,"") | AH55: =IF(AND(ISNUMBER(SEARCH(" RAP "," "&SUBSTITUTE($I55,","," ")&" ")),ISNUMBER($L55)),$L55,"") | AI55: =IF(AND(ISNUMBER(SEARCH(" AC "," "&SUBSTITUTE($I55,","," ")&" ")),ISNUMBER($L55)),$L55,"") | AJ55: =IF(AND(ISNUMBER(SEARCH(" MAC "," "&SUBSTITUTE($I55,","," ")&" ")),ISNUMBER($L55)),$L55,"") | AK55: =IF(AND(ISNUMBER(SEARCH(" UAH "," "&SUBSTITUTE($I55,","," ")&" ")),ISNUMBER($L55)),$L55,"") | AL55: =IF(AND(ISNUMBER(SEARCH(" RB "," "&SUBSTITUTE($I55,","," ")&" ")),ISNUMBER($L55)),$L55,"")
A56: SRV-10 | B56: SRV | C56: Servers & Virtualisation | D56: Certificates and PKI: internal CA health (CRL/AIA publishing, CA OS support), certificate expiry inventory, public cert automation plan (public TLS max lifetime 200 days since 15 Mar 2026, 100 days from Mar 2027, 47 days from Mar 2029 - CA/B Forum SC-081) | E56: Expired certificates cause outages; manual renewal will not scale as lifetimes shrink. | F56: pkiview.msc / certutil; GeoCerts portal; Orion SSL monitors; crt.sh | G56: List public certs and expiry; internal CA CRL validity; plan for ACME/automation; certificates on load balancers/firewalls included. | H56: Inventory current; nothing expiring < 30 days unowned; automation plan for public certs. | J56: Value-add | K56: 2 | M56: =IF(ISNUMBER(L56),IF(L56<K56,"Gap","OK"),IF(L56="N/A","N/A","")) | P56: =IF(AND(M56="Gap",N56<>"",O56<>""),VLOOKUP(N56&O56,Lists!$H$4:$I$12,2,FALSE()),"") | Q56: =IF(AND(M56="Gap",O56="S",OR(N56="H",N56="M")),"Yes","") | R56: Value-add | S56: =IF(A56="","",IFERROR(IF(OR(VLOOKUP(A56,AutoEvidence!$A$2:$G$400,2,FALSE())="Collected",VLOOKUP(A56,AutoEvidence!$A$2:$G$400,2,FALSE())="Partial"),VLOOKUP(A56,AutoEvidence!$A$2:$G$400,3,FALSE())&" ("&VLOOKUP(A56,AutoEvidence!$A$2:$G$400,2,FALSE())&")",VLOOKUP(A56,AutoEvidence!$A$2:$G$400,2,FALSE())),"")) | T56: =IF(A56="","",IFERROR(VLOOKUP(A56,AutoEvidence!$A$2:$G$400,4,FALSE())&"","")) | AB56: =IF(M56="Gap",1,IF(M56="OK",0,"")) | AC56: =IF(P56<>"",VALUE(RIGHT(P56,1))*1000+ROW(),"") | AD56: =IF(ISNUMBER(L56),MIN(L56,K56),"") | AE56: =IF(AND(ISNUMBER(SEARCH(" PA "," "&SUBSTITUTE($I56,","," ")&" ")),ISNUMBER($L56)),$L56,"") | AF56: =IF(AND(ISNUMBER(SEARCH(" PO "," "&SUBSTITUTE($I56,","," ")&" ")),ISNUMBER($L56)),$L56,"") | AG56: =IF(AND(ISNUMBER(SEARCH(" MFA "," "&SUBSTITUTE($I56,","," ")&" ")),ISNUMBER($L56)),$L56,"") | AH56: =IF(AND(ISNUMBER(SEARCH(" RAP "," "&SUBSTITUTE($I56,","," ")&" ")),ISNUMBER($L56)),$L56,"") | AI56: =IF(AND(ISNUMBER(SEARCH(" AC "," "&SUBSTITUTE($I56,","," ")&" ")),ISNUMBER($L56)),$L56,"") | AJ56: =IF(AND(ISNUMBER(SEARCH(" MAC "," "&SUBSTITUTE($I56,","," ")&" ")),ISNUMBER($L56)),$L56,"") | AK56: =IF(AND(ISNUMBER(SEARCH(" UAH "," "&SUBSTITUTE($I56,","," ")&" ")),ISNUMBER($L56)),$L56,"") | AL56: =IF(AND(ISNUMBER(SEARCH(" RB "," "&SUBSTITUTE($I56,","," ")&" ")),ISNUMBER($L56)),$L56,"")
A57: SRV-11 | B57: SRV | C57: Servers & Virtualisation | D57: Core services: NTP hierarchy, DNS (scavenging, forwarders not ISP, split-brain documented), DHCP failover and scope utilisation | E57: Quiet services that cause loud outages (Kerberos time skew, scope exhaustion). | F57: RDM to DC: w32tm /query /status; DNS server properties; DHCP scope statistics | G57: PDC syncs to external stratum; scavenging enabled with sane intervals; DHCP failover or documented single point; scopes < 80% utilised. | H57: All three healthy and documented. | J57: BAU | K57: 2 | M57: =IF(ISNUMBER(L57),IF(L57<K57,"Gap","OK"),IF(L57="N/A","N/A","")) | P57: =IF(AND(M57="Gap",N57<>"",O57<>""),VLOOKUP(N57&O57,Lists!$H$4:$I$12,2,FALSE()),"") | Q57: =IF(AND(M57="Gap",O57="S",OR(N57="H",N57="M")),"Yes","") | R57: BAU | S57: =IF(A57="","",IFERROR(IF(OR(VLOOKUP(A57,AutoEvidence!$A$2:$G$400,2,FALSE())="Collected",VLOOKUP(A57,AutoEvidence!$A$2:$G$400,2,FALSE())="Partial"),VLOOKUP(A57,AutoEvidence!$A$2:$G$400,3,FALSE())&" ("&VLOOKUP(A57,AutoEvidence!$A$2:$G$400,2,FALSE())&")",VLOOKUP(A57,AutoEvidence!$A$2:$G$400,2,FALSE())),"")) | T57: =IF(A57="","",IFERROR(VLOOKUP(A57,AutoEvidence!$A$2:$G$400,4,FALSE())&"","")) | AB57: =IF(M57="Gap",1,IF(M57="OK",0,"")) | AC57: =IF(P57<>"",VALUE(RIGHT(P57,1))*1000+ROW(),"") | AD57: =IF(ISNUMBER(L57),MIN(L57,K57),"") | AE57: =IF(AND(ISNUMBER(SEARCH(" PA "," "&SUBSTITUTE($I57,","," ")&" ")),ISNUMBER($L57)),$L57,"") | AF57: =IF(AND(ISNUMBER(SEARCH(" PO "," "&SUBSTITUTE($I57,","," ")&" ")),ISNUMBER($L57)),$L57,"") | AG57: =IF(AND(ISNUMBER(SEARCH(" MFA "," "&SUBSTITUTE($I57,","," ")&" ")),ISNUMBER($L57)),$L57,"") | AH57: =IF(AND(ISNUMBER(SEARCH(" RAP "," "&SUBSTITUTE($I57,","," ")&" ")),ISNUMBER($L57)),$L57,"") | AI57: =IF(AND(ISNUMBER(SEARCH(" AC "," "&SUBSTITUTE($I57,","," ")&" ")),ISNUMBER($L57)),$L57,"") | AJ57: =IF(AND(ISNUMBER(SEARCH(" MAC "," "&SUBSTITUTE($I57,","," ")&" ")),ISNUMBER($L57)),$L57,"") | AK57: =IF(AND(ISNUMBER(SEARCH(" UAH "," "&SUBSTITUTE($I57,","," ")&" ")),ISNUMBER($L57)),$L57,"") | AL57: =IF(AND(ISNUMBER(SEARCH(" RB "," "&SUBSTITUTE($I57,","," ")&" ")),ISNUMBER($L57)),$L57,"")
A58: SRV-12 | B58: SRV | C58: Servers & Virtualisation | D58: Print, RDS and legacy services: print server hardening (Point and Print), RDS host and CAL licensing, legacy runtimes (.NET, Java) on supported versions | E58: Print spooler and remote-desktop hosts are recurring CVE targets and licence-compliance traps. | F58: RMM inventory; RD Licensing Manager; farm consoles (RAS/Citrix); vendor advisories | G58: Check spooler exposure and Point and Print restrictions; RDS CAL count vs users; farm version support; runtime versions on app servers. | H58: Hardened, licensed, supported. | I58: PA | J58: Value-add | K58: 2 | M58: =IF(ISNUMBER(L58),IF(L58<K58,"Gap","OK"),IF(L58="N/A","N/A","")) | P58: =IF(AND(M58="Gap",N58<>"",O58<>""),VLOOKUP(N58&O58,Lists!$H$4:$I$12,2,FALSE()),"") | Q58: =IF(AND(M58="Gap",O58="S",OR(N58="H",N58="M")),"Yes","") | R58: Value-add | S58: =IF(A58="","",IFERROR(IF(OR(VLOOKUP(A58,AutoEvidence!$A$2:$G$400,2,FALSE())="Collected",VLOOKUP(A58,AutoEvidence!$A$2:$G$400,2,FALSE())="Partial"),VLOOKUP(A58,AutoEvidence!$A$2:$G$400,3,FALSE())&" ("&VLOOKUP(A58,AutoEvidence!$A$2:$G$400,2,FALSE())&")",VLOOKUP(A58,AutoEvidence!$A$2:$G$400,2,FALSE())),"")) | T58: =IF(A58="","",IFERROR(VLOOKUP(A58,AutoEvidence!$A$2:$G$400,4,FALSE())&"","")) | AB58: =IF(M58="Gap",1,IF(M58="OK",0,"")) | AC58: =IF(P58<>"",VALUE(RIGHT(P58,1))*1000+ROW(),"") | AD58: =IF(ISNUMBER(L58),MIN(L58,K58),"") | AE58: =IF(AND(ISNUMBER(SEARCH(" PA "," "&SUBSTITUTE($I58,","," ")&" ")),ISNUMBER($L58)),$L58,"") | AF58: =IF(AND(ISNUMBER(SEARCH(" PO "," "&SUBSTITUTE($I58,","," ")&" ")),ISNUMBER($L58)),$L58,"") | AG58: =IF(AND(ISNUMBER(SEARCH(" MFA "," "&SUBSTITUTE($I58,","," ")&" ")),ISNUMBER($L58)),$L58,"") | AH58: =IF(AND(ISNUMBER(SEARCH(" RAP "," "&SUBSTITUTE($I58,","," ")&" ")),ISNUMBER($L58)),$L58,"") | AI58: =IF(AND(ISNUMBER(SEARCH(" AC "," "&SUBSTITUTE($I58,","," ")&" ")),ISNUMBER($L58)),$L58,"") | AJ58: =IF(AND(ISNUMBER(SEARCH(" MAC "," "&SUBSTITUTE($I58,","," ")&" ")),ISNUMBER($L58)),$L58,"") | AK58: =IF(AND(ISNUMBER(SEARCH(" UAH "," "&SUBSTITUTE($I58,","," ")&" ")),ISNUMBER($L58)),$L58,"") | AL58: =IF(AND(ISNUMBER(SEARCH(" RB "," "&SUBSTITUTE($I58,","," ")&" ")),ISNUMBER($L58)),$L58,"")
A59: SRV-13 | B59: SRV | C59: Servers & Virtualisation | D59: Linux estate: distro support status, automated patching (unattended-upgrades/dnf-automatic/Ansible), SSH hardening (key-only, no root), monitoring and backup agents, domain integration (SSSD) if applicable | E59: Linux boxes are often 'someone else's' and fall outside the Windows-centric patch and monitoring loops. | F59: SSH via RDM; /etc/os-release; sshd_config; Orion Linux agent; Veeam Linux agent | G59: Inventory Linux hosts; check EoL status, patch automation, SSH settings, monitoring/backup presence, owner. | H59: All Linux hosts supported, patched, monitored, backed up. | I59: PO | J59: BAU | K59: 2 | M59: =IF(ISNUMBER(L59),IF(L59<K59,"Gap","OK"),IF(L59="N/A","N/A","")) | P59: =IF(AND(M59="Gap",N59<>"",O59<>""),VLOOKUP(N59&O59,Lists!$H$4:$I$12,2,FALSE()),"") | Q59: =IF(AND(M59="Gap",O59="S",OR(N59="H",N59="M")),"Yes","") | R59: BAU | S59: =IF(A59="","",IFERROR(IF(OR(VLOOKUP(A59,AutoEvidence!$A$2:$G$400,2,FALSE())="Collected",VLOOKUP(A59,AutoEvidence!$A$2:$G$400,2,FALSE())="Partial"),VLOOKUP(A59,AutoEvidence!$A$2:$G$400,3,FALSE())&" ("&VLOOKUP(A59,AutoEvidence!$A$2:$G$400,2,FALSE())&")",VLOOKUP(A59,AutoEvidence!$A$2:$G$400,2,FALSE())),"")) | T59: =IF(A59="","",IFERROR(VLOOKUP(A59,AutoEvidence!$A$2:$G$400,4,FALSE())&"","")) | AB59: =IF(M59="Gap",1,IF(M59="OK",0,"")) | AC59: =IF(P59<>"",VALUE(RIGHT(P59,1))*1000+ROW(),"") | AD59: =IF(ISNUMBER(L59),MIN(L59,K59),"") | AE59: =IF(AND(ISNUMBER(SEARCH(" PA "," "&SUBSTITUTE($I59,","," ")&" ")),ISNUMBER($L59)),$L59,"") | AF59: =IF(AND(ISNUMBER(SEARCH(" PO "," "&SUBSTITUTE($I59,","," ")&" ")),ISNUMBER($L59)),$L59,"") | AG59: =IF(AND(ISNUMBER(SEARCH(" MFA "," "&SUBSTITUTE($I59,","," ")&" ")),ISNUMBER($L59)),$L59,"") | AH59: =IF(AND(ISNUMBER(SEARCH(" RAP "," "&SUBSTITUTE($I59,","," ")&" ")),ISNUMBER($L59)),$L59,"") | AI59: =IF(AND(ISNUMBER(SEARCH(" AC "," "&SUBSTITUTE($I59,","," ")&" ")),ISNUMBER($L59)),$L59,"") | AJ59: =IF(AND(ISNUMBER(SEARCH(" MAC "," "&SUBSTITUTE($I59,","," ")&" ")),ISNUMBER($L59)),$L59,"") | AK59: =IF(AND(ISNUMBER(SEARCH(" UAH "," "&SUBSTITUTE($I59,","," ")&" ")),ISNUMBER($L59)),$L59,"") | AL59: =IF(AND(ISNUMBER(SEARCH(" RB "," "&SUBSTITUTE($I59,","," ")&" ")),ISNUMBER($L59)),$L59,"")
A60: SRV-14 | B60: SRV | C60: Servers & Virtualisation | D60: Published application and VDI platform (Citrix CVAD / Parallels RAS / RDS): farm version in support, broker and gateway redundancy, session host and VDA health, licensing model and entitlement headroom, gateway exposure and MFA | E60: The entire user population reaches its applications through this platform, so a single broker, an expired gateway certificate or an out-of-support farm version is a total outage rather than a degraded service - and the session hosts are usually excluded from endpoint tooling because they are filed as servers. | F60: Citrix Studio / Get-BrokerSite on a Delivery Controller; Parallels RAS console; NetScaler GUI or NITRO; RD Licensing Manager for CALs. CER-Discovery -Scope Citrix,ParallelsRas,NetScaler. | G60: Confirm the farm version is still in support (Citrix LTSR/CR dates, Parallels RAS 36-month LTS). Check there are two publishing agents/controllers and two gateways, not one of each. Confirm MFA on every published gateway. Check for unregistered VDAs or session hosts with an unhealthy agent. Read licence entitlement, usage headroom and renewal date. Confirm the session hosts appear in the patching, EDR and application-control coverage counts. | H60: Farm version in support; publishing agent/controller and gateway both redundant; MFA on every published gateway; session hosts inside the patching, EDR and application-control coverage counts; licence entitlement, headroom and renewal date known. | I60: PA, MFA | J60: Value-add | K60: 2 | M60: =IF(ISNUMBER(L60),IF(L60<K60,"Gap","OK"),IF(L60="N/A","N/A","")) | P60: =IF(AND(M60="Gap",N60<>"",O60<>""),VLOOKUP(N60&O60,Lists!$H$4:$I$12,2,FALSE()),"") | Q60: =IF(AND(M60="Gap",O60="S",OR(N60="H",N60="M")),"Yes","") | R60: Value-add | S60: =IF(A60="","",IFERROR(IF(OR(VLOOKUP(A60,AutoEvidence!$A$2:$G$400,2,FALSE())="Collected",VLOOKUP(A60,AutoEvidence!$A$2:$G$400,2,FALSE())="Partial"),VLOOKUP(A60,AutoEvidence!$A$2:$G$400,3,FALSE())&" ("&VLOOKUP(A60,AutoEvidence!$A$2:$G$400,2,FALSE())&")",VLOOKUP(A60,AutoEvidence!$A$2:$G$400,2,FALSE())),"")) | T60: =IF(A60="","",IFERROR(VLOOKUP(A60,AutoEvidence!$A$2:$G$400,4,FALSE())&"","")) | AB60: =IF(M60="Gap",1,IF(M60="OK",0,"")) | AC60: =IF(P60<>"",VALUE(RIGHT(P60,1))*1000+ROW(),"") | AD60: =IF(ISNUMBER(L60),MIN(L60,K60),"") | AE60: =IF(AND(ISNUMBER(SEARCH(" PA "," "&SUBSTITUTE($I60,","," ")&" ")),ISNUMBER($L60)),$L60,"") | AF60: =IF(AND(ISNUMBER(SEARCH(" PO "," "&SUBSTITUTE($I60,","," ")&" ")),ISNUMBER($L60)),$L60,"") | AG60: =IF(AND(ISNUMBER(SEARCH(" MFA "," "&SUBSTITUTE($I60,","," ")&" ")),ISNUMBER($L60)),$L60,"") | AH60: =IF(AND(ISNUMBER(SEARCH(" RAP "," "&SUBSTITUTE($I60,","," ")&" ")),ISNUMBER($L60)),$L60,"") | AI60: =IF(AND(ISNUMBER(SEARCH(" AC "," "&SUBSTITUTE($I60,","," ")&" ")),ISNUMBER($L60)),$L60,"") | AJ60: =IF(AND(ISNUMBER(SEARCH(" MAC "," "&SUBSTITUTE($I60,","," ")&" ")),ISNUMBER($L60)),$L60,"") | AK60: =IF(AND(ISNUMBER(SEARCH(" UAH "," "&SUBSTITUTE($I60,","," ")&" ")),ISNUMBER($L60)),$L60,"") | AL60: =IF(AND(ISNUMBER(SEARCH(" RB "," "&SUBSTITUTE($I60,","," ")&" ")),ISNUMBER($L60)),$L60,"")
A61: NET-01 | B61: NET | C61: Network & Firewall | D61: Network documentation current: L3 diagram (< 12 months), VLAN/IP schema in Netbox, WAN/ISP circuits and carrier contacts recorded | E61: Handbook: network changes require diagram updates; incidents without a diagram take twice as long. | F61: SharePoint Technical docs; Netbox; SNOW KB; STACK.md | G61: Locate diagram and check revision date against last network change; Netbox prefixes vs live config; carrier details for each circuit. | H61: Diagram < 12 months and accurate; IPAM current; circuits documented. | J61: BAU | K61: 2 | M61: =IF(ISNUMBER(L61),IF(L61<K61,"Gap","OK"),IF(L61="N/A","N/A","")) | P61: =IF(AND(M61="Gap",N61<>"",O61<>""),VLOOKUP(N61&O61,Lists!$H$4:$I$12,2,FALSE()),"") | Q61: =IF(AND(M61="Gap",O61="S",OR(N61="H",N61="M")),"Yes","") | R61: BAU | S61: =IF(A61="","",IFERROR(IF(OR(VLOOKUP(A61,AutoEvidence!$A$2:$G$400,2,FALSE())="Collected",VLOOKUP(A61,AutoEvidence!$A$2:$G$400,2,FALSE())="Partial"),VLOOKUP(A61,AutoEvidence!$A$2:$G$400,3,FALSE())&" ("&VLOOKUP(A61,AutoEvidence!$A$2:$G$400,2,FALSE())&")",VLOOKUP(A61,AutoEvidence!$A$2:$G$400,2,FALSE())),"")) | T61: =IF(A61="","",IFERROR(VLOOKUP(A61,AutoEvidence!$A$2:$G$400,4,FALSE())&"","")) | AB61: =IF(M61="Gap",1,IF(M61="OK",0,"")) | AC61: =IF(P61<>"",VALUE(RIGHT(P61,1))*1000+ROW(),"") | AD61: =IF(ISNUMBER(L61),MIN(L61,K61),"") | AE61: =IF(AND(ISNUMBER(SEARCH(" PA "," "&SUBSTITUTE($I61,","," ")&" ")),ISNUMBER($L61)),$L61,"") | AF61: =IF(AND(ISNUMBER(SEARCH(" PO "," "&SUBSTITUTE($I61,","," ")&" ")),ISNUMBER($L61)),$L61,"") | AG61: =IF(AND(ISNUMBER(SEARCH(" MFA "," "&SUBSTITUTE($I61,","," ")&" ")),ISNUMBER($L61)),$L61,"") | AH61: =IF(AND(ISNUMBER(SEARCH(" RAP "," "&SUBSTITUTE($I61,","," ")&" ")),ISNUMBER($L61)),$L61,"") | AI61: =IF(AND(ISNUMBER(SEARCH(" AC "," "&SUBSTITUTE($I61,","," ")&" ")),ISNUMBER($L61)),$L61,"") | AJ61: =IF(AND(ISNUMBER(SEARCH(" MAC "," "&SUBSTITUTE($I61,","," ")&" ")),ISNUMBER($L61)),$L61,"") | AK61: =IF(AND(ISNUMBER(SEARCH(" UAH "," "&SUBSTITUTE($I61,","," ")&" ")),ISNUMBER($L61)),$L61,"") | AL61: =IF(AND(ISNUMBER(SEARCH(" RB "," "&SUBSTITUTE($I61,","," ")&" ")),ISNUMBER($L61)),$L61,"")
A62: NET-02 | B62: NET | C62: Network & Firewall | D62: Firewall platform: model in support, FortiOS on a recommended mature branch (per PSIRT), HA pair, config backed up in FortiManager, management not internet-exposed, individual admin accounts, MFA | E62: Fortinet edge devices are actively exploited within days of PSIRT advisories; unmanaged firmware is the top network risk. | F62: FortiManager (mfm01); FortiGate GUI; Fortinet product lifecycle; PSIRT advisories; bA Fortinet best-practice checklist | G62: Record model/firmware; compare to PSIRT; HA state; last config backup; admin access restricted to trusted hosts with MFA; local admin credentials in CyberArk. | H62: Supported model, current recommended firmware, HA (or documented risk), management locked down. | I62: PO | J62: BAU | K62: 2 | M62: =IF(ISNUMBER(L62),IF(L62<K62,"Gap","OK"),IF(L62="N/A","N/A","")) | P62: =IF(AND(M62="Gap",N62<>"",O62<>""),VLOOKUP(N62&O62,Lists!$H$4:$I$12,2,FALSE()),"") | Q62: =IF(AND(M62="Gap",O62="S",OR(N62="H",N62="M")),"Yes","") | R62: BAU | S62: =IF(A62="","",IFERROR(IF(OR(VLOOKUP(A62,AutoEvidence!$A$2:$G$400,2,FALSE())="Collected",VLOOKUP(A62,AutoEvidence!$A$2:$G$400,2,FALSE())="Partial"),VLOOKUP(A62,AutoEvidence!$A$2:$G$400,3,FALSE())&" ("&VLOOKUP(A62,AutoEvidence!$A$2:$G$400,2,FALSE())&")",VLOOKUP(A62,AutoEvidence!$A$2:$G$400,2,FALSE())),"")) | T62: =IF(A62="","",IFERROR(VLOOKUP(A62,AutoEvidence!$A$2:$G$400,4,FALSE())&"","")) | AB62: =IF(M62="Gap",1,IF(M62="OK",0,"")) | AC62: =IF(P62<>"",VALUE(RIGHT(P62,1))*1000+ROW(),"") | AD62: =IF(ISNUMBER(L62),MIN(L62,K62),"") | AE62: =IF(AND(ISNUMBER(SEARCH(" PA "," "&SUBSTITUTE($I62,","," ")&" ")),ISNUMBER($L62)),$L62,"") | AF62: =IF(AND(ISNUMBER(SEARCH(" PO "," "&SUBSTITUTE($I62,","," ")&" ")),ISNUMBER($L62)),$L62,"") | AG62: =IF(AND(ISNUMBER(SEARCH(" MFA "," "&SUBSTITUTE($I62,","," ")&" ")),ISNUMBER($L62)),$L62,"") | AH62: =IF(AND(ISNUMBER(SEARCH(" RAP "," "&SUBSTITUTE($I62,","," ")&" ")),ISNUMBER($L62)),$L62,"") | AI62: =IF(AND(ISNUMBER(SEARCH(" AC "," "&SUBSTITUTE($I62,","," ")&" ")),ISNUMBER($L62)),$L62,"") | AJ62: =IF(AND(ISNUMBER(SEARCH(" MAC "," "&SUBSTITUTE($I62,","," ")&" ")),ISNUMBER($L62)),$L62,"") | AK62: =IF(AND(ISNUMBER(SEARCH(" UAH "," "&SUBSTITUTE($I62,","," ")&" ")),ISNUMBER($L62)),$L62,"") | AL62: =IF(AND(ISNUMBER(SEARCH(" RB "," "&SUBSTITUTE($I62,","," ")&" ")),ISNUMBER($L62)),$L62,"")
A63: NET-03 | B63: NET | C63: Network & Firewall | D63: Firewall policy hygiene: no any/any, unused rules (zero hits > 90 days) removed, logging on all policies, security profiles (IPS/AV/web filter/app control/DNS filter) on internet-bound policies, geo-blocking | E63: Policy sprawl hides risky rules; unlogged rules blind the SIEM. | F63: FortiManager/FortiAnalyzer policy hit counts; FortiGate policy table; Rapid7 log sources | G63: Export policy table; count any/any and disabled/unused rules; check UTM profiles and logging per policy; SSL inspection posture documented. | H63: Clean policy set with profiles and logging on every internet-bound rule. | J63: Value-add | K63: 2 | M63: =IF(ISNUMBER(L63),IF(L63<K63,"Gap","OK"),IF(L63="N/A","N/A","")) | P63: =IF(AND(M63="Gap",N63<>"",O63<>""),VLOOKUP(N63&O63,Lists!$H$4:$I$12,2,FALSE()),"") | Q63: =IF(AND(M63="Gap",O63="S",OR(N63="H",N63="M")),"Yes","") | R63: Value-add | S63: =IF(A63="","",IFERROR(IF(OR(VLOOKUP(A63,AutoEvidence!$A$2:$G$400,2,FALSE())="Collected",VLOOKUP(A63,AutoEvidence!$A$2:$G$400,2,FALSE())="Partial"),VLOOKUP(A63,AutoEvidence!$A$2:$G$400,3,FALSE())&" ("&VLOOKUP(A63,AutoEvidence!$A$2:$G$400,2,FALSE())&")",VLOOKUP(A63,AutoEvidence!$A$2:$G$400,2,FALSE())),"")) | T63: =IF(A63="","",IFERROR(VLOOKUP(A63,AutoEvidence!$A$2:$G$400,4,FALSE())&"","")) | AB63: =IF(M63="Gap",1,IF(M63="OK",0,"")) | AC63: =IF(P63<>"",VALUE(RIGHT(P63,1))*1000+ROW(),"") | AD63: =IF(ISNUMBER(L63),MIN(L63,K63),"") | AE63: =IF(AND(ISNUMBER(SEARCH(" PA "," "&SUBSTITUTE($I63,","," ")&" ")),ISNUMBER($L63)),$L63,"") | AF63: =IF(AND(ISNUMBER(SEARCH(" PO "," "&SUBSTITUTE($I63,","," ")&" ")),ISNUMBER($L63)),$L63,"") | AG63: =IF(AND(ISNUMBER(SEARCH(" MFA "," "&SUBSTITUTE($I63,","," ")&" ")),ISNUMBER($L63)),$L63,"") | AH63: =IF(AND(ISNUMBER(SEARCH(" RAP "," "&SUBSTITUTE($I63,","," ")&" ")),ISNUMBER($L63)),$L63,"") | AI63: =IF(AND(ISNUMBER(SEARCH(" AC "," "&SUBSTITUTE($I63,","," ")&" ")),ISNUMBER($L63)),$L63,"") | AJ63: =IF(AND(ISNUMBER(SEARCH(" MAC "," "&SUBSTITUTE($I63,","," ")&" ")),ISNUMBER($L63)),$L63,"") | AK63: =IF(AND(ISNUMBER(SEARCH(" UAH "," "&SUBSTITUTE($I63,","," ")&" ")),ISNUMBER($L63)),$L63,"") | AL63: =IF(AND(ISNUMBER(SEARCH(" RB "," "&SUBSTITUTE($I63,","," ")&" ")),ISNUMBER($L63)),$L63,"")
A64: NET-04 | B64: NET | C64: Network & Firewall | D64: Internet-facing exposure: external scan of all public IPs; every open port justified; no RDP/SMB/database exposed; SSL-VPN tunnel mode (removed in FortiOS 7.6.3) migrated to IPsec (TCP/443 option) or ZTNA | E64: Exposed services and legacy VPN portals are the initial access of choice for ransomware crews. | F64: Rapid7 IVM external scan; LionGard attack surface; Shodan; FortiGate VIP/NAT table | G64: Scan or review last scan; map each open port to a business justification and owner; check VPN type and firmware support. | H64: Only justified services exposed, behind IPS; VPN modern and MFA-protected. | I64: PO | J64: Billable | K64: 2 | M64: =IF(ISNUMBER(L64),IF(L64<K64,"Gap","OK"),IF(L64="N/A","N/A","")) | P64: =IF(AND(M64="Gap",N64<>"",O64<>""),VLOOKUP(N64&O64,Lists!$H$4:$I$12,2,FALSE()),"") | Q64: =IF(AND(M64="Gap",O64="S",OR(N64="H",N64="M")),"Yes","") | R64: Billable | S64: =IF(A64="","",IFERROR(IF(OR(VLOOKUP(A64,AutoEvidence!$A$2:$G$400,2,FALSE())="Collected",VLOOKUP(A64,AutoEvidence!$A$2:$G$400,2,FALSE())="Partial"),VLOOKUP(A64,AutoEvidence!$A$2:$G$400,3,FALSE())&" ("&VLOOKUP(A64,AutoEvidence!$A$2:$G$400,2,FALSE())&")",VLOOKUP(A64,AutoEvidence!$A$2:$G$400,2,FALSE())),"")) | T64: =IF(A64="","",IFERROR(VLOOKUP(A64,AutoEvidence!$A$2:$G$400,4,FALSE())&"","")) | AB64: =IF(M64="Gap",1,IF(M64="OK",0,"")) | AC64: =IF(P64<>"",VALUE(RIGHT(P64,1))*1000+ROW(),"") | AD64: =IF(ISNUMBER(L64),MIN(L64,K64),"") | AE64: =IF(AND(ISNUMBER(SEARCH(" PA "," "&SUBSTITUTE($I64,","," ")&" ")),ISNUMBER($L64)),$L64,"") | AF64: =IF(AND(ISNUMBER(SEARCH(" PO "," "&SUBSTITUTE($I64,","," ")&" ")),ISNUMBER($L64)),$L64,"") | AG64: =IF(AND(ISNUMBER(SEARCH(" MFA "," "&SUBSTITUTE($I64,","," ")&" ")),ISNUMBER($L64)),$L64,"") | AH64: =IF(AND(ISNUMBER(SEARCH(" RAP "," "&SUBSTITUTE($I64,","," ")&" ")),ISNUMBER($L64)),$L64,"") | AI64: =IF(AND(ISNUMBER(SEARCH(" AC "," "&SUBSTITUTE($I64,","," ")&" ")),ISNUMBER($L64)),$L64,"") | AJ64: =IF(AND(ISNUMBER(SEARCH(" MAC "," "&SUBSTITUTE($I64,","," ")&" ")),ISNUMBER($L64)),$L64,"") | AK64: =IF(AND(ISNUMBER(SEARCH(" UAH "," "&SUBSTITUTE($I64,","," ")&" ")),ISNUMBER($L64)),$L64,"") | AL64: =IF(AND(ISNUMBER(SEARCH(" RB "," "&SUBSTITUTE($I64,","," ")&" ")),ISNUMBER($L64)),$L64,"")
A65: NET-05 | B65: NET | C65: Network & Firewall | D65: Remote access: VPN/ZTNA requires MFA (SAML/Entra), device posture checks, split-tunnel policy documented, contractor access segregated and time-bound | E65: VPN without MFA is the cheapest credential-stuffing target on the internet (E8 MFA). | F65: FortiGate SSL-VPN/IPsec settings; Entra enterprise app for VPN SAML; VPN user groups | G65: Confirm authentication chain includes MFA; local VPN accounts count (should be zero except break-glass); posture checks; contractor group and expiry. | H65: MFA on all remote access; no standing local VPN accounts. | I65: MFA | J65: BAU | K65: 2 | M65: =IF(ISNUMBER(L65),IF(L65<K65,"Gap","OK"),IF(L65="N/A","N/A","")) | P65: =IF(AND(M65="Gap",N65<>"",O65<>""),VLOOKUP(N65&O65,Lists!$H$4:$I$12,2,FALSE()),"") | Q65: =IF(AND(M65="Gap",O65="S",OR(N65="H",N65="M")),"Yes","") | R65: BAU | S65: =IF(A65="","",IFERROR(IF(OR(VLOOKUP(A65,AutoEvidence!$A$2:$G$400,2,FALSE())="Collected",VLOOKUP(A65,AutoEvidence!$A$2:$G$400,2,FALSE())="Partial"),VLOOKUP(A65,AutoEvidence!$A$2:$G$400,3,FALSE())&" ("&VLOOKUP(A65,AutoEvidence!$A$2:$G$400,2,FALSE())&")",VLOOKUP(A65,AutoEvidence!$A$2:$G$400,2,FALSE())),"")) | T65: =IF(A65="","",IFERROR(VLOOKUP(A65,AutoEvidence!$A$2:$G$400,4,FALSE())&"","")) | AB65: =IF(M65="Gap",1,IF(M65="OK",0,"")) | AC65: =IF(P65<>"",VALUE(RIGHT(P65,1))*1000+ROW(),"") | AD65: =IF(ISNUMBER(L65),MIN(L65,K65),"") | AE65: =IF(AND(ISNUMBER(SEARCH(" PA "," "&SUBSTITUTE($I65,","," ")&" ")),ISNUMBER($L65)),$L65,"") | AF65: =IF(AND(ISNUMBER(SEARCH(" PO "," "&SUBSTITUTE($I65,","," ")&" ")),ISNUMBER($L65)),$L65,"") | AG65: =IF(AND(ISNUMBER(SEARCH(" MFA "," "&SUBSTITUTE($I65,","," ")&" ")),ISNUMBER($L65)),$L65,"") | AH65: =IF(AND(ISNUMBER(SEARCH(" RAP "," "&SUBSTITUTE($I65,","," ")&" ")),ISNUMBER($L65)),$L65,"") | AI65: =IF(AND(ISNUMBER(SEARCH(" AC "," "&SUBSTITUTE($I65,","," ")&" ")),ISNUMBER($L65)),$L65,"") | AJ65: =IF(AND(ISNUMBER(SEARCH(" MAC "," "&SUBSTITUTE($I65,","," ")&" ")),ISNUMBER($L65)),$L65,"") | AK65: =IF(AND(ISNUMBER(SEARCH(" UAH "," "&SUBSTITUTE($I65,","," ")&" ")),ISNUMBER($L65)),$L65,"") | AL65: =IF(AND(ISNUMBER(SEARCH(" RB "," "&SUBSTITUTE($I65,","," ")&" ")),ISNUMBER($L65)),$L65,"")
A66: NET-06 | B66: NET | C66: Network & Firewall | D66: Segmentation: user/server/guest/IoT-OT/voice/management VLANs separated by policy; guest wireless isolated; printers, cameras, BMS not on user VLAN | E66: Flat networks turn one infected laptop into a whole-of-business outage. | F66: Firewall interfaces and inter-VLAN policies; switch VLAN config; diagram | G66: List VLANs and the policies between them; confirm default inter-VLAN deny; guest isolation; where OT/IoT sits. | H66: Segmented with default-deny between zones; guest/IoT isolated. | J66: Billable | K66: 2 | M66: =IF(ISNUMBER(L66),IF(L66<K66,"Gap","OK"),IF(L66="N/A","N/A","")) | P66: =IF(AND(M66="Gap",N66<>"",O66<>""),VLOOKUP(N66&O66,Lists!$H$4:$I$12,2,FALSE()),"") | Q66: =IF(AND(M66="Gap",O66="S",OR(N66="H",N66="M")),"Yes","") | R66: Billable | S66: =IF(A66="","",IFERROR(IF(OR(VLOOKUP(A66,AutoEvidence!$A$2:$G$400,2,FALSE())="Collected",VLOOKUP(A66,AutoEvidence!$A$2:$G$400,2,FALSE())="Partial"),VLOOKUP(A66,AutoEvidence!$A$2:$G$400,3,FALSE())&" ("&VLOOKUP(A66,AutoEvidence!$A$2:$G$400,2,FALSE())&")",VLOOKUP(A66,AutoEvidence!$A$2:$G$400,2,FALSE())),"")) | T66: =IF(A66="","",IFERROR(VLOOKUP(A66,AutoEvidence!$A$2:$G$400,4,FALSE())&"","")) | AB66: =IF(M66="Gap",1,IF(M66="OK",0,"")) | AC66: =IF(P66<>"",VALUE(RIGHT(P66,1))*1000+ROW(),"") | AD66: =IF(ISNUMBER(L66),MIN(L66,K66),"") | AE66: =IF(AND(ISNUMBER(SEARCH(" PA "," "&SUBSTITUTE($I66,","," ")&" ")),ISNUMBER($L66)),$L66,"") | AF66: =IF(AND(ISNUMBER(SEARCH(" PO "," "&SUBSTITUTE($I66,","," ")&" ")),ISNUMBER($L66)),$L66,"") | AG66: =IF(AND(ISNUMBER(SEARCH(" MFA "," "&SUBSTITUTE($I66,","," ")&" ")),ISNUMBER($L66)),$L66,"") | AH66: =IF(AND(ISNUMBER(SEARCH(" RAP "," "&SUBSTITUTE($I66,","," ")&" ")),ISNUMBER($L66)),$L66,"") | AI66: =IF(AND(ISNUMBER(SEARCH(" AC "," "&SUBSTITUTE($I66,","," ")&" ")),ISNUMBER($L66)),$L66,"") | AJ66: =IF(AND(ISNUMBER(SEARCH(" MAC "," "&SUBSTITUTE($I66,","," ")&" ")),ISNUMBER($L66)),$L66,"") | AK66: =IF(AND(ISNUMBER(SEARCH(" UAH "," "&SUBSTITUTE($I66,","," ")&" ")),ISNUMBER($L66)),$L66,"") | AL66: =IF(AND(ISNUMBER(SEARCH(" RB "," "&SUBSTITUTE($I66,","," ")&" ")),ISNUMBER($L66)),$L66,"")
A67: NET-07 | B67: NET | C67: Network & Firewall | D67: Switching and wireless: firmware currency, loop protection, uplink redundancy, PoE budget, WPA2/3-Enterprise with 802.1X (no corporate PSK), controller/cloud licence expiry | E67: Access-layer neglect causes the intermittent faults that consume service-desk time. | F67: Meraki dashboard / Aruba Central / FortiSwitch via FortiGate; Orion; bA Fortinet Wireless Design checklist | G67: Firmware versions vs vendor recommended; STP/loop guard; corporate SSID auth method; licence expiry dates; APs/switches unreachable. | H67: Supported firmware; 802.1X for corporate Wi-Fi; licences > 90 days. | I67: PO | J67: Value-add | K67: 2 | M67: =IF(ISNUMBER(L67),IF(L67<K67,"Gap","OK"),IF(L67="N/A","N/A","")) | P67: =IF(AND(M67="Gap",N67<>"",O67<>""),VLOOKUP(N67&O67,Lists!$H$4:$I$12,2,FALSE()),"") | Q67: =IF(AND(M67="Gap",O67="S",OR(N67="H",N67="M")),"Yes","") | R67: Value-add | S67: =IF(A67="","",IFERROR(IF(OR(VLOOKUP(A67,AutoEvidence!$A$2:$G$400,2,FALSE())="Collected",VLOOKUP(A67,AutoEvidence!$A$2:$G$400,2,FALSE())="Partial"),VLOOKUP(A67,AutoEvidence!$A$2:$G$400,3,FALSE())&" ("&VLOOKUP(A67,AutoEvidence!$A$2:$G$400,2,FALSE())&")",VLOOKUP(A67,AutoEvidence!$A$2:$G$400,2,FALSE())),"")) | T67: =IF(A67="","",IFERROR(VLOOKUP(A67,AutoEvidence!$A$2:$G$400,4,FALSE())&"","")) | AB67: =IF(M67="Gap",1,IF(M67="OK",0,"")) | AC67: =IF(P67<>"",VALUE(RIGHT(P67,1))*1000+ROW(),"") | AD67: =IF(ISNUMBER(L67),MIN(L67,K67),"") | AE67: =IF(AND(ISNUMBER(SEARCH(" PA "," "&SUBSTITUTE($I67,","," ")&" ")),ISNUMBER($L67)),$L67,"") | AF67: =IF(AND(ISNUMBER(SEARCH(" PO "," "&SUBSTITUTE($I67,","," ")&" ")),ISNUMBER($L67)),$L67,"") | AG67: =IF(AND(ISNUMBER(SEARCH(" MFA "," "&SUBSTITUTE($I67,","," ")&" ")),ISNUMBER($L67)),$L67,"") | AH67: =IF(AND(ISNUMBER(SEARCH(" RAP "," "&SUBSTITUTE($I67,","," ")&" ")),ISNUMBER($L67)),$L67,"") | AI67: =IF(AND(ISNUMBER(SEARCH(" AC "," "&SUBSTITUTE($I67,","," ")&" ")),ISNUMBER($L67)),$L67,"") | AJ67: =IF(AND(ISNUMBER(SEARCH(" MAC "," "&SUBSTITUTE($I67,","," ")&" ")),ISNUMBER($L67)),$L67,"") | AK67: =IF(AND(ISNUMBER(SEARCH(" UAH "," "&SUBSTITUTE($I67,","," ")&" ")),ISNUMBER($L67)),$L67,"") | AL67: =IF(AND(ISNUMBER(SEARCH(" RB "," "&SUBSTITUTE($I67,","," ")&" ")),ISNUMBER($L67)),$L67,"")
A68: NET-08 | B68: NET | C68: Network & Firewall | D68: Network monitoring coverage: every firewall/switch/AP/UPS in Orion (or LogicMonitor/Meraki) with SNMPv3, utilisation alerts, config backup (NCM/FortiManager), syslog to FortiAnalyzer/Rapid7 | E68: Unmonitored network devices are diagnosed by user complaints. | F68: Orion node list; Orion NCM; FortiAnalyzer; Rapid7 log sources | G68: Diff device inventory vs monitored nodes; SNMP version; last config backup per device; syslog source list. | H68: 100% of network devices monitored, backed up and logging. | J68: BAU | K68: 2 | M68: =IF(ISNUMBER(L68),IF(L68<K68,"Gap","OK"),IF(L68="N/A","N/A","")) | P68: =IF(AND(M68="Gap",N68<>"",O68<>""),VLOOKUP(N68&O68,Lists!$H$4:$I$12,2,FALSE()),"") | Q68: =IF(AND(M68="Gap",O68="S",OR(N68="H",N68="M")),"Yes","") | R68: BAU | S68: =IF(A68="","",IFERROR(IF(OR(VLOOKUP(A68,AutoEvidence!$A$2:$G$400,2,FALSE())="Collected",VLOOKUP(A68,AutoEvidence!$A$2:$G$400,2,FALSE())="Partial"),VLOOKUP(A68,AutoEvidence!$A$2:$G$400,3,FALSE())&" ("&VLOOKUP(A68,AutoEvidence!$A$2:$G$400,2,FALSE())&")",VLOOKUP(A68,AutoEvidence!$A$2:$G$400,2,FALSE())),"")) | T68: =IF(A68="","",IFERROR(VLOOKUP(A68,AutoEvidence!$A$2:$G$400,4,FALSE())&"","")) | AB68: =IF(M68="Gap",1,IF(M68="OK",0,"")) | AC68: =IF(P68<>"",VALUE(RIGHT(P68,1))*1000+ROW(),"") | AD68: =IF(ISNUMBER(L68),MIN(L68,K68),"") | AE68: =IF(AND(ISNUMBER(SEARCH(" PA "," "&SUBSTITUTE($I68,","," ")&" ")),ISNUMBER($L68)),$L68,"") | AF68: =IF(AND(ISNUMBER(SEARCH(" PO "," "&SUBSTITUTE($I68,","," ")&" ")),ISNUMBER($L68)),$L68,"") | AG68: =IF(AND(ISNUMBER(SEARCH(" MFA "," "&SUBSTITUTE($I68,","," ")&" ")),ISNUMBER($L68)),$L68,"") | AH68: =IF(AND(ISNUMBER(SEARCH(" RAP "," "&SUBSTITUTE($I68,","," ")&" ")),ISNUMBER($L68)),$L68,"") | AI68: =IF(AND(ISNUMBER(SEARCH(" AC "," "&SUBSTITUTE($I68,","," ")&" ")),ISNUMBER($L68)),$L68,"") | AJ68: =IF(AND(ISNUMBER(SEARCH(" MAC "," "&SUBSTITUTE($I68,","," ")&" ")),ISNUMBER($L68)),$L68,"") | AK68: =IF(AND(ISNUMBER(SEARCH(" UAH "," "&SUBSTITUTE($I68,","," ")&" ")),ISNUMBER($L68)),$L68,"") | AL68: =IF(AND(ISNUMBER(SEARCH(" RB "," "&SUBSTITUTE($I68,","," ")&" ")),ISNUMBER($L68)),$L68,"")
A69: NET-09 | B69: NET | C69: Network & Firewall | D69: WAN and internet resilience: dual ISP or SD-WAN with tested failover, 4G/5G backup where appropriate, single points of failure listed, carrier SLA known | E69: Cloud-first clients lose everything when the single link drops. | F69: FortiGate SD-WAN status; change records for failover tests; PROFILE.md sites | G69: Per site: links, failover method, last test date, SLA; list SPOFs (single firewall, single switch, single ISP). | H69: Critical sites have tested failover; SPOFs accepted in writing or planned. | J69: Billable | K69: 2 | M69: =IF(ISNUMBER(L69),IF(L69<K69,"Gap","OK"),IF(L69="N/A","N/A","")) | P69: =IF(AND(M69="Gap",N69<>"",O69<>""),VLOOKUP(N69&O69,Lists!$H$4:$I$12,2,FALSE()),"") | Q69: =IF(AND(M69="Gap",O69="S",OR(N69="H",N69="M")),"Yes","") | R69: Billable | S69: =IF(A69="","",IFERROR(IF(OR(VLOOKUP(A69,AutoEvidence!$A$2:$G$400,2,FALSE())="Collected",VLOOKUP(A69,AutoEvidence!$A$2:$G$400,2,FALSE())="Partial"),VLOOKUP(A69,AutoEvidence!$A$2:$G$400,3,FALSE())&" ("&VLOOKUP(A69,AutoEvidence!$A$2:$G$400,2,FALSE())&")",VLOOKUP(A69,AutoEvidence!$A$2:$G$400,2,FALSE())),"")) | T69: =IF(A69="","",IFERROR(VLOOKUP(A69,AutoEvidence!$A$2:$G$400,4,FALSE())&"","")) | AB69: =IF(M69="Gap",1,IF(M69="OK",0,"")) | AC69: =IF(P69<>"",VALUE(RIGHT(P69,1))*1000+ROW(),"") | AD69: =IF(ISNUMBER(L69),MIN(L69,K69),"") | AE69: =IF(AND(ISNUMBER(SEARCH(" PA "," "&SUBSTITUTE($I69,","," ")&" ")),ISNUMBER($L69)),$L69,"") | AF69: =IF(AND(ISNUMBER(SEARCH(" PO "," "&SUBSTITUTE($I69,","," ")&" ")),ISNUMBER($L69)),$L69,"") | AG69: =IF(AND(ISNUMBER(SEARCH(" MFA "," "&SUBSTITUTE($I69,","," ")&" ")),ISNUMBER($L69)),$L69,"") | AH69: =IF(AND(ISNUMBER(SEARCH(" RAP "," "&SUBSTITUTE($I69,","," ")&" ")),ISNUMBER($L69)),$L69,"") | AI69: =IF(AND(ISNUMBER(SEARCH(" AC "," "&SUBSTITUTE($I69,","," ")&" ")),ISNUMBER($L69)),$L69,"") | AJ69: =IF(AND(ISNUMBER(SEARCH(" MAC "," "&SUBSTITUTE($I69,","," ")&" ")),ISNUMBER($L69)),$L69,"") | AK69: =IF(AND(ISNUMBER(SEARCH(" UAH "," "&SUBSTITUTE($I69,","," ")&" ")),ISNUMBER($L69)),$L69,"") | AL69: =IF(AND(ISNUMBER(SEARCH(" RB "," "&SUBSTITUTE($I69,","," ")&" ")),ISNUMBER($L69)),$L69,"")
A70: NET-10 | B70: NET | C70: Network & Firewall | D70: DNS and domain hygiene: registrar (TPP) and DNS (EasyDNS) access controlled, registrar lock, expiry > 6 months, CAA record, stale/dangling records removed (subdomain takeover) | E70: Domain loss or hijack is total business outage; dangling CNAMEs are free phishing infrastructure. | F70: TPP Wholesale; EasyDNS; whois; DNS zone export; crt.sh | G70: Check expiry, lock, contacts; review zone for records pointing at decommissioned services; CAA present; DNSSEC status. | H70: Locked, current, clean zone, CAA set. | J70: Value-add | K70: 2 | M70: =IF(ISNUMBER(L70),IF(L70<K70,"Gap","OK"),IF(L70="N/A","N/A","")) | P70: =IF(AND(M70="Gap",N70<>"",O70<>""),VLOOKUP(N70&O70,Lists!$H$4:$I$12,2,FALSE()),"") | Q70: =IF(AND(M70="Gap",O70="S",OR(N70="H",N70="M")),"Yes","") | R70: Value-add | S70: =IF(A70="","",IFERROR(IF(OR(VLOOKUP(A70,AutoEvidence!$A$2:$G$400,2,FALSE())="Collected",VLOOKUP(A70,AutoEvidence!$A$2:$G$400,2,FALSE())="Partial"),VLOOKUP(A70,AutoEvidence!$A$2:$G$400,3,FALSE())&" ("&VLOOKUP(A70,AutoEvidence!$A$2:$G$400,2,FALSE())&")",VLOOKUP(A70,AutoEvidence!$A$2:$G$400,2,FALSE())),"")) | T70: =IF(A70="","",IFERROR(VLOOKUP(A70,AutoEvidence!$A$2:$G$400,4,FALSE())&"","")) | AB70: =IF(M70="Gap",1,IF(M70="OK",0,"")) | AC70: =IF(P70<>"",VALUE(RIGHT(P70,1))*1000+ROW(),"") | AD70: =IF(ISNUMBER(L70),MIN(L70,K70),"") | AE70: =IF(AND(ISNUMBER(SEARCH(" PA "," "&SUBSTITUTE($I70,","," ")&" ")),ISNUMBER($L70)),$L70,"") | AF70: =IF(AND(ISNUMBER(SEARCH(" PO "," "&SUBSTITUTE($I70,","," ")&" ")),ISNUMBER($L70)),$L70,"") | AG70: =IF(AND(ISNUMBER(SEARCH(" MFA "," "&SUBSTITUTE($I70,","," ")&" ")),ISNUMBER($L70)),$L70,"") | AH70: =IF(AND(ISNUMBER(SEARCH(" RAP "," "&SUBSTITUTE($I70,","," ")&" ")),ISNUMBER($L70)),$L70,"") | AI70: =IF(AND(ISNUMBER(SEARCH(" AC "," "&SUBSTITUTE($I70,","," ")&" ")),ISNUMBER($L70)),$L70,"") | AJ70: =IF(AND(ISNUMBER(SEARCH(" MAC "," "&SUBSTITUTE($I70,","," ")&" ")),ISNUMBER($L70)),$L70,"") | AK70: =IF(AND(ISNUMBER(SEARCH(" UAH "," "&SUBSTITUTE($I70,","," ")&" ")),ISNUMBER($L70)),$L70,"") | AL70: =IF(AND(ISNUMBER(SEARCH(" RB "," "&SUBSTITUTE($I70,","," ")&" ")),ISNUMBER($L70)),$L70,"")
A71: NET-11 | B71: NET | C71: Network & Firewall | D71: Network access control: 802.1X/MAB or port security on wired, rogue device detection, DHCP snooping/dynamic ARP inspection where supported | E71: Anyone who can plug in should not get the server VLAN. | F71: Switch config; NAC (FortiNAC/Meraki/Aruba ClearPass) if present | G71: Check whether unused ports are disabled or in a quarantine VLAN; 802.1X on user ports; rogue detection alerts. | H71: Port-level control on user-accessible ports. | J71: Billable | K71: 2 | M71: =IF(ISNUMBER(L71),IF(L71<K71,"Gap","OK"),IF(L71="N/A","N/A","")) | P71: =IF(AND(M71="Gap",N71<>"",O71<>""),VLOOKUP(N71&O71,Lists!$H$4:$I$12,2,FALSE()),"") | Q71: =IF(AND(M71="Gap",O71="S",OR(N71="H",N71="M")),"Yes","") | R71: Billable | S71: =IF(A71="","",IFERROR(IF(OR(VLOOKUP(A71,AutoEvidence!$A$2:$G$400,2,FALSE())="Collected",VLOOKUP(A71,AutoEvidence!$A$2:$G$400,2,FALSE())="Partial"),VLOOKUP(A71,AutoEvidence!$A$2:$G$400,3,FALSE())&" ("&VLOOKUP(A71,AutoEvidence!$A$2:$G$400,2,FALSE())&")",VLOOKUP(A71,AutoEvidence!$A$2:$G$400,2,FALSE())),"")) | T71: =IF(A71="","",IFERROR(VLOOKUP(A71,AutoEvidence!$A$2:$G$400,4,FALSE())&"","")) | AB71: =IF(M71="Gap",1,IF(M71="OK",0,"")) | AC71: =IF(P71<>"",VALUE(RIGHT(P71,1))*1000+ROW(),"") | AD71: =IF(ISNUMBER(L71),MIN(L71,K71),"") | AE71: =IF(AND(ISNUMBER(SEARCH(" PA "," "&SUBSTITUTE($I71,","," ")&" ")),ISNUMBER($L71)),$L71,"") | AF71: =IF(AND(ISNUMBER(SEARCH(" PO "," "&SUBSTITUTE($I71,","," ")&" ")),ISNUMBER($L71)),$L71,"") | AG71: =IF(AND(ISNUMBER(SEARCH(" MFA "," "&SUBSTITUTE($I71,","," ")&" ")),ISNUMBER($L71)),$L71,"") | AH71: =IF(AND(ISNUMBER(SEARCH(" RAP "," "&SUBSTITUTE($I71,","," ")&" ")),ISNUMBER($L71)),$L71,"") | AI71: =IF(AND(ISNUMBER(SEARCH(" AC "," "&SUBSTITUTE($I71,","," ")&" ")),ISNUMBER($L71)),$L71,"") | AJ71: =IF(AND(ISNUMBER(SEARCH(" MAC "," "&SUBSTITUTE($I71,","," ")&" ")),ISNUMBER($L71)),$L71,"") | AK71: =IF(AND(ISNUMBER(SEARCH(" UAH "," "&SUBSTITUTE($I71,","," ")&" ")),ISNUMBER($L71)),$L71,"") | AL71: =IF(AND(ISNUMBER(SEARCH(" RB "," "&SUBSTITUTE($I71,","," ")&" ")),ISNUMBER($L71)),$L71,"")
A72: NET-12 | B72: NET | C72: Network & Firewall | D72: Voice/UC and special networks: Teams Phone/SBC or PBX support status, QoS, emergency-call location, BMS/CCTV/OT firmware and isolation | E72: Legacy PBX and OT devices are unpatched Linux boxes with vendor remote access. | F72: Teams admin centre; SBC/PBX console; vendor support contracts; NET-06 segmentation | G72: Inventory voice and OT/IoT platforms; support status; remote-access method used by vendors; isolation confirmed. | H72: Supported, isolated, vendor access controlled. | I72: PO | J72: Value-add | K72: 2 | M72: =IF(ISNUMBER(L72),IF(L72<K72,"Gap","OK"),IF(L72="N/A","N/A","")) | P72: =IF(AND(M72="Gap",N72<>"",O72<>""),VLOOKUP(N72&O72,Lists!$H$4:$I$12,2,FALSE()),"") | Q72: =IF(AND(M72="Gap",O72="S",OR(N72="H",N72="M")),"Yes","") | R72: Value-add | S72: =IF(A72="","",IFERROR(IF(OR(VLOOKUP(A72,AutoEvidence!$A$2:$G$400,2,FALSE())="Collected",VLOOKUP(A72,AutoEvidence!$A$2:$G$400,2,FALSE())="Partial"),VLOOKUP(A72,AutoEvidence!$A$2:$G$400,3,FALSE())&" ("&VLOOKUP(A72,AutoEvidence!$A$2:$G$400,2,FALSE())&")",VLOOKUP(A72,AutoEvidence!$A$2:$G$400,2,FALSE())),"")) | T72: =IF(A72="","",IFERROR(VLOOKUP(A72,AutoEvidence!$A$2:$G$400,4,FALSE())&"","")) | AB72: =IF(M72="Gap",1,IF(M72="OK",0,"")) | AC72: =IF(P72<>"",VALUE(RIGHT(P72,1))*1000+ROW(),"") | AD72: =IF(ISNUMBER(L72),MIN(L72,K72),"") | AE72: =IF(AND(ISNUMBER(SEARCH(" PA "," "&SUBSTITUTE($I72,","," ")&" ")),ISNUMBER($L72)),$L72,"") | AF72: =IF(AND(ISNUMBER(SEARCH(" PO "," "&SUBSTITUTE($I72,","," ")&" ")),ISNUMBER($L72)),$L72,"") | AG72: =IF(AND(ISNUMBER(SEARCH(" MFA "," "&SUBSTITUTE($I72,","," ")&" ")),ISNUMBER($L72)),$L72,"") | AH72: =IF(AND(ISNUMBER(SEARCH(" RAP "," "&SUBSTITUTE($I72,","," ")&" ")),ISNUMBER($L72)),$L72,"") | AI72: =IF(AND(ISNUMBER(SEARCH(" AC "," "&SUBSTITUTE($I72,","," ")&" ")),ISNUMBER($L72)),$L72,"") | AJ72: =IF(AND(ISNUMBER(SEARCH(" MAC "," "&SUBSTITUTE($I72,","," ")&" ")),ISNUMBER($L72)),$L72,"") | AK72: =IF(AND(ISNUMBER(SEARCH(" UAH "," "&SUBSTITUTE($I72,","," ")&" ")),ISNUMBER($L72)),$L72,"") | AL72: =IF(AND(ISNUMBER(SEARCH(" RB "," "&SUBSTITUTE($I72,","," ")&" ")),ISNUMBER($L72)),$L72,"")
A73: BDR-01 | B73: BDR | C73: Backup & DR | D73: Backup coverage: every production server/VM, database and SaaS workload is in a backup job; unprotected list is empty | E73: The item nobody added to the job is the one that gets encrypted (E8 RB). | F73: Veeam console (unprotected VMs); vminfo.empowercloud.net.au last-backup; Azure Backup; BAMS backup line items (eFO) | G73: Diff inventory (SRV-01) against protected objects; confirm new VMs are auto-included (tag/folder-based jobs); compare to contracted backup items. | H73: 100% of production protected; contract matches reality. | I73: RB | J73: BAU | K73: 2 | M73: =IF(ISNUMBER(L73),IF(L73<K73,"Gap","OK"),IF(L73="N/A","N/A","")) | P73: =IF(AND(M73="Gap",N73<>"",O73<>""),VLOOKUP(N73&O73,Lists!$H$4:$I$12,2,FALSE()),"") | Q73: =IF(AND(M73="Gap",O73="S",OR(N73="H",N73="M")),"Yes","") | R73: BAU | S73: =IF(A73="","",IFERROR(IF(OR(VLOOKUP(A73,AutoEvidence!$A$2:$G$400,2,FALSE())="Collected",VLOOKUP(A73,AutoEvidence!$A$2:$G$400,2,FALSE())="Partial"),VLOOKUP(A73,AutoEvidence!$A$2:$G$400,3,FALSE())&" ("&VLOOKUP(A73,AutoEvidence!$A$2:$G$400,2,FALSE())&")",VLOOKUP(A73,AutoEvidence!$A$2:$G$400,2,FALSE())),"")) | T73: =IF(A73="","",IFERROR(VLOOKUP(A73,AutoEvidence!$A$2:$G$400,4,FALSE())&"","")) | AB73: =IF(M73="Gap",1,IF(M73="OK",0,"")) | AC73: =IF(P73<>"",VALUE(RIGHT(P73,1))*1000+ROW(),"") | AD73: =IF(ISNUMBER(L73),MIN(L73,K73),"") | AE73: =IF(AND(ISNUMBER(SEARCH(" PA "," "&SUBSTITUTE($I73,","," ")&" ")),ISNUMBER($L73)),$L73,"") | AF73: =IF(AND(ISNUMBER(SEARCH(" PO "," "&SUBSTITUTE($I73,","," ")&" ")),ISNUMBER($L73)),$L73,"") | AG73: =IF(AND(ISNUMBER(SEARCH(" MFA "," "&SUBSTITUTE($I73,","," ")&" ")),ISNUMBER($L73)),$L73,"") | AH73: =IF(AND(ISNUMBER(SEARCH(" RAP "," "&SUBSTITUTE($I73,","," ")&" ")),ISNUMBER($L73)),$L73,"") | AI73: =IF(AND(ISNUMBER(SEARCH(" AC "," "&SUBSTITUTE($I73,","," ")&" ")),ISNUMBER($L73)),$L73,"") | AJ73: =IF(AND(ISNUMBER(SEARCH(" MAC "," "&SUBSTITUTE($I73,","," ")&" ")),ISNUMBER($L73)),$L73,"") | AK73: =IF(AND(ISNUMBER(SEARCH(" UAH "," "&SUBSTITUTE($I73,","," ")&" ")),ISNUMBER($L73)),$L73,"") | AL73: =IF(AND(ISNUMBER(SEARCH(" RB "," "&SUBSTITUTE($I73,","," ")&" ")),ISNUMBER($L73)),$L73,"")
A74: BDR-02 | B74: BDR | C74: Backup & DR | D74: Backup success and monitoring: 30-day success >= 98%, failures actioned within 24 h, job alerts to bA Backup team/NOC, warnings not chronically ignored | E74: A green dashboard with 40 days of warnings is a failed backup in waiting. | F74: Veeam reports/Veeam ONE; Orion backup monitors; SNOW incident history for backup failures | G74: Pull 30-day job history; list repeat failures and warnings older than 7 days; confirm alert routing and ticket creation. | H74: >= 98% success; no failure unactioned > 24 h. | I74: RB | J74: BAU | K74: 2 | M74: =IF(ISNUMBER(L74),IF(L74<K74,"Gap","OK"),IF(L74="N/A","N/A","")) | P74: =IF(AND(M74="Gap",N74<>"",O74<>""),VLOOKUP(N74&O74,Lists!$H$4:$I$12,2,FALSE()),"") | Q74: =IF(AND(M74="Gap",O74="S",OR(N74="H",N74="M")),"Yes","") | R74: BAU | S74: =IF(A74="","",IFERROR(IF(OR(VLOOKUP(A74,AutoEvidence!$A$2:$G$400,2,FALSE())="Collected",VLOOKUP(A74,AutoEvidence!$A$2:$G$400,2,FALSE())="Partial"),VLOOKUP(A74,AutoEvidence!$A$2:$G$400,3,FALSE())&" ("&VLOOKUP(A74,AutoEvidence!$A$2:$G$400,2,FALSE())&")",VLOOKUP(A74,AutoEvidence!$A$2:$G$400,2,FALSE())),"")) | T74: =IF(A74="","",IFERROR(VLOOKUP(A74,AutoEvidence!$A$2:$G$400,4,FALSE())&"","")) | AB74: =IF(M74="Gap",1,IF(M74="OK",0,"")) | AC74: =IF(P74<>"",VALUE(RIGHT(P74,1))*1000+ROW(),"") | AD74: =IF(ISNUMBER(L74),MIN(L74,K74),"") | AE74: =IF(AND(ISNUMBER(SEARCH(" PA "," "&SUBSTITUTE($I74,","," ")&" ")),ISNUMBER($L74)),$L74,"") | AF74: =IF(AND(ISNUMBER(SEARCH(" PO "," "&SUBSTITUTE($I74,","," ")&" ")),ISNUMBER($L74)),$L74,"") | AG74: =IF(AND(ISNUMBER(SEARCH(" MFA "," "&SUBSTITUTE($I74,","," ")&" ")),ISNUMBER($L74)),$L74,"") | AH74: =IF(AND(ISNUMBER(SEARCH(" RAP "," "&SUBSTITUTE($I74,","," ")&" ")),ISNUMBER($L74)),$L74,"") | AI74: =IF(AND(ISNUMBER(SEARCH(" AC "," "&SUBSTITUTE($I74,","," ")&" ")),ISNUMBER($L74)),$L74,"") | AJ74: =IF(AND(ISNUMBER(SEARCH(" MAC "," "&SUBSTITUTE($I74,","," ")&" ")),ISNUMBER($L74)),$L74,"") | AK74: =IF(AND(ISNUMBER(SEARCH(" UAH "," "&SUBSTITUTE($I74,","," ")&" ")),ISNUMBER($L74)),$L74,"") | AL74: =IF(AND(ISNUMBER(SEARCH(" RB "," "&SUBSTITUTE($I74,","," ")&" ")),ISNUMBER($L74)),$L74,"")
A75: BDR-03 | B75: BDR | C75: Backup & DR | D75: Retention, RPO and RTO documented per system tier and agreed with the business; regulatory retention (e.g. 7 years financial records) reflected; matches contract | E75: Without agreed targets, every restore conversation becomes a dispute. | F75: Backup job settings; SoW/BAMS scope; PROFILE.md; DR plan | G75: Table systems by tier with RPO/RTO/retention; compare job configuration; note gaps between contract, configuration and expectation. | H75: Documented, agreed, and matching configuration. | I75: RB | J75: Value-add | K75: 2 | M75: =IF(ISNUMBER(L75),IF(L75<K75,"Gap","OK"),IF(L75="N/A","N/A","")) | P75: =IF(AND(M75="Gap",N75<>"",O75<>""),VLOOKUP(N75&O75,Lists!$H$4:$I$12,2,FALSE()),"") | Q75: =IF(AND(M75="Gap",O75="S",OR(N75="H",N75="M")),"Yes","") | R75: Value-add | S75: =IF(A75="","",IFERROR(IF(OR(VLOOKUP(A75,AutoEvidence!$A$2:$G$400,2,FALSE())="Collected",VLOOKUP(A75,AutoEvidence!$A$2:$G$400,2,FALSE())="Partial"),VLOOKUP(A75,AutoEvidence!$A$2:$G$400,3,FALSE())&" ("&VLOOKUP(A75,AutoEvidence!$A$2:$G$400,2,FALSE())&")",VLOOKUP(A75,AutoEvidence!$A$2:$G$400,2,FALSE())),"")) | T75: =IF(A75="","",IFERROR(VLOOKUP(A75,AutoEvidence!$A$2:$G$400,4,FALSE())&"","")) | AB75: =IF(M75="Gap",1,IF(M75="OK",0,"")) | AC75: =IF(P75<>"",VALUE(RIGHT(P75,1))*1000+ROW(),"") | AD75: =IF(ISNUMBER(L75),MIN(L75,K75),"") | AE75: =IF(AND(ISNUMBER(SEARCH(" PA "," "&SUBSTITUTE($I75,","," ")&" ")),ISNUMBER($L75)),$L75,"") | AF75: =IF(AND(ISNUMBER(SEARCH(" PO "," "&SUBSTITUTE($I75,","," ")&" ")),ISNUMBER($L75)),$L75,"") | AG75: =IF(AND(ISNUMBER(SEARCH(" MFA "," "&SUBSTITUTE($I75,","," ")&" ")),ISNUMBER($L75)),$L75,"") | AH75: =IF(AND(ISNUMBER(SEARCH(" RAP "," "&SUBSTITUTE($I75,","," ")&" ")),ISNUMBER($L75)),$L75,"") | AI75: =IF(AND(ISNUMBER(SEARCH(" AC "," "&SUBSTITUTE($I75,","," ")&" ")),ISNUMBER($L75)),$L75,"") | AJ75: =IF(AND(ISNUMBER(SEARCH(" MAC "," "&SUBSTITUTE($I75,","," ")&" ")),ISNUMBER($L75)),$L75,"") | AK75: =IF(AND(ISNUMBER(SEARCH(" UAH "," "&SUBSTITUTE($I75,","," ")&" ")),ISNUMBER($L75)),$L75,"") | AL75: =IF(AND(ISNUMBER(SEARCH(" RB "," "&SUBSTITUTE($I75,","," ")&" ")),ISNUMBER($L75)),$L75,"")
A76: BDR-04 | B76: BDR | C76: Backup & DR | D76: 3-2-1 and immutability: second copy offsite (emPOWER cross-DC / Azure / object storage), immutable or air-gapped copy, repository not domain-joined, separate credentials, MFA on backup console | E76: Modern ransomware deletes backups first; E8 ML1 requires backups protected from modification/deletion. | F76: Veeam repository settings (immutability, hardened repo); Azure Backup soft delete/immutable vault; backup server domain membership; console MFA | G76: Trace each copy; confirm immutability window >= retention of most recent restore point; backup server local accounts; MFA and least privilege on console. | H76: Immutable offsite copy; backup infrastructure isolated from production AD. | I76: RB | J76: Billable | K76: 2 | M76: =IF(ISNUMBER(L76),IF(L76<K76,"Gap","OK"),IF(L76="N/A","N/A","")) | P76: =IF(AND(M76="Gap",N76<>"",O76<>""),VLOOKUP(N76&O76,Lists!$H$4:$I$12,2,FALSE()),"") | Q76: =IF(AND(M76="Gap",O76="S",OR(N76="H",N76="M")),"Yes","") | R76: Billable | S76: =IF(A76="","",IFERROR(IF(OR(VLOOKUP(A76,AutoEvidence!$A$2:$G$400,2,FALSE())="Collected",VLOOKUP(A76,AutoEvidence!$A$2:$G$400,2,FALSE())="Partial"),VLOOKUP(A76,AutoEvidence!$A$2:$G$400,3,FALSE())&" ("&VLOOKUP(A76,AutoEvidence!$A$2:$G$400,2,FALSE())&")",VLOOKUP(A76,AutoEvidence!$A$2:$G$400,2,FALSE())),"")) | T76: =IF(A76="","",IFERROR(VLOOKUP(A76,AutoEvidence!$A$2:$G$400,4,FALSE())&"","")) | AB76: =IF(M76="Gap",1,IF(M76="OK",0,"")) | AC76: =IF(P76<>"",VALUE(RIGHT(P76,1))*1000+ROW(),"") | AD76: =IF(ISNUMBER(L76),MIN(L76,K76),"") | AE76: =IF(AND(ISNUMBER(SEARCH(" PA "," "&SUBSTITUTE($I76,","," ")&" ")),ISNUMBER($L76)),$L76,"") | AF76: =IF(AND(ISNUMBER(SEARCH(" PO "," "&SUBSTITUTE($I76,","," ")&" ")),ISNUMBER($L76)),$L76,"") | AG76: =IF(AND(ISNUMBER(SEARCH(" MFA "," "&SUBSTITUTE($I76,","," ")&" ")),ISNUMBER($L76)),$L76,"") | AH76: =IF(AND(ISNUMBER(SEARCH(" RAP "," "&SUBSTITUTE($I76,","," ")&" ")),ISNUMBER($L76)),$L76,"") | AI76: =IF(AND(ISNUMBER(SEARCH(" AC "," "&SUBSTITUTE($I76,","," ")&" ")),ISNUMBER($L76)),$L76,"") | AJ76: =IF(AND(ISNUMBER(SEARCH(" MAC "," "&SUBSTITUTE($I76,","," ")&" ")),ISNUMBER($L76)),$L76,"") | AK76: =IF(AND(ISNUMBER(SEARCH(" UAH "," "&SUBSTITUTE($I76,","," ")&" ")),ISNUMBER($L76)),$L76,"") | AL76: =IF(AND(ISNUMBER(SEARCH(" RB "," "&SUBSTITUTE($I76,","," ")&" ")),ISNUMBER($L76)),$L76,"")
A77: BDR-05 | B77: BDR | C77: Backup & DR | D77: Restore testing: file, VM and application-level restores tested in the last 6 months with evidence; DR runbook exercised annually | E77: E8 RB ML1: restoration tested as part of DR exercises. Untested backups are hope, not a control. | F77: Veeam SureBackup reports; change/ticket records of restore tests; DR test report; LOG.md | G77: Find last restore test evidence per tier; schedule one if absent; record results in STACK.md and the client report. | H77: Evidence of restore tests <= 6 months; DR test <= 12 months. | I77: RB | J77: BAU | K77: 2 | M77: =IF(ISNUMBER(L77),IF(L77<K77,"Gap","OK"),IF(L77="N/A","N/A","")) | P77: =IF(AND(M77="Gap",N77<>"",O77<>""),VLOOKUP(N77&O77,Lists!$H$4:$I$12,2,FALSE()),"") | Q77: =IF(AND(M77="Gap",O77="S",OR(N77="H",N77="M")),"Yes","") | R77: BAU | S77: =IF(A77="","",IFERROR(IF(OR(VLOOKUP(A77,AutoEvidence!$A$2:$G$400,2,FALSE())="Collected",VLOOKUP(A77,AutoEvidence!$A$2:$G$400,2,FALSE())="Partial"),VLOOKUP(A77,AutoEvidence!$A$2:$G$400,3,FALSE())&" ("&VLOOKUP(A77,AutoEvidence!$A$2:$G$400,2,FALSE())&")",VLOOKUP(A77,AutoEvidence!$A$2:$G$400,2,FALSE())),"")) | T77: =IF(A77="","",IFERROR(VLOOKUP(A77,AutoEvidence!$A$2:$G$400,4,FALSE())&"","")) | AB77: =IF(M77="Gap",1,IF(M77="OK",0,"")) | AC77: =IF(P77<>"",VALUE(RIGHT(P77,1))*1000+ROW(),"") | AD77: =IF(ISNUMBER(L77),MIN(L77,K77),"") | AE77: =IF(AND(ISNUMBER(SEARCH(" PA "," "&SUBSTITUTE($I77,","," ")&" ")),ISNUMBER($L77)),$L77,"") | AF77: =IF(AND(ISNUMBER(SEARCH(" PO "," "&SUBSTITUTE($I77,","," ")&" ")),ISNUMBER($L77)),$L77,"") | AG77: =IF(AND(ISNUMBER(SEARCH(" MFA "," "&SUBSTITUTE($I77,","," ")&" ")),ISNUMBER($L77)),$L77,"") | AH77: =IF(AND(ISNUMBER(SEARCH(" RAP "," "&SUBSTITUTE($I77,","," ")&" ")),ISNUMBER($L77)),$L77,"") | AI77: =IF(AND(ISNUMBER(SEARCH(" AC "," "&SUBSTITUTE($I77,","," ")&" ")),ISNUMBER($L77)),$L77,"") | AJ77: =IF(AND(ISNUMBER(SEARCH(" MAC "," "&SUBSTITUTE($I77,","," ")&" ")),ISNUMBER($L77)),$L77,"") | AK77: =IF(AND(ISNUMBER(SEARCH(" UAH "," "&SUBSTITUTE($I77,","," ")&" ")),ISNUMBER($L77)),$L77,"") | AL77: =IF(AND(ISNUMBER(SEARCH(" RB "," "&SUBSTITUTE($I77,","," ")&" ")),ISNUMBER($L77)),$L77,"")
A78: BDR-06 | B78: BDR | C78: Backup & DR | D78: Application-consistent backups: SQL/Exchange/AD with VSS and log truncation; AD system state and forest-recovery capability; DC snapshot policy | E78: Crash-consistent images of databases and DCs restore into corruption. | F78: Veeam job settings (application-aware processing, guest credentials); SQL log growth; AD backup job | G78: Check application-aware processing succeeds (not falling back); SQL logs truncating; at least two DCs backed up with system state; snapshot-revert of DCs prohibited. | H78: App-aware on all DB/AD workloads; AD recoverable. | I78: RB | J78: BAU | K78: 2 | M78: =IF(ISNUMBER(L78),IF(L78<K78,"Gap","OK"),IF(L78="N/A","N/A","")) | P78: =IF(AND(M78="Gap",N78<>"",O78<>""),VLOOKUP(N78&O78,Lists!$H$4:$I$12,2,FALSE()),"") | Q78: =IF(AND(M78="Gap",O78="S",OR(N78="H",N78="M")),"Yes","") | R78: BAU | S78: =IF(A78="","",IFERROR(IF(OR(VLOOKUP(A78,AutoEvidence!$A$2:$G$400,2,FALSE())="Collected",VLOOKUP(A78,AutoEvidence!$A$2:$G$400,2,FALSE())="Partial"),VLOOKUP(A78,AutoEvidence!$A$2:$G$400,3,FALSE())&" ("&VLOOKUP(A78,AutoEvidence!$A$2:$G$400,2,FALSE())&")",VLOOKUP(A78,AutoEvidence!$A$2:$G$400,2,FALSE())),"")) | T78: =IF(A78="","",IFERROR(VLOOKUP(A78,AutoEvidence!$A$2:$G$400,4,FALSE())&"","")) | AB78: =IF(M78="Gap",1,IF(M78="OK",0,"")) | AC78: =IF(P78<>"",VALUE(RIGHT(P78,1))*1000+ROW(),"") | AD78: =IF(ISNUMBER(L78),MIN(L78,K78),"") | AE78: =IF(AND(ISNUMBER(SEARCH(" PA "," "&SUBSTITUTE($I78,","," ")&" ")),ISNUMBER($L78)),$L78,"") | AF78: =IF(AND(ISNUMBER(SEARCH(" PO "," "&SUBSTITUTE($I78,","," ")&" ")),ISNUMBER($L78)),$L78,"") | AG78: =IF(AND(ISNUMBER(SEARCH(" MFA "," "&SUBSTITUTE($I78,","," ")&" ")),ISNUMBER($L78)),$L78,"") | AH78: =IF(AND(ISNUMBER(SEARCH(" RAP "," "&SUBSTITUTE($I78,","," ")&" ")),ISNUMBER($L78)),$L78,"") | AI78: =IF(AND(ISNUMBER(SEARCH(" AC "," "&SUBSTITUTE($I78,","," ")&" ")),ISNUMBER($L78)),$L78,"") | AJ78: =IF(AND(ISNUMBER(SEARCH(" MAC "," "&SUBSTITUTE($I78,","," ")&" ")),ISNUMBER($L78)),$L78,"") | AK78: =IF(AND(ISNUMBER(SEARCH(" UAH "," "&SUBSTITUTE($I78,","," ")&" ")),ISNUMBER($L78)),$L78,"") | AL78: =IF(AND(ISNUMBER(SEARCH(" RB "," "&SUBSTITUTE($I78,","," ")&" ")),ISNUMBER($L78)),$L78,"")
A79: BDR-07 | B79: BDR | C79: Backup & DR | D79: Endpoint and user data protection: OneDrive Known Folder Move enforced, no critical data on local drives or personal cloud, laptop loss scenario covered | E79: Desktop and Documents folders are where the finance spreadsheets actually live. | F79: Intune OneDrive KFM policy; OneDrive usage report; Defender for Cloud Apps discovery (shadow storage) | G79: KFM policy assigned and enforced; % users with OneDrive active; unsanctioned cloud storage in discovery logs. | H79: KFM enforced; unsanctioned storage addressed. | I79: RB | J79: Value-add | K79: 2 | M79: =IF(ISNUMBER(L79),IF(L79<K79,"Gap","OK"),IF(L79="N/A","N/A","")) | P79: =IF(AND(M79="Gap",N79<>"",O79<>""),VLOOKUP(N79&O79,Lists!$H$4:$I$12,2,FALSE()),"") | Q79: =IF(AND(M79="Gap",O79="S",OR(N79="H",N79="M")),"Yes","") | R79: Value-add | S79: =IF(A79="","",IFERROR(IF(OR(VLOOKUP(A79,AutoEvidence!$A$2:$G$400,2,FALSE())="Collected",VLOOKUP(A79,AutoEvidence!$A$2:$G$400,2,FALSE())="Partial"),VLOOKUP(A79,AutoEvidence!$A$2:$G$400,3,FALSE())&" ("&VLOOKUP(A79,AutoEvidence!$A$2:$G$400,2,FALSE())&")",VLOOKUP(A79,AutoEvidence!$A$2:$G$400,2,FALSE())),"")) | T79: =IF(A79="","",IFERROR(VLOOKUP(A79,AutoEvidence!$A$2:$G$400,4,FALSE())&"","")) | AB79: =IF(M79="Gap",1,IF(M79="OK",0,"")) | AC79: =IF(P79<>"",VALUE(RIGHT(P79,1))*1000+ROW(),"") | AD79: =IF(ISNUMBER(L79),MIN(L79,K79),"") | AE79: =IF(AND(ISNUMBER(SEARCH(" PA "," "&SUBSTITUTE($I79,","," ")&" ")),ISNUMBER($L79)),$L79,"") | AF79: =IF(AND(ISNUMBER(SEARCH(" PO "," "&SUBSTITUTE($I79,","," ")&" ")),ISNUMBER($L79)),$L79,"") | AG79: =IF(AND(ISNUMBER(SEARCH(" MFA "," "&SUBSTITUTE($I79,","," ")&" ")),ISNUMBER($L79)),$L79,"") | AH79: =IF(AND(ISNUMBER(SEARCH(" RAP "," "&SUBSTITUTE($I79,","," ")&" ")),ISNUMBER($L79)),$L79,"") | AI79: =IF(AND(ISNUMBER(SEARCH(" AC "," "&SUBSTITUTE($I79,","," ")&" ")),ISNUMBER($L79)),$L79,"") | AJ79: =IF(AND(ISNUMBER(SEARCH(" MAC "," "&SUBSTITUTE($I79,","," ")&" ")),ISNUMBER($L79)),$L79,"") | AK79: =IF(AND(ISNUMBER(SEARCH(" UAH "," "&SUBSTITUTE($I79,","," ")&" ")),ISNUMBER($L79)),$L79,"") | AL79: =IF(AND(ISNUMBER(SEARCH(" RB "," "&SUBSTITUTE($I79,","," ")&" ")),ISNUMBER($L79)),$L79,"")
A80: BDR-08 | B80: BDR | C80: Backup & DR | D80: DR plan and BCP: documented plan with system priorities, RTO tiers, failover procedure (emPOWER DRaaS / ASR / rebuild), dependency map (DNS, identity, licensing), contact tree, reviewed <= 12 months | E80: Backups without a plan produce a 5-day outage instead of a 5-hour one. | F80: SNOW KB / SharePoint DR document; ASR/DRaaS configuration; PROFILE.md contacts | G80: Locate the plan; check date, owner, whether it reflects current architecture; confirm failover mechanism actually configured for tier-1 systems. | H80: Current plan, configured failover for tier-1, annual review. | I80: RB | J80: Billable | K80: 2 | M80: =IF(ISNUMBER(L80),IF(L80<K80,"Gap","OK"),IF(L80="N/A","N/A","")) | P80: =IF(AND(M80="Gap",N80<>"",O80<>""),VLOOKUP(N80&O80,Lists!$H$4:$I$12,2,FALSE()),"") | Q80: =IF(AND(M80="Gap",O80="S",OR(N80="H",N80="M")),"Yes","") | R80: Billable | S80: =IF(A80="","",IFERROR(IF(OR(VLOOKUP(A80,AutoEvidence!$A$2:$G$400,2,FALSE())="Collected",VLOOKUP(A80,AutoEvidence!$A$2:$G$400,2,FALSE())="Partial"),VLOOKUP(A80,AutoEvidence!$A$2:$G$400,3,FALSE())&" ("&VLOOKUP(A80,AutoEvidence!$A$2:$G$400,2,FALSE())&")",VLOOKUP(A80,AutoEvidence!$A$2:$G$400,2,FALSE())),"")) | T80: =IF(A80="","",IFERROR(VLOOKUP(A80,AutoEvidence!$A$2:$G$400,4,FALSE())&"","")) | AB80: =IF(M80="Gap",1,IF(M80="OK",0,"")) | AC80: =IF(P80<>"",VALUE(RIGHT(P80,1))*1000+ROW(),"") | AD80: =IF(ISNUMBER(L80),MIN(L80,K80),"") | AE80: =IF(AND(ISNUMBER(SEARCH(" PA "," "&SUBSTITUTE($I80,","," ")&" ")),ISNUMBER($L80)),$L80,"") | AF80: =IF(AND(ISNUMBER(SEARCH(" PO "," "&SUBSTITUTE($I80,","," ")&" ")),ISNUMBER($L80)),$L80,"") | AG80: =IF(AND(ISNUMBER(SEARCH(" MFA "," "&SUBSTITUTE($I80,","," ")&" ")),ISNUMBER($L80)),$L80,"") | AH80: =IF(AND(ISNUMBER(SEARCH(" RAP "," "&SUBSTITUTE($I80,","," ")&" ")),ISNUMBER($L80)),$L80,"") | AI80: =IF(AND(ISNUMBER(SEARCH(" AC "," "&SUBSTITUTE($I80,","," ")&" ")),ISNUMBER($L80)),$L80,"") | AJ80: =IF(AND(ISNUMBER(SEARCH(" MAC "," "&SUBSTITUTE($I80,","," ")&" ")),ISNUMBER($L80)),$L80,"") | AK80: =IF(AND(ISNUMBER(SEARCH(" UAH "," "&SUBSTITUTE($I80,","," ")&" ")),ISNUMBER($L80)),$L80,"") | AL80: =IF(AND(ISNUMBER(SEARCH(" RB "," "&SUBSTITUTE($I80,","," ")&" ")),ISNUMBER($L80)),$L80,"")
A81: BDR-09 | B81: BDR | C81: Backup & DR | D81: Backup platform lifecycle: Veeam version in support, repository capacity >= 6 months growth headroom, backup server OS supported, licences current | E81: The backup server is often the oldest, least-patched box in the room. | F81: Veeam console (About, licence); repository free space trend; N-Central OS report | G81: Version and licence expiry; capacity trend; OS of backup server and proxies; patch status. | H81: Supported, licensed, >= 6 months capacity. | I81: RB, PO | J81: BAU | K81: 2 | M81: =IF(ISNUMBER(L81),IF(L81<K81,"Gap","OK"),IF(L81="N/A","N/A","")) | P81: =IF(AND(M81="Gap",N81<>"",O81<>""),VLOOKUP(N81&O81,Lists!$H$4:$I$12,2,FALSE()),"") | Q81: =IF(AND(M81="Gap",O81="S",OR(N81="H",N81="M")),"Yes","") | R81: BAU | S81: =IF(A81="","",IFERROR(IF(OR(VLOOKUP(A81,AutoEvidence!$A$2:$G$400,2,FALSE())="Collected",VLOOKUP(A81,AutoEvidence!$A$2:$G$400,2,FALSE())="Partial"),VLOOKUP(A81,AutoEvidence!$A$2:$G$400,3,FALSE())&" ("&VLOOKUP(A81,AutoEvidence!$A$2:$G$400,2,FALSE())&")",VLOOKUP(A81,AutoEvidence!$A$2:$G$400,2,FALSE())),"")) | T81: =IF(A81="","",IFERROR(VLOOKUP(A81,AutoEvidence!$A$2:$G$400,4,FALSE())&"","")) | AB81: =IF(M81="Gap",1,IF(M81="OK",0,"")) | AC81: =IF(P81<>"",VALUE(RIGHT(P81,1))*1000+ROW(),"") | AD81: =IF(ISNUMBER(L81),MIN(L81,K81),"") | AE81: =IF(AND(ISNUMBER(SEARCH(" PA "," "&SUBSTITUTE($I81,","," ")&" ")),ISNUMBER($L81)),$L81,"") | AF81: =IF(AND(ISNUMBER(SEARCH(" PO "," "&SUBSTITUTE($I81,","," ")&" ")),ISNUMBER($L81)),$L81,"") | AG81: =IF(AND(ISNUMBER(SEARCH(" MFA "," "&SUBSTITUTE($I81,","," ")&" ")),ISNUMBER($L81)),$L81,"") | AH81: =IF(AND(ISNUMBER(SEARCH(" RAP "," "&SUBSTITUTE($I81,","," ")&" ")),ISNUMBER($L81)),$L81,"") | AI81: =IF(AND(ISNUMBER(SEARCH(" AC "," "&SUBSTITUTE($I81,","," ")&" ")),ISNUMBER($L81)),$L81,"") | AJ81: =IF(AND(ISNUMBER(SEARCH(" MAC "," "&SUBSTITUTE($I81,","," ")&" ")),ISNUMBER($L81)),$L81,"") | AK81: =IF(AND(ISNUMBER(SEARCH(" UAH "," "&SUBSTITUTE($I81,","," ")&" ")),ISNUMBER($L81)),$L81,"") | AL81: =IF(AND(ISNUMBER(SEARCH(" RB "," "&SUBSTITUTE($I81,","," ")&" ")),ISNUMBER($L81)),$L81,"")
A82: BDR-10 | B82: BDR | C82: Backup & DR | D82: Configuration backups of platforms: firewall/switch configs, Entra/Intune/CA policy exports, Azure resource templates, hypervisor config - versioned and restorable | E82: Rebuilding a tenant's Conditional Access from memory during an incident is not a plan. | F82: FortiManager revisions; Orion NCM; Intune/Entra export scripts or third-party (e.g. M365DSC); git/SharePoint versions | G82: Confirm each platform has an automated or scheduled config export; last export date; where stored and who can restore. | H82: All platforms exported <= 30 days, stored securely. | I82: RB | J82: Value-add | K82: 2 | M82: =IF(ISNUMBER(L82),IF(L82<K82,"Gap","OK"),IF(L82="N/A","N/A","")) | P82: =IF(AND(M82="Gap",N82<>"",O82<>""),VLOOKUP(N82&O82,Lists!$H$4:$I$12,2,FALSE()),"") | Q82: =IF(AND(M82="Gap",O82="S",OR(N82="H",N82="M")),"Yes","") | R82: Value-add | S82: =IF(A82="","",IFERROR(IF(OR(VLOOKUP(A82,AutoEvidence!$A$2:$G$400,2,FALSE())="Collected",VLOOKUP(A82,AutoEvidence!$A$2:$G$400,2,FALSE())="Partial"),VLOOKUP(A82,AutoEvidence!$A$2:$G$400,3,FALSE())&" ("&VLOOKUP(A82,AutoEvidence!$A$2:$G$400,2,FALSE())&")",VLOOKUP(A82,AutoEvidence!$A$2:$G$400,2,FALSE())),"")) | T82: =IF(A82="","",IFERROR(VLOOKUP(A82,AutoEvidence!$A$2:$G$400,4,FALSE())&"","")) | AB82: =IF(M82="Gap",1,IF(M82="OK",0,"")) | AC82: =IF(P82<>"",VALUE(RIGHT(P82,1))*1000+ROW(),"") | AD82: =IF(ISNUMBER(L82),MIN(L82,K82),"") | AE82: =IF(AND(ISNUMBER(SEARCH(" PA "," "&SUBSTITUTE($I82,","," ")&" ")),ISNUMBER($L82)),$L82,"") | AF82: =IF(AND(ISNUMBER(SEARCH(" PO "," "&SUBSTITUTE($I82,","," ")&" ")),ISNUMBER($L82)),$L82,"") | AG82: =IF(AND(ISNUMBER(SEARCH(" MFA "," "&SUBSTITUTE($I82,","," ")&" ")),ISNUMBER($L82)),$L82,"") | AH82: =IF(AND(ISNUMBER(SEARCH(" RAP "," "&SUBSTITUTE($I82,","," ")&" ")),ISNUMBER($L82)),$L82,"") | AI82: =IF(AND(ISNUMBER(SEARCH(" AC "," "&SUBSTITUTE($I82,","," ")&" ")),ISNUMBER($L82)),$L82,"") | AJ82: =IF(AND(ISNUMBER(SEARCH(" MAC "," "&SUBSTITUTE($I82,","," ")&" ")),ISNUMBER($L82)),$L82,"") | AK82: =IF(AND(ISNUMBER(SEARCH(" UAH "," "&SUBSTITUTE($I82,","," ")&" ")),ISNUMBER($L82)),$L82,"") | AL82: =IF(AND(ISNUMBER(SEARCH(" RB "," "&SUBSTITUTE($I82,","," ")&" ")),ISNUMBER($L82)),$L82,"")
A83: COV-01 | B83: COV | C83: Monitoring, Patching & BAMS Coverage | D83: BAMS inclusions reconciled: PowerBI 'eFO People or Items in My Org - with ROLES' vs actual devices/services - every billed item exists, every managed item is billed, BAMS codes correct | E83: Handbook priority 13 (quarterly). Revenue leakage and billing for decommissioned items both damage the relationship. | F83: PowerBI report; eFO Cloud Services; SNOW CIs; SRV-01/END-01 inventories | G83: Export billed items; diff against inventories; list unbilled managed items and billed non-existent items; raise with SDM/CAM. | H83: Zero unexplained differences; corrections raised. | J83: BAU | K83: 2 | M83: =IF(ISNUMBER(L83),IF(L83<K83,"Gap","OK"),IF(L83="N/A","N/A","")) | P83: =IF(AND(M83="Gap",N83<>"",O83<>""),VLOOKUP(N83&O83,Lists!$H$4:$I$12,2,FALSE()),"") | Q83: =IF(AND(M83="Gap",O83="S",OR(N83="H",N83="M")),"Yes","") | R83: BAU | S83: =IF(A83="","",IFERROR(IF(OR(VLOOKUP(A83,AutoEvidence!$A$2:$G$400,2,FALSE())="Collected",VLOOKUP(A83,AutoEvidence!$A$2:$G$400,2,FALSE())="Partial"),VLOOKUP(A83,AutoEvidence!$A$2:$G$400,3,FALSE())&" ("&VLOOKUP(A83,AutoEvidence!$A$2:$G$400,2,FALSE())&")",VLOOKUP(A83,AutoEvidence!$A$2:$G$400,2,FALSE())),"")) | T83: =IF(A83="","",IFERROR(VLOOKUP(A83,AutoEvidence!$A$2:$G$400,4,FALSE())&"","")) | AB83: =IF(M83="Gap",1,IF(M83="OK",0,"")) | AC83: =IF(P83<>"",VALUE(RIGHT(P83,1))*1000+ROW(),"") | AD83: =IF(ISNUMBER(L83),MIN(L83,K83),"") | AE83: =IF(AND(ISNUMBER(SEARCH(" PA "," "&SUBSTITUTE($I83,","," ")&" ")),ISNUMBER($L83)),$L83,"") | AF83: =IF(AND(ISNUMBER(SEARCH(" PO "," "&SUBSTITUTE($I83,","," ")&" ")),ISNUMBER($L83)),$L83,"") | AG83: =IF(AND(ISNUMBER(SEARCH(" MFA "," "&SUBSTITUTE($I83,","," ")&" ")),ISNUMBER($L83)),$L83,"") | AH83: =IF(AND(ISNUMBER(SEARCH(" RAP "," "&SUBSTITUTE($I83,","," ")&" ")),ISNUMBER($L83)),$L83,"") | AI83: =IF(AND(ISNUMBER(SEARCH(" AC "," "&SUBSTITUTE($I83,","," ")&" ")),ISNUMBER($L83)),$L83,"") | AJ83: =IF(AND(ISNUMBER(SEARCH(" MAC "," "&SUBSTITUTE($I83,","," ")&" ")),ISNUMBER($L83)),$L83,"") | AK83: =IF(AND(ISNUMBER(SEARCH(" UAH "," "&SUBSTITUTE($I83,","," ")&" ")),ISNUMBER($L83)),$L83,"") | AL83: =IF(AND(ISNUMBER(SEARCH(" RB "," "&SUBSTITUTE($I83,","," ")&" ")),ISNUMBER($L83)),$L83,"")
A84: COV-02 | B84: COV | C84: Monitoring, Patching & BAMS Coverage | D84: Monitoring coverage: every server, network device and critical service in Orion (LogicMonitor for cloud); muted/unmanaged nodes justified (they still consume licences) | E84: Unmonitored = discovered by the client. Handbook: validate monitoring before handover. | F84: Orion node list and unmanaged nodes; LogicMonitor; SRV-01 inventory; KB0011149 | G84: Diff inventory vs monitored nodes; review unmanaged/muted list with reasons and dates; raise Catalogue Tasks for onboarding gaps. | H84: 100% of in-scope CIs monitored; muted list clean. | J84: BAU | K84: 2 | M84: =IF(ISNUMBER(L84),IF(L84<K84,"Gap","OK"),IF(L84="N/A","N/A","")) | P84: =IF(AND(M84="Gap",N84<>"",O84<>""),VLOOKUP(N84&O84,Lists!$H$4:$I$12,2,FALSE()),"") | Q84: =IF(AND(M84="Gap",O84="S",OR(N84="H",N84="M")),"Yes","") | R84: BAU | S84: =IF(A84="","",IFERROR(IF(OR(VLOOKUP(A84,AutoEvidence!$A$2:$G$400,2,FALSE())="Collected",VLOOKUP(A84,AutoEvidence!$A$2:$G$400,2,FALSE())="Partial"),VLOOKUP(A84,AutoEvidence!$A$2:$G$400,3,FALSE())&" ("&VLOOKUP(A84,AutoEvidence!$A$2:$G$400,2,FALSE())&")",VLOOKUP(A84,AutoEvidence!$A$2:$G$400,2,FALSE())),"")) | T84: =IF(A84="","",IFERROR(VLOOKUP(A84,AutoEvidence!$A$2:$G$400,4,FALSE())&"","")) | AB84: =IF(M84="Gap",1,IF(M84="OK",0,"")) | AC84: =IF(P84<>"",VALUE(RIGHT(P84,1))*1000+ROW(),"") | AD84: =IF(ISNUMBER(L84),MIN(L84,K84),"") | AE84: =IF(AND(ISNUMBER(SEARCH(" PA "," "&SUBSTITUTE($I84,","," ")&" ")),ISNUMBER($L84)),$L84,"") | AF84: =IF(AND(ISNUMBER(SEARCH(" PO "," "&SUBSTITUTE($I84,","," ")&" ")),ISNUMBER($L84)),$L84,"") | AG84: =IF(AND(ISNUMBER(SEARCH(" MFA "," "&SUBSTITUTE($I84,","," ")&" ")),ISNUMBER($L84)),$L84,"") | AH84: =IF(AND(ISNUMBER(SEARCH(" RAP "," "&SUBSTITUTE($I84,","," ")&" ")),ISNUMBER($L84)),$L84,"") | AI84: =IF(AND(ISNUMBER(SEARCH(" AC "," "&SUBSTITUTE($I84,","," ")&" ")),ISNUMBER($L84)),$L84,"") | AJ84: =IF(AND(ISNUMBER(SEARCH(" MAC "," "&SUBSTITUTE($I84,","," ")&" ")),ISNUMBER($L84)),$L84,"") | AK84: =IF(AND(ISNUMBER(SEARCH(" UAH "," "&SUBSTITUTE($I84,","," ")&" ")),ISNUMBER($L84)),$L84,"") | AL84: =IF(AND(ISNUMBER(SEARCH(" RB "," "&SUBSTITUTE($I84,","," ")&" ")),ISNUMBER($L84)),$L84,"")
A85: COV-03 | B85: COV | C85: Monitoring, Patching & BAMS Coverage | D85: Monitoring quality: application/service monitors for critical apps (not just ping/CPU), thresholds tuned, top alerters reviewed, alerts map to runbooks, SSL/domain/backup monitors present | E85: Noisy or shallow monitoring trains the NOC to ignore the real one. | F85: Orion application monitors (SAM); alert history 30 days; NOC runbooks in SNOW KB | G85: List critical apps (PROFILE) and check each has a service-level monitor; top 10 alerting nodes and whether they are actioned; certificate and backup monitors exist. | H85: Service-level monitoring for all tier-1 apps; noise actioned. | J85: Value-add | K85: 2 | M85: =IF(ISNUMBER(L85),IF(L85<K85,"Gap","OK"),IF(L85="N/A","N/A","")) | P85: =IF(AND(M85="Gap",N85<>"",O85<>""),VLOOKUP(N85&O85,Lists!$H$4:$I$12,2,FALSE()),"") | Q85: =IF(AND(M85="Gap",O85="S",OR(N85="H",N85="M")),"Yes","") | R85: Value-add | S85: =IF(A85="","",IFERROR(IF(OR(VLOOKUP(A85,AutoEvidence!$A$2:$G$400,2,FALSE())="Collected",VLOOKUP(A85,AutoEvidence!$A$2:$G$400,2,FALSE())="Partial"),VLOOKUP(A85,AutoEvidence!$A$2:$G$400,3,FALSE())&" ("&VLOOKUP(A85,AutoEvidence!$A$2:$G$400,2,FALSE())&")",VLOOKUP(A85,AutoEvidence!$A$2:$G$400,2,FALSE())),"")) | T85: =IF(A85="","",IFERROR(VLOOKUP(A85,AutoEvidence!$A$2:$G$400,4,FALSE())&"","")) | AB85: =IF(M85="Gap",1,IF(M85="OK",0,"")) | AC85: =IF(P85<>"",VALUE(RIGHT(P85,1))*1000+ROW(),"") | AD85: =IF(ISNUMBER(L85),MIN(L85,K85),"") | AE85: =IF(AND(ISNUMBER(SEARCH(" PA "," "&SUBSTITUTE($I85,","," ")&" ")),ISNUMBER($L85)),$L85,"") | AF85: =IF(AND(ISNUMBER(SEARCH(" PO "," "&SUBSTITUTE($I85,","," ")&" ")),ISNUMBER($L85)),$L85,"") | AG85: =IF(AND(ISNUMBER(SEARCH(" MFA "," "&SUBSTITUTE($I85,","," ")&" ")),ISNUMBER($L85)),$L85,"") | AH85: =IF(AND(ISNUMBER(SEARCH(" RAP "," "&SUBSTITUTE($I85,","," ")&" ")),ISNUMBER($L85)),$L85,"") | AI85: =IF(AND(ISNUMBER(SEARCH(" AC "," "&SUBSTITUTE($I85,","," ")&" ")),ISNUMBER($L85)),$L85,"") | AJ85: =IF(AND(ISNUMBER(SEARCH(" MAC "," "&SUBSTITUTE($I85,","," ")&" ")),ISNUMBER($L85)),$L85,"") | AK85: =IF(AND(ISNUMBER(SEARCH(" UAH "," "&SUBSTITUTE($I85,","," ")&" ")),ISNUMBER($L85)),$L85,"") | AL85: =IF(AND(ISNUMBER(SEARCH(" RB "," "&SUBSTITUTE($I85,","," ")&" ")),ISNUMBER($L85)),$L85,"")
A86: COV-04 | B86: COV | C86: Monitoring, Patching & BAMS Coverage | D86: Patching coverage: every server and endpoint in an N-Central patch policy; devices not checked in > 30 days; approvals and windows documented; exclusions justified | E86: Patching only works on the devices the tool can see. | F86: N-Central device list, patch policy membership, last check-in; STACK.md patch windows | G86: Devices without a policy; stale agents; exclusions list with reason and expiry; window documented per client and communicated. | H86: 100% policy membership; < 3% stale agents; exclusions dated. | I86: PO, PA | J86: BAU | K86: 2 | M86: =IF(ISNUMBER(L86),IF(L86<K86,"Gap","OK"),IF(L86="N/A","N/A","")) | P86: =IF(AND(M86="Gap",N86<>"",O86<>""),VLOOKUP(N86&O86,Lists!$H$4:$I$12,2,FALSE()),"") | Q86: =IF(AND(M86="Gap",O86="S",OR(N86="H",N86="M")),"Yes","") | R86: BAU | S86: =IF(A86="","",IFERROR(IF(OR(VLOOKUP(A86,AutoEvidence!$A$2:$G$400,2,FALSE())="Collected",VLOOKUP(A86,AutoEvidence!$A$2:$G$400,2,FALSE())="Partial"),VLOOKUP(A86,AutoEvidence!$A$2:$G$400,3,FALSE())&" ("&VLOOKUP(A86,AutoEvidence!$A$2:$G$400,2,FALSE())&")",VLOOKUP(A86,AutoEvidence!$A$2:$G$400,2,FALSE())),"")) | T86: =IF(A86="","",IFERROR(VLOOKUP(A86,AutoEvidence!$A$2:$G$400,4,FALSE())&"","")) | AB86: =IF(M86="Gap",1,IF(M86="OK",0,"")) | AC86: =IF(P86<>"",VALUE(RIGHT(P86,1))*1000+ROW(),"") | AD86: =IF(ISNUMBER(L86),MIN(L86,K86),"") | AE86: =IF(AND(ISNUMBER(SEARCH(" PA "," "&SUBSTITUTE($I86,","," ")&" ")),ISNUMBER($L86)),$L86,"") | AF86: =IF(AND(ISNUMBER(SEARCH(" PO "," "&SUBSTITUTE($I86,","," ")&" ")),ISNUMBER($L86)),$L86,"") | AG86: =IF(AND(ISNUMBER(SEARCH(" MFA "," "&SUBSTITUTE($I86,","," ")&" ")),ISNUMBER($L86)),$L86,"") | AH86: =IF(AND(ISNUMBER(SEARCH(" RAP "," "&SUBSTITUTE($I86,","," ")&" ")),ISNUMBER($L86)),$L86,"") | AI86: =IF(AND(ISNUMBER(SEARCH(" AC "," "&SUBSTITUTE($I86,","," ")&" ")),ISNUMBER($L86)),$L86,"") | AJ86: =IF(AND(ISNUMBER(SEARCH(" MAC "," "&SUBSTITUTE($I86,","," ")&" ")),ISNUMBER($L86)),$L86,"") | AK86: =IF(AND(ISNUMBER(SEARCH(" UAH "," "&SUBSTITUTE($I86,","," ")&" ")),ISNUMBER($L86)),$L86,"") | AL86: =IF(AND(ISNUMBER(SEARCH(" RB "," "&SUBSTITUTE($I86,","," ")&" ")),ISNUMBER($L86)),$L86,"")
A87: COV-05 | B87: COV | C87: Monitoring, Patching & BAMS Coverage | D87: Security tooling coverage vs contract: EDR, Huntress, Rapid7, Airlock, Mimecast seat counts vs devices/users; agents missing; SIEM log sources (DCs, firewalls, M365) actually ingesting | E87: Paid-for seats not deployed are both a security gap and an awkward renewal conversation. | F87: Each console's device/user count; eFO subscription quantities; Rapid7 IDR data collection health | G87: Table product | licensed | deployed | healthy; list uncovered devices; confirm log sources with recent events. | H87: Deployed = licensed = devices; all core log sources live. | J87: BAU | K87: 2 | M87: =IF(ISNUMBER(L87),IF(L87<K87,"Gap","OK"),IF(L87="N/A","N/A","")) | P87: =IF(AND(M87="Gap",N87<>"",O87<>""),VLOOKUP(N87&O87,Lists!$H$4:$I$12,2,FALSE()),"") | Q87: =IF(AND(M87="Gap",O87="S",OR(N87="H",N87="M")),"Yes","") | R87: BAU | S87: =IF(A87="","",IFERROR(IF(OR(VLOOKUP(A87,AutoEvidence!$A$2:$G$400,2,FALSE())="Collected",VLOOKUP(A87,AutoEvidence!$A$2:$G$400,2,FALSE())="Partial"),VLOOKUP(A87,AutoEvidence!$A$2:$G$400,3,FALSE())&" ("&VLOOKUP(A87,AutoEvidence!$A$2:$G$400,2,FALSE())&")",VLOOKUP(A87,AutoEvidence!$A$2:$G$400,2,FALSE())),"")) | T87: =IF(A87="","",IFERROR(VLOOKUP(A87,AutoEvidence!$A$2:$G$400,4,FALSE())&"","")) | AB87: =IF(M87="Gap",1,IF(M87="OK",0,"")) | AC87: =IF(P87<>"",VALUE(RIGHT(P87,1))*1000+ROW(),"") | AD87: =IF(ISNUMBER(L87),MIN(L87,K87),"") | AE87: =IF(AND(ISNUMBER(SEARCH(" PA "," "&SUBSTITUTE($I87,","," ")&" ")),ISNUMBER($L87)),$L87,"") | AF87: =IF(AND(ISNUMBER(SEARCH(" PO "," "&SUBSTITUTE($I87,","," ")&" ")),ISNUMBER($L87)),$L87,"") | AG87: =IF(AND(ISNUMBER(SEARCH(" MFA "," "&SUBSTITUTE($I87,","," ")&" ")),ISNUMBER($L87)),$L87,"") | AH87: =IF(AND(ISNUMBER(SEARCH(" RAP "," "&SUBSTITUTE($I87,","," ")&" ")),ISNUMBER($L87)),$L87,"") | AI87: =IF(AND(ISNUMBER(SEARCH(" AC "," "&SUBSTITUTE($I87,","," ")&" ")),ISNUMBER($L87)),$L87,"") | AJ87: =IF(AND(ISNUMBER(SEARCH(" MAC "," "&SUBSTITUTE($I87,","," ")&" ")),ISNUMBER($L87)),$L87,"") | AK87: =IF(AND(ISNUMBER(SEARCH(" UAH "," "&SUBSTITUTE($I87,","," ")&" ")),ISNUMBER($L87)),$L87,"") | AL87: =IF(AND(ISNUMBER(SEARCH(" RB "," "&SUBSTITUTE($I87,","," ")&" ")),ISNUMBER($L87)),$L87,"")
A88: COV-06 | B88: COV | C88: Monitoring, Patching & BAMS Coverage | D88: Ticket and incident trends: last 90 days incidents by CI/category, repeat offenders raised as problem records, P1/P2 count, SLA breaches, noisy CIs recorded in PROBLEMS.md | E88: Recurring incidents are the cheapest improvement opportunities and the client's lived experience of bA. | F88: SNOW reports (customer account); PROBLEMS.md; LOG.md | G88: Pull incident list; group by CI and category; anything >= 3 in 90 days -> problem record + PROBLEMS.md signature; note SLA breaches and causes. | H88: Top repeat issues have problem records and owners. | J88: BAU | K88: 2 | M88: =IF(ISNUMBER(L88),IF(L88<K88,"Gap","OK"),IF(L88="N/A","N/A","")) | P88: =IF(AND(M88="Gap",N88<>"",O88<>""),VLOOKUP(N88&O88,Lists!$H$4:$I$12,2,FALSE()),"") | Q88: =IF(AND(M88="Gap",O88="S",OR(N88="H",N88="M")),"Yes","") | R88: BAU | S88: =IF(A88="","",IFERROR(IF(OR(VLOOKUP(A88,AutoEvidence!$A$2:$G$400,2,FALSE())="Collected",VLOOKUP(A88,AutoEvidence!$A$2:$G$400,2,FALSE())="Partial"),VLOOKUP(A88,AutoEvidence!$A$2:$G$400,3,FALSE())&" ("&VLOOKUP(A88,AutoEvidence!$A$2:$G$400,2,FALSE())&")",VLOOKUP(A88,AutoEvidence!$A$2:$G$400,2,FALSE())),"")) | T88: =IF(A88="","",IFERROR(VLOOKUP(A88,AutoEvidence!$A$2:$G$400,4,FALSE())&"","")) | AB88: =IF(M88="Gap",1,IF(M88="OK",0,"")) | AC88: =IF(P88<>"",VALUE(RIGHT(P88,1))*1000+ROW(),"") | AD88: =IF(ISNUMBER(L88),MIN(L88,K88),"") | AE88: =IF(AND(ISNUMBER(SEARCH(" PA "," "&SUBSTITUTE($I88,","," ")&" ")),ISNUMBER($L88)),$L88,"") | AF88: =IF(AND(ISNUMBER(SEARCH(" PO "," "&SUBSTITUTE($I88,","," ")&" ")),ISNUMBER($L88)),$L88,"") | AG88: =IF(AND(ISNUMBER(SEARCH(" MFA "," "&SUBSTITUTE($I88,","," ")&" ")),ISNUMBER($L88)),$L88,"") | AH88: =IF(AND(ISNUMBER(SEARCH(" RAP "," "&SUBSTITUTE($I88,","," ")&" ")),ISNUMBER($L88)),$L88,"") | AI88: =IF(AND(ISNUMBER(SEARCH(" AC "," "&SUBSTITUTE($I88,","," ")&" ")),ISNUMBER($L88)),$L88,"") | AJ88: =IF(AND(ISNUMBER(SEARCH(" MAC "," "&SUBSTITUTE($I88,","," ")&" ")),ISNUMBER($L88)),$L88,"") | AK88: =IF(AND(ISNUMBER(SEARCH(" UAH "," "&SUBSTITUTE($I88,","," ")&" ")),ISNUMBER($L88)),$L88,"") | AL88: =IF(AND(ISNUMBER(SEARCH(" RB "," "&SUBSTITUTE($I88,","," ")&" ")),ISNUMBER($L88)),$L88,"")
